Workbook

Sheet Inputs
A1: ZAN FINANCIAL MODEL النموذج المالي لزان
B2: Model Inputs & Assumptions | D2: المدخلات والافتراضات
A4: 1 GENERAL ASSUMPTIONS الافتراضات العامة
B5: Project Name | C5: ZAN Waterfront – Jazan
B6: Location | C6: Jazan, North Corniche
B7: Model Start Year | C7: 2026
B8: Projection Horizon (years) | C8: 50
B9: Currency | C9: SAR
A11: 2 RENT ASSUMPTIONS افتراضات الإيجار
B12: Annual Rent Escalation (%) | C12: 0.0075
B13: Flexible Block Efficiency % | C13: 0.85
B14: Flexible Block Lease Rate (SAR/m²) | C14: 700
B15: Flexible Block Cost/m² (SAR) | C15: 3500
A17: 3 LAND RENT إيجار الأرض
B18: Annual Land Rent (SAR) | C18: 6000000
B19: Escalation Every N Years | C19: 5
B20: Land Rent Escalation (%) | C20: 0.05
B21: Grace Period (years) | C21: 5
B22: Land Rent Term (years) | C22: 50
A24: 4 CAPEX ASSUMPTIONS افتراضات التكاليف
B25: Soft Cost (%) | C25: 0.1
B26: Contingency (%) | C26: 0.05
A28: 5 SCENARIO SELECTOR اختيار السيناريو
B29: Active Scenario | C29: Base Case
B30: Options: | C30: Base Case
C31: CAPEX +10%
C32: Rent -10%
C33: Delay +6 months
C34: Escalation +0.5%
C35: Escalation -0.5%
B37: CAPEX Multiplier (calculated) | C37: =IF(C29="CAPEX +10%",1.1,1)
B38: Rent Multiplier (calculated) | C38: =IF(C29="Rent -10%",0.9,1)
B39: Delay (months) | C39: =IF(C29="Delay +6 months",6,0)
B40: Escalation Adjustment | C40: =IF(C29="Escalation +0.5%",0.005,IF(C29="Escalation -0.5%",-0.005,0))
B41: Effective Rent Escalation | C41: =C12+C40
A43: 6 PHASES & PHASING المراحل
B44: Phase / المرحلة | C44: Start Year Offset | D44: Phase Footprint | E44: Land Rent Alloc. %
B45: ZAN 1 | C45: 2 | D45: =SUMPRODUCT((Program!A4:A50=B45)*(Program!G4:G50)) | E45: =IF(D$60=0,0,D45/D$60)
B46: ZAN 2 | C46: 3 | D46: =SUMPRODUCT((Program!A4:A50=B46)*(Program!G4:G50)) | E46: =IF(D$60=0,0,D46/D$60)
B47: ZAN 3 | C47: 4 | D47: =SUMPRODUCT((Program!A4:A50=B47)*(Program!G4:G50)) | E47: =IF(D$60=0,0,D47/D$60)
B48: ZAN 4 | C48: 5 | D48: =SUMPRODUCT((Program!A4:A50=B48)*(Program!G4:G50)) | E48: =IF(D$60=0,0,D48/D$60)
B49: ZAN 5 | C49: 7 | D49: =SUMPRODUCT((Program!A4:A50=B49)*(Program!G4:G50)) | E49: =IF(D$60=0,0,D49/D$60)
B50: ZAN 6 | C50: 7 | D50: =SUMPRODUCT((Program!A4:A50=B50)*(Program!G4:G50)) | E50: =IF(D$60=0,0,D50/D$60)
B51: ZAN 7 | C51: 0 | D51: =SUMPRODUCT((Program!A4:A50=B51)*(Program!G4:G50)) | E51: =IF(D$60=0,0,D51/D$60)
B52: ZAN 8 | C52: 0 | D52: =SUMPRODUCT((Program!A4:A50=B52)*(Program!G4:G50)) | E52: =IF(D$60=0,0,D52/D$60)
B53: ZAN 9 | C53: 0 | D53: =SUMPRODUCT((Program!A4:A50=B53)*(Program!G4:G50)) | E53: =IF(D$60=0,0,D53/D$60)
B54: ZAN 10 | C54: 0 | D54: =SUMPRODUCT((Program!A4:A50=B54)*(Program!G4:G50)) | E54: =IF(D$60=0,0,D54/D$60)
B55: ZAN 11 | C55: 0 | D55: =SUMPRODUCT((Program!A4:A50=B55)*(Program!G4:G50)) | E55: =IF(D$60=0,0,D55/D$60)
B56: ZAN 12 | C56: 0 | D56: =SUMPRODUCT((Program!A4:A50=B56)*(Program!G4:G50)) | E56: =IF(D$60=0,0,D56/D$60)
B57: ZAN 13 | C57: 0 | D57: =SUMPRODUCT((Program!A4:A50=B57)*(Program!G4:G50)) | E57: =IF(D$60=0,0,D57/D$60)
B58: ZAN 14 | C58: 0 | D58: =SUMPRODUCT((Program!A4:A50=B58)*(Program!G4:G50)) | E58: =IF(D$60=0,0,D58/D$60)
B59: ZAN 15 | C59: 0 | D59: =SUMPRODUCT((Program!A4:A50=B59)*(Program!G4:G50)) | E59: =IF(D$60=0,0,D59/D$60)
B60: Total | D60: =SUM(D45:D59) | E60: =SUM(E45:E59)
A62: 7 LAND CAPITALIZATION تقييم حق المنفعة
B63: Total Land Area (m²) | C63: 302473
B64: Capitalization of Leasehold Right (SAR) | C64: =C63*1000
B66: Phase | C66: Footprint | D66: Alloc. % | E66: Capitalization (SAR)
B67: =B45 | C67: =D45 | D67: =E45 | E67: =D67*$C$64
B68: =B46 | C68: =D46 | D68: =E46 | E68: =D68*$C$64
B69: =B47 | C69: =D47 | D69: =E47 | E69: =D69*$C$64
B70: =B48 | C70: =D48 | D70: =E48 | E70: =D70*$C$64
B71: =B49 | C71: =D49 | D71: =E49 | E71: =D71*$C$64
B72: =B50 | C72: =D50 | D72: =E50 | E72: =D72*$C$64
B73: =B51 | C73: =D51 | D73: =E51 | E73: =D73*$C$64
B74: =B52 | C74: =D52 | D74: =E52 | E74: =D74*$C$64
B75: =B53 | C75: =D53 | D75: =E53 | E75: =D75*$C$64
B76: =B54 | C76: =D54 | D76: =E54 | E76: =D76*$C$64
B77: =B55 | C77: =D55 | D77: =E55 | E77: =D77*$C$64
B78: =B56 | C78: =D56 | D78: =E56 | E78: =D78*$C$64
... B81: =B59 | C81: =D59 | D81: =E59 | E81: =D81*$C$64
B82: Total | C82: =SUM(C67:C81) | D82: =SUM(D67:D81) | E82: =SUM(E67:E81)
A84: 8 DEBT PARAMETERS معايير الدين
B85: Max Debt (% of Dev Cost incl. Land) | C85: 0.7
A87: 9 LAND ACQUISITION TYPE نوع تملك الأرض
B88: Land Type | C88: Lease | D88: نوع تملك الأرض
B89: Options: | C89: Lease
C90: Purchase
C91: Partner
C92: BOT
B93: Land Purchase Price (SAR) | C93: 0 | D93: سعر شراء الأرض
B94: Partner Land Equity % | C94: 0 | D94: نسبة ملكية شريك الأرض
B95: BOT Operation Period (years) | C95: 0 | D95: فترة التشغيل BOT
B97: Effective Land Cost (calculated) | C97: =IF(C88="Purchase",C93,IF(C88="Lease",C64,0))
B98: Annual Land Cost (calculated) | C98: =IF(C88="Lease",C18,0)
A100: 10 FINANCING MODE هيكل التمويل
B101: Financing Mode | C101: Fund | D101: نمط التمويل
B102: Options: | C102: Self
C103: Bank
C104: Fund
C105: JV
A106: 11 EXIT STRATEGY استراتيجية التخارج
B107: Exit Type | C107: Sale | D107: نوع التخارج
B108: Options: | C108: Sale
C109: Hold
C110: REIT
C111: Refinance
C112: Partial
B113: Exit Year | C113: 2032
B114: Exit Multiple (x rent) | C114: 10
B115: Exit Cost % | C115: 0.02
...

Sheet Program
A1: ASSET PROGRAM TABLE جدول الأصول
A3: Phase المرحلة | B3: Category التصنيف | C3: Asset Name اسم الأصل | D3: Code الرمز | E3: Notes ملاحظات | F3: Plot Area مساحة القطعة | G3: Bldg Footprint مساحة الدور | H3: GFA إجمالي المساحات | I3: Rev Type نوع الإيراد | J3: Eff % الكفاءة | K3: Leasable Area المساحة التأجيرية | L3: Lease Rate إيجار المتر | M3: Op EBITDA إيراد تشغيلي | N3: Escalation % الزيادة السنوية | O3: Ramp Up Yrs سنوات النمو | P3: Stab Occ % إشغال مستقر | Q3: Cost/m² تكلفة المتر | R3: Constr Start بداية البناء | S3: Constr Duration مدة البناء (شهر) | T3: Total CAPEX إجمالي التكلفة | U3: Constr Start Yr سنة بداية البناء | V3: Revenue Start Yr سنة بداية الإيراد | W3: Base Revenue الإيراد الأساسي | X3: Ramp Target هدف النمو
A4: ZAN 1 | B4: Hospitality | C4: Hotel | D4: H | E4: Anchor (Hotel) | F4: 5133 | G4: 2072 | H4: 16577 | I4: Operating | J4: 0 | K4: =H4*J4 | L4: 0 | M4: =Operating_PL!C44 | N4: =Inputs!C41 | O4: 4 | P4: 1 | Q4: 8000 | R4: =IFERROR(VLOOKUP(A4,Inputs!B45:C59,2,FALSE())+ROUND(Inputs!C39/12,0),0) | S4: 36 | T4: =H4*Q4*(1+Inputs!$C$25)*(1+Inputs!$C$26)*Inputs!$C$37 | U4: =Inputs!$C$7+R4 | V4: =IF(S4=0,U4,U4+CEILING(S4/12,1)) | W4: =IF(I4="Lease",K4*L4,IF(I4="Operating",M4,0)) | X4: =IF(I4="Lease",P4,1)
A5: ZAN 1 | B5: Retail | C5: Retail - Sport Complex | D5: S | F5: 6000 | G5: 6000 | H5: 6000 | I5: Lease | J5: 1 | K5: =H5*J5 | L5: 173 | M5: =IF(I5="Operating",0,0) | N5: =Inputs!C41 | O5: 3 | P5: 0.9 | Q5: 240 | R5: =IFERROR(VLOOKUP(A5,Inputs!B45:C59,2,FALSE())+ROUND(Inputs!C39/12,0),0) | S5: 6 | T5: =H5*Q5*(1+Inputs!$C$25)*(1+Inputs!$C$26)*Inputs!$C$37 | U5: =Inputs!$C$7+R5 | V5: =IF(S5=0,U5,U5+CEILING(S5/12,1)) | W5: =IF(I5="Lease",K5*L5,IF(I5="Operating",M5,0)) | X5: =IF(I5="Lease",P5,1)
A6: ZAN 1 | B6: Utilities | C6: Parking & Landscaping ZAN1 | D6: (N/A) | E6: Parking & Landscaping | F6: =0 | G6: 0 | H6: =(Inputs!C63-Program!G34)*Inputs!E45 | I6: Lease | J6: 0 | K6: =H6*J6 | L6: 0 | M6: =IF(I6="Operating",0,0) | N6: =0 | O6: 0 | P6: 0 | Q6: 500 | R6: 4 | S6: 12 | T6: =H6*Q6*(1+Inputs!$C$25)*(1+Inputs!$C$26)*Inputs!$C$37 | U6: =Inputs!$C$7+R6 | V6: =IF(S6=0,U6,U6+CEILING(S6/12,1)) | W6: =IF(I6="Lease",K6*L6,IF(I6="Operating",M6,0)) | X6: =IF(I6="Lease",P6,1)
A7: ZAN 1 | B7: Retail | C7: Fuel Station | D7: F | E7: Shared utility | F7: 6920 | G7: 3586 | H7: 3586 | I7: Lease | J7: 0.3 | K7: =H7*J7 | L7: 900 | M7: =IF(I7="Operating",0,0) | N7: =Inputs!C41 | O7: 3 | P7: 0.9 | Q7: 1500 | R7: =IFERROR(VLOOKUP(A7,Inputs!B45:C59,2,FALSE())+ROUND(Inputs!C39/12,0),0) | S7: 12 | T7: =H7*Q7*(1+Inputs!$C$25)*(1+Inputs!$C$26)*Inputs!$C$37 | U7: =Inputs!$C$7+R7 | V7: =IF(S7=0,U7,U7+CEILING(S7/12,1)) | W7: =IF(I7="Lease",K7*L7,IF(I7="Operating",M7,0)) | X7: =IF(I7="Lease",P7,1)
A8: ZAN 1 | B8: Marina | C8: Marina Berths | D8: MAR | E8: Anchor | F8: 3000 | G8: 0 | H8: 2400 | I8: Operating | J8: 0 | K8: =H8*J8 | L8: 0 | M8: =Operating_PL!C80 | N8: =Inputs!C41 | O8: 4 | P8: 0.9 | Q8: 16000 | R8: 4 | S8: 12 | T8: =H8*Q8*(1+Inputs!$C$25)*(1+Inputs!$C$26)*Inputs!$C$37 | U8: =Inputs!$C$7+R8 | V8: =IF(S8=0,U8,U8+CEILING(S8/12,1)) | W8: =IF(I8="Lease",K8*L8,IF(I8="Operating",M8,0)) | X8: =IF(I8="Lease",P8,1)
A9: ZAN 1 | B9: Retail | C9: Marina Mall | D9: C1 | E9: Anchor (Mall) | F9: 28947 | G9: 20840 | H9: 31260 | I9: Lease | J9: 0.8 | K9: =H9*J9 | L9: 2100 | M9: =IF(I9="Operating",0,0) | N9: =Inputs!C41 | O9: 3 | P9: 0.9 | Q9: 3900 | R9: =IFERROR(VLOOKUP(A9,Inputs!B45:C59,2,FALSE())+ROUND(Inputs!C39/12,0),0) | S9: 30 | T9: =H9*Q9*(1+Inputs!$C$25)*(1+Inputs!$C$26)*Inputs!$C$37 | U9: =Inputs!$C$7+R9 | V9: =IF(S9=0,U9,U9+CEILING(S9/12,1)) | W9: =IF(I9="Lease",K9*L9,IF(I9="Operating",M9,0)) | X9: =IF(I9="Lease",P9,1)
A10: ZAN 2 | B10: Retail | C10: Seafront Mall | D10: C2 | E10: Supporting anchor | F10: 4718 | G10: 4511 | H10: 8918 | I10: Lease | J10: 0.9 | K10: =H10*J10 | L10: 2000 | M10: =IF(I10="Operating",0,0) | N10: =Inputs!C41 | O10: 3 | P10: 0.9 | Q10: 3500 | R10: =IFERROR(VLOOKUP(A10,Inputs!B45:C59,2,FALSE())+ROUND(Inputs!C39/12,0),0) | S10: 24 | T10: =H10*Q10*(1+Inputs!$C$25)*(1+Inputs!$C$26)*Inputs!$C$37 | U10: =Inputs!$C$7+R10 | V10: =IF(S10=0,U10,U10+CEILING(S10/12,1)) | W10: =IF(I10="Lease",K10*L10,IF(I10="Operating",M10,0)) | X10: =IF(I10="Lease",P10,1)
A11: ZAN 2 | B11: Office | C11: Flexible Block (Office) | D11: R1 | E11: Flexible | F11: 4781 | G11: 2367 | H11: 11168 | I11: Lease | J11: =Inputs!C13 | K11: =H11*J11 | L11: 850 | M11: =IF(I11="Operating",0,0) | N11: =Inputs!C41 | O11: 3 | P11: 0.9 | Q11: 2600 | R11: =IFERROR(VLOOKUP(A11,Inputs!B45:C59,2,FALSE())+ROUND(Inputs!C39/12,0),0) | S11: 30 | T11: =H11*Q11*(1+Inputs!$C$25)*(1+Inputs!$C$26)*Inputs!$C$37 | U11: =Inputs!$C$7+R11 | V11: =IF(S11=0,U11,U11+CEILING(S11/12,1)) | W11: =IF(I11="Lease",K11*L11,IF(I11="Operating",M11,0)) | X11: =IF(I11="Lease",P11,1)
A12: ZAN 2 | B12: Hospitality | C12: Resort | D12: Resort | E12: Core resort | F12: 33000 | G12: 15877 | H12: 16296 | I12: Operating | J12: 0 | K12: =H12*J12 | L12: 0 | M12: =Operating_PL!D44 | N12: =Inputs!C41 | O12: 4 | P12: 0.9 | Q12: 10000 | R12: =IFERROR(VLOOKUP(A12,Inputs!B45:C59,2,FALSE())+ROUND(Inputs!C39/12,0),0) | S12: 42 | T12: =H12*Q12*(1+Inputs!$C$25)*(1+Inputs!$C$26)*Inputs!$C$37 | U12: =Inputs!$C$7+R12 | V12: =IF(S12=0,U12,U12+CEILING(S12/12,1)) | W12: =IF(I12="Lease",K12*L12,IF(I12="Operating",M12,0)) | X12: =IF(I12="Lease",P12,1)
A13: ZAN 2 | B13: Retail | C13: Supermarket | D13: C4 | E13: Daily needs | F13: 2023 | G13: 2023 | H13: 4044 | I13: Lease | J13: 0.9 | K13: =H13*J13 | L13: 500 | M13: =IF(I13="Operating",0,0) | N13: =Inputs!C41 | O13: 2 | P13: 0.9 | Q13: 1500 | R13: =IFERROR(VLOOKUP(A13,Inputs!B45:C59,2,FALSE())+ROUND(Inputs!C39/12,0),0) | S13: 18 | T13: =H13*Q13*(1+Inputs!$C$25)*(1+Inputs!$C$26)*Inputs!$C$37 | U13: =Inputs!$C$7+R13 | V13: =IF(S13=0,U13,U13+CEILING(S13/12,1)) | W13: =IF(I13="Lease",K13*L13,IF(I13="Operating",M13,0)) | X13: =IF(I13="Lease",P13,1)
A14: ZAN 2 | B14: Retail | C14: Shops / Cafes | D14: C5 | E14: F&B support | F14: 7439 | G14: 1167 | H14: 1167 | I14: Lease | J14: 0.9 | K14: =H14*J14 | L14: 2000 | M14: =IF(I14="Operating",0,0) | N14: =Inputs!C41 | O14: 2 | P14: 0.9 | Q14: 3000 | R14: =IFERROR(VLOOKUP(A14,Inputs!B45:C59,2,FALSE())+ROUND(Inputs!C39/12,0),0) | S14: 18 | T14: =H14*Q14*(1+Inputs!$C$25)*(1+Inputs!$C$26)*Inputs!$C$37 | U14: =Inputs!$C$7+R14 | V14: =IF(S14=0,U14,U14+CEILING(S14/12,1)) | W14: =IF(I14="Lease",K14*L14,IF(I14="Operating",M14,0)) | X14: =IF(I14="Lease",P14,1)
A15: ZAN 2 | B15: Retail | C15: Shopping Area | D15: C3 | E15: Convenience | F15: 1567 | G15: 917 | H15: 3668 | I15: Lease | J15: 0.9 | K15: =H15*J15 | L15: 2000 | M15: =IF(I15="Operating",0,0) | N15: =Inputs!C41 | O15: 2 | P15: 0.9 | Q15: 3000 | R15: =IFERROR(VLOOKUP(A15,Inputs!B45:C59,2,FALSE())+ROUND(Inputs!C39/12,0),0) | S15: 18 | T15: =H15*Q15*(1+Inputs!$C$25)*(1+Inputs!$C$26)*Inputs!$C$37 | U15: =Inputs!$C$7+R15 | V15: =IF(S15=0,U15,U15+CEILING(S15/12,1)) | W15: =IF(I15="Lease",K15*L15,IF(I15="Operating",M15,0)) | X15: =IF(I15="Lease",P15,1)
A16: ZAN 2 | B16: Retail | C16: Shops / Cafes | D16: C10 | E16: F&B support | F16: 6990 | G16: 1167 | H16: 1167 | I16: Lease | J16: 0.9 | K16: =H16*J16 | L16: 2000 | M16: =IF(I16="Operating",0,0) | N16: =Inputs!C41 | O16: 2 | P16: 0.9 | Q16: 3000 | R16: =IFERROR(VLOOKUP(A16,Inputs!B45:C59,2,FALSE())+ROUND(Inputs!C39/12,0),0) | S16: 18 | T16: =H16*Q16*(1+Inputs!$C$25)*(1+Inputs!$C$26)*Inputs!$C$37 | U16: =Inputs!$C$7+R16 | V16: =IF(S16=0,U16,U16+CEILING(S16/12,1)) | W16: =IF(I16="Lease",K16*L16,IF(I16="Operating",M16,0)) | X16: =IF(I16="Lease",P16,1)
A17: ZAN 2 | B17: Utilities | C17: Parking & Landscaping ZAN2 | D17: (N/A) | E17: Parking & Landscaping | F17: =0 | G17: 0 | H17: =(Inputs!C63-Program!G34)*Inputs!E46 | I17: Lease | J17: 0 | K17: =H17*J17 | L17: 0 | M17: =IF(I17="Operating",0,0) | N17: =0 | O17: 0 | P17: 0 | Q17: 500 | R17: 4 | S17: 12 | T17: =H17*Q17*(1+Inputs!$C$25)*(1+Inputs!$C$26)*Inputs!$C$37 | U17: =Inputs!$C$7+R17 | V17: =IF(S17=0,U17,U17+CEILING(S17/12,1)) | W17: =IF(I17="Lease",K17*L17,IF(I17="Operating",M17,0)) | X17: =IF(I17="Lease",P17,1)
A18: ZAN 2 | B18: Office | C18: Office Block | D18: O1 | E18: Office | F18: 5497 | G18: 2710 | H18: 16429 | I18: Lease | J18: 0.9 | K18: =H18*J18 | L18: 900 | M18: =IF(I18="Operating",0,0) | N18: =Inputs!C41 | O18: 3 | P18: 0.9 | Q18: 2600 | R18: =IFERROR(VLOOKUP(A18,Inputs!B45:C59,2,FALSE())+ROUND(Inputs!C39/12,0),0) | S18: 30 | T18: =H18*Q18*(1+Inputs!$C$25)*(1+Inputs!$C$26)*Inputs!$C$37 | U18: =Inputs!$C$7+R18 | V18: =IF(S18=0,U18,U18+CEILING(S18/12,1)) | W18: =IF(I18="Lease",K18*L18,IF(I18="Operating",M18,0)) | X18: =IF(I18="Lease",P18,1)
A19: ZAN 2 | B19: Flexible | C19: Flexible Block (Residential) | D19: R3 | E19: Flexible | F19: 6664 | G19: 3066 | H19: 17153 | I19: Lease | J19: =Inputs!C13 | K19: =H19*J19 | L19: 750 | M19: =IF(I19="Operating",0,0) | N19: =Inputs!C41 | O19: 3 | P19: 0.9 | Q19: 3000 | R19: =IFERROR(VLOOKUP(A19,Inputs!B45:C59,2,FALSE())+ROUND(Inputs!C39/12,0),0) | S19: 30 | T19: =H19*Q19*(1+Inputs!$C$25)*(1+Inputs!$C$26)*Inputs!$C$37 | U19: =Inputs!$C$7+R19 | V19: =IF(S19=0,U19,U19+CEILING(S19/12,1)) | W19: =IF(I19="Lease",K19*L19,IF(I19="Operating",M19,0)) | X19: =IF(I19="Lease",P19,1)
A20: ZAN 2 | B20: Flexible | C20: Flexible Block | D20: R4 | E20: Flexible | F20: 7558 | G20: 3310 | H20: 19316 | I20: Lease | J20: =Inputs!C13 | K20: =H20*J20 | L20: 800 | M20: =IF(I20="Operating",0,0) | N20: =Inputs!C41 | O20: 3 | P20: 0.9 | Q20: 2500 | R20: =IFERROR(VLOOKUP(A20,Inputs!B45:C59,2,FALSE())+ROUND(Inputs!C39/12,0),0) | S20: 30 | T20: =H20*Q20*(1+Inputs!$C$25)*(1+Inputs!$C$26)*Inputs!$C$37 | U20: =Inputs!$C$7+R20 | V20: =IF(S20=0,U20,U20+CEILING(S20/12,1)) | W20: =IF(I20="Lease",K20*L20,IF(I20="Operating",M20,0)) | X20: =IF(I20="Lease",P20,1)
A21: ZAN 3 | B21: Residential | C21: Flexible Block | D21: R2 | E21: Flexible | F21: 6031 | G21: 2867 | H21: 14453 | I21: Lease | J21: =Inputs!C13 | K21: =H21*J21 | L21: 800 | M21: =IF(I21="Operating",0,0) | N21: =Inputs!C41 | O21: 3 | P21: 0.9 | Q21: 2500 | R21: =IFERROR(VLOOKUP(A21,Inputs!B45:C59,2,FALSE())+ROUND(Inputs!C39/12,0),0) | S21: 30 | T21: =H21*Q21*(1+Inputs!$C$25)*(1+Inputs!$C$26)*Inputs!$C$37 | U21: =Inputs!$C$7+R21 | V21: =IF(S21=0,U21,U21+CEILING(S21/12,1)) | W21: =IF(I21="Lease",K21*L21,IF(I21="Operating",M21,0)) | X21: =IF(I21="Lease",P21,1)
A22: ZAN 3 | B22: Cultural | C22: Multi-Purpose Hall | D22: M | E22: Events/MICE | F22: 5376 | G22: 1624 | H22: 3248 | I22: Lease | J22: 1 | K22: =H22*J22 | L22: 900 | M22: =IF(I22="Operating",0,0) | N22: =Inputs!C41 | O22: 3 | P22: 0.9 | Q22: 7500 | R22: =IFERROR(VLOOKUP(A22,Inputs!B45:C59,2,FALSE())+ROUND(Inputs!C39/12,0),0) | S22: 24 | T22: =H22*Q22*(1+Inputs!$C$25)*(1+Inputs!$C$26)*Inputs!$C$37 | U22: =Inputs!$C$7+R22 | V22: =IF(S22=0,U22,U22+CEILING(S22/12,1)) | W22: =IF(I22="Lease",K22*L22,IF(I22="Operating",M22,0)) | X22: =IF(I22="Lease",P22,1)
A23: ZAN 3 | B23: Open Space | C23: Unallocated / Open Area | D23: Area | E23: Future plots | F23: 16642 | G23: 0 | H23: =F23*0.01 | I23: Lease | J23: 1 | K23: =H23*J23 | L23: 15000 | M23: =IF(I23="Operating",0,0) | N23: =Inputs!C41 | O23: 1 | P23: 1 | Q23: 450 | R23: =IFERROR(VLOOKUP(A23,Inputs!B45:C59,2,FALSE())+ROUND(Inputs!C39/12,0),0) | S23: 12 | T23: =H23*Q23*(1+Inputs!$C$25)*(1+Inputs!$C$26)*Inputs!$C$37 | U23: =Inputs!$C$7+R23 | V23: =IF(S23=0,U23,U23+CEILING(S23/12,1)) | W23: =IF(I23="Lease",K23*L23,IF(I23="Operating",M23,0)) | X23: =IF(I23="Lease",P23,1)
A24: ZAN 3 | B24: Retail | C24: Shops / Cafes | D24: C6 | E24: Secondary | F24: 7121 | G24: 1005 | H24: 1005 | I24: Lease | J24: 0.9 | K24: =H24*J24 | L24: 2200 | M24: =IF(I24="Operating",0,0) | N24: =Inputs!C41 | O24: 2 | P24: 0.9 | Q24: 3000 | R24: =IFERROR(VLOOKUP(A24,Inputs!B45:C59,2,FALSE())+ROUND(Inputs!C39/12,0),0) | S24: 18 | T24: =H24*Q24*(1+Inputs!$C$25)*(1+Inputs!$C$26)*Inputs!$C$37 | U24: =Inputs!$C$7+R24 | V24: =IF(S24=0,U24,U24+CEILING(S24/12,1)) | W24: =IF(I24="Lease",K24*L24,IF(I24="Operating",M24,0)) | X24: =IF(I24="Lease",P24,1)
A25: ZAN 3 | B25: Retail | C25: Small Market | D25: C8 | E25: Micro retail | F25: 616 | G25: 328 | H25: 314 | I25: Lease | J25: 0.9 | K25: =H25*J25 | L25: 2000 | M25: =IF(I25="Operating",0,0) | N25: =Inputs!C41 | O25: 2 | P25: 0.9 | Q25: 2000 | R25: =IFERROR(VLOOKUP(A25,Inputs!B45:C59,2,FALSE())+ROUND(Inputs!C39/12,0),0) | S25: 18 | T25: =H25*Q25*(1+Inputs!$C$25)*(1+Inputs!$C$26)*Inputs!$C$37 | U25: =Inputs!$C$7+R25 | V25: =IF(S25=0,U25,U25+CEILING(S25/12,1)) | W25: =IF(I25="Lease",K25*L25,IF(I25="Operating",M25,0)) | X25: =IF(I25="Lease",P25,1)
A26: ZAN 3 | B26: Amenity | C26: Small Pavilions / Shops | D26: A1 | E26: Activation | F26: 15371 | G26: 4251 | H26: 3791 | I26: Lease | J26: 0.9 | K26: =H26*J26 | L26: 2200 | M26: =IF(I26="Operating",0,0) | N26: =Inputs!C41 | O26: 2 | P26: 0.9 | Q26: 2000 | R26: =IFERROR(VLOOKUP(A26,Inputs!B45:C59,2,FALSE())+ROUND(Inputs!C39/12,0),0) | S26: 18 | T26: =H26*Q26*(1+Inputs!$C$25)*(1+Inputs!$C$26)*Inputs!$C$37 | U26: =Inputs!$C$7+R26 | V26: =IF(S26=0,U26,U26+CEILING(S26/12,1)) | W26: =IF(I26="Lease",K26*L26,IF(I26="Operating",M26,0)) | X26: =IF(I26="Lease",P26,1)
A27: ZAN 3 | B27: Flexible | C27: Flexible Block | D27: R5 | E27: Flexible | F27: 6016 | G27: 4321 | H27: 25927 | I27: Lease | J27: =Inputs!C13 | K27: =H27*J27 | L27: 800 | M27: =IF(I27="Operating",0,0) | N27: =Inputs!C41 | O27: 3 | P27: 0.9 | Q27: 2800 | R27: =IFERROR(VLOOKUP(A27,Inputs!B45:C59,2,FALSE())+ROUND(Inputs!C39/12,0),0) | S27: 30 | T27: =H27*Q27*(1+Inputs!$C$25)*(1+Inputs!$C$26)*Inputs!$C$37 | U27: =Inputs!$C$7+R27 | V27: =IF(S27=0,U27,U27+CEILING(S27/12,1)) | W27: =IF(I27="Lease",K27*L27,IF(I27="Operating",M27,0)) | X27: =IF(I27="Lease",P27,1)
A28: ZAN 3 | B28: Retail | C28: Shops / Cafes | D28: C7 | E28: Secondary | F28: 11401 | G28: 1310 | H28: 1310 | I28: Lease | J28: 0.9 | K28: =H28*J28 | L28: 2000 | M28: =IF(I28="Operating",0,0) | N28: =Inputs!C41 | O28: 2 | P28: 0.9 | Q28: 3000 | R28: =IFERROR(VLOOKUP(A28,Inputs!B45:C59,2,FALSE())+ROUND(Inputs!C39/12,0),0) | S28: 18 | T28: =H28*Q28*(1+Inputs!$C$25)*(1+Inputs!$C$26)*Inputs!$C$37 | U28: =Inputs!$C$7+R28 | V28: =IF(S28=0,U28,U28+CEILING(S28/12,1)) | W28: =IF(I28="Lease",K28*L28,IF(I28="Operating",M28,0)) | X28: =IF(I28="Lease",P28,1)
A29: ZAN 3 | B29: Retail | C29: Small Market | D29: C9 | E29: Micro retail | F29: 619 | G29: 362 | H29: 347 | I29: Lease | J29: 0.9 | K29: =H29*J29 | L29: 2000 | M29: =IF(I29="Operating",0,0) | N29: =Inputs!C41 | O29: 2 | P29: 0.9 | Q29: 2000 | R29: =IFERROR(VLOOKUP(A29,Inputs!B45:C59,2,FALSE())+ROUND(Inputs!C39/12,0),0) | S29: 18 | T29: =H29*Q29*(1+Inputs!$C$25)*(1+Inputs!$C$26)*Inputs!$C$37 | U29: =Inputs!$C$7+R29 | V29: =IF(S29=0,U29,U29+CEILING(S29/12,1)) | W29: =IF(I29="Lease",K29*L29,IF(I29="Operating",M29,0)) | X29: =IF(I29="Lease",P29,1)
A30: ZAN 3 | B30: Residential | C30: Flexible Block (Branded) | D30: R6 | E30: Flexible | F30: 7411 | G30: 7430 | H30: 44218 | I30: Lease | J30: =Inputs!C13 | K30: =H30*J30 | L30: 1200 | M30: =IF(I30="Operating",0,0) | N30: =Inputs!C41 | O30: 3 | P30: 0.9 | Q30: 4500 | R30: =IFERROR(VLOOKUP(A30,Inputs!B45:C59,2,FALSE())+ROUND(Inputs!C39/12,0),0) | S30: 30 | T30: =H30*Q30*(1+Inputs!$C$25)*(1+Inputs!$C$26)*Inputs!$C$37 | U30: =Inputs!$C$7+R30 | V30: =IF(S30=0,U30,U30+CEILING(S30/12,1)) | W30: =IF(I30="Lease",K30*L30,IF(I30="Operating",M30,0)) | X30: =IF(I30="Lease",P30,1)
A31: ZAN 3 | B31: Retail | C31: Flexible Block | D31: R7 | E31: Branded/Flex | F31: 3806 | G31: 1774 | H31: =G31*2.5 | I31: Lease | J31: =Inputs!C13 | K31: =H31*J31 | L31: 800 | M31: =IF(I31="Operating",0,0) | N31: =Inputs!C41 | O31: 3 | P31: 0.9 | Q31: 2500 | R31: =IFERROR(VLOOKUP(A31,Inputs!B45:C59,2,FALSE())+ROUND(Inputs!C39/12,0),0) | S31: 30 | T31: =H31*Q31*(1+Inputs!$C$25)*(1+Inputs!$C$26)*Inputs!$C$37 | U31: =Inputs!$C$7+R31 | V31: =IF(S31=0,U31,U31+CEILING(S31/12,1)) | W31: =IF(I31="Lease",K31*L31,IF(I31="Operating",M31,0)) | X31: =IF(I31="Lease",P31,1)
A32: ZAN 3 | B32: Marina | C32: Yacht Club | D32: Yacht Club | E32: Marina anchor | F32: 3186 | G32: 1474 | H32: 2400 | I32: Lease | J32: 0.85 | K32: =H32*J32 | L32: 950 | M32: =IF(I32="Operating",0,0) | N32: =Inputs!C41 | O32: 3 | P32: 0.9 | Q32: 6500 | R32: =IFERROR(VLOOKUP(A32,Inputs!B45:C59,2,FALSE())+ROUND(Inputs!C39/12,0),0) | S32: 30 | T32: =H32*Q32*(1+Inputs!$C$25)*(1+Inputs!$C$26)*Inputs!$C$37 | U32: =Inputs!$C$7+R32 | V32: =IF(S32=0,U32,U32+CEILING(S32/12,1)) | W32: =IF(I32="Lease",K32*L32,IF(I32="Operating",M32,0)) | X32: =IF(I32="Lease",P32,1)
A33: ZAN 3 | B33: Utilities | C33: Parking & Landscaping ZAN3 | D33: (N/A) | E33: Parking & Landscaping | F33: =0 | G33: 0 | H33: =(Inputs!C63-Program!G34)*Inputs!E47 | I33: Lease | J33: 0 | K33: =H33*J33 | L33: 0 | M33: =IF(I33="Operating",0,0) | N33: =0 | O33: 0 | P33: 0 | Q33: 500 | R33: 4 | S33: 12 | T33: =H33*Q33*(1+Inputs!$C$25)*(1+Inputs!$C$26)*Inputs!$C$37 | U33: =Inputs!$C$7+R33 | V33: =IF(S33=0,U33,U33+CEILING(S33/12,1)) | W33: =IF(I33="Lease",K33*L33,IF(I33="Operating",M33,0)) | X33: =IF(I33="Lease",P33,1)
C34: TOTAL | F34: =SUM(F4:F33) | G34: =SUM(G4:G33) | H34: =SUM(H4:H33) | K34: =SUM(K4:K33) | T34: =SUM(T4:T33)

Sheet CAPEX
A1: CAPEX SCHEDULE جدول توزيع التكاليف
A3: # | B3: Asset | C3: Phase | D3: Total | E3: =$C63+0 | F3: =$C63+1 | G3: =$C63+2 | H3: =$C63+3 | I3: =$C63+4 | J3: =$C63+5 | K3: =$C63+6 | L3: =$C63+7 | M3: =$C63+8 | N3: =$C63+9 | O3: =$C63+10 | P3: =$C63+11 | Q3: =$C63+12 | R3: =$C63+13 | S3: =$C63+14 | T3: =$C63+15 | U3: =$C63+16 | V3: =$C63+17 | W3: =$C63+18 | X3: =$C63+19 | Y3: =$C63+20 | Z3: =$C63+21 | AA3: =$C63+22 | AB3: =$C63+23 | AC3: =$C63+24 | AD3: =$C63+25 | AE3: =$C63+26 | AF3: =$C63+27 | AG3: =$C63+28 | AH3: =$C63+29 | AI3: =$C63+30 | AJ3: =$C63+31 | AK3: =$C63+32 | AL3: =$C63+33 | AM3: =$C63+34 | AN3: =$C63+35 | AO3: =$C63+36 | AP3: =$C63+37 | AQ3: =$C63+38 | AR3: =$C63+39 | AS3: =$C63+40 | AT3: =$C63+41 | AU3: =$C63+42 | AV3: =$C63+43 | AW3: =$C63+44 | AX3: =$C63+45 | AY3: =$C63+46 | AZ3: =$C63+47 | BA3: =$C63+48 | BB3: =$C63+49
A4: =A66 | B4: =B66 | C4: =C66 | D4: =SUM(E4:BB4) | E4: =IF(OR(D66=0,E66=0,F66=0),0,IF(AND(E$3>=G66,E$3<H66),F66*MIN(12,E66-(E$3-G66)*12)/E66,0)) | F4: =IF(OR(D66=0,E66=0,F66=0),0,IF(AND(F$3>=G66,F$3<H66),F66*MIN(12,E66-(F$3-G66)*12)/E66,0)) | G4: =IF(OR(D66=0,E66=0,F66=0),0,IF(AND(G$3>=G66,G$3<H66),F66*MIN(12,E66-(G$3-G66)*12)/E66,0)) | H4: =IF(OR(D66=0,E66=0,F66=0),0,IF(AND(H$3>=G66,H$3<H66),F66*MIN(12,E66-(H$3-G66)*12)/E66,0)) | I4: =IF(OR(D66=0,E66=0,F66=0),0,IF(AND(I$3>=G66,I$3<H66),F66*MIN(12,E66-(I$3-G66)*12)/E66,0)) | J4: =IF(OR(D66=0,E66=0,F66=0),0,IF(AND(J$3>=G66,J$3<H66),F66*MIN(12,E66-(J$3-G66)*12)/E66,0)) | K4: =IF(OR(D66=0,E66=0,F66=0),0,IF(AND(K$3>=G66,K$3<H66),F66*MIN(12,E66-(K$3-G66)*12)/E66,0)) | L4: =IF(OR(D66=0,E66=0,F66=0),0,IF(AND(L$3>=G66,L$3<H66),F66*MIN(12,E66-(L$3-G66)*12)/E66,0)) | M4: =IF(OR(D66=0,E66=0,F66=0),0,IF(AND(M$3>=G66,M$3<H66),F66*MIN(12,E66-(M$3-G66)*12)/E66,0)) | N4: =IF(OR(D66=0,E66=0,F66=0),0,IF(AND(N$3>=G66,N$3<H66),F66*MIN(12,E66-(N$3-G66)*12)/E66,0)) | O4: =IF(OR(D66=0,E66=0,F66=0),0,IF(AND(O$3>=G66,O$3<H66),F66*MIN(12,E66-(O$3-G66)*12)/E66,0)) | P4: =IF(OR(D66=0,E66=0,F66=0),0,IF(AND(P$3>=G66,P$3<H66),F66*MIN(12,E66-(P$3-G66)*12)/E66,0)) | Q4: =IF(OR(D66=0,E66=0,F66=0),0,IF(AND(Q$3>=G66,Q$3<H66),F66*MIN(12,E66-(Q$3-G66)*12)/E66,0)) | R4: =IF(OR(D66=0,E66=0,F66=0),0,IF(AND(R$3>=G66,R$3<H66),F66*MIN(12,E66-(R$3-G66)*12)/E66,0)) | S4: =IF(OR(D66=0,E66=0,F66=0),0,IF(AND(S$3>=G66,S$3<H66),F66*MIN(12,E66-(S$3-G66)*12)/E66,0)) | T4: =IF(OR(D66=0,E66=0,F66=0),0,IF(AND(T$3>=G66,T$3<H66),F66*MIN(12,E66-(T$3-G66)*12)/E66,0)) | U4: =IF(OR(D66=0,E66=0,F66=0),0,IF(AND(U$3>=G66,U$3<H66),F66*MIN(12,E66-(U$3-G66)*12)/E66,0)) | V4: =IF(OR(D66=0,E66=0,F66=0),0,IF(AND(V$3>=G66,V$3<H66),F66*MIN(12,E66-(V$3-G66)*12)/E66,0)) | W4: =IF(OR(D66=0,E66=0,F66=0),0,IF(AND(W$3>=G66,W$3<H66),F66*MIN(12,E66-(W$3-G66)*12)/E66,0)) | X4: =IF(OR(D66=0,E66=0,F66=0),0,IF(AND(X$3>=G66,X$3<H66),F66*MIN(12,E66-(X$3-G66)*12)/E66,0)) | Y4: =IF(OR(D66=0,E66=0,F66=0),0,IF(AND(Y$3>=G66,Y$3<H66),F66*MIN(12,E66-(Y$3-G66)*12)/E66,0)) | Z4: =IF(OR(D66=0,E66=0,F66=0),0,IF(AND(Z$3>=G66,Z$3<H66),F66*MIN(12,E66-(Z$3-G66)*12)/E66,0)) | AA4: =IF(OR(D66=0,E66=0,F66=0),0,IF(AND(AA$3>=G66,AA$3<H66),F66*MIN(12,E66-(AA$3-G66)*12)/E66,0)) | AB4: =IF(OR(D66=0,E66=0,F66=0),0,IF(AND(AB$3>=G66,AB$3<H66),F66*MIN(12,E66-(AB$3-G66)*12)/E66,0)) | AC4: =IF(OR(D66=0,E66=0,F66=0),0,IF(AND(AC$3>=G66,AC$3<H66),F66*MIN(12,E66-(AC$3-G66)*12)/E66,0)) | AD4: =IF(OR(D66=0,E66=0,F66=0),0,IF(AND(AD$3>=G66,AD$3<H66),F66*MIN(12,E66-(AD$3-G66)*12)/E66,0)) | AE4: =IF(OR(D66=0,E66=0,F66=0),0,IF(AND(AE$3>=G66,AE$3<H66),F66*MIN(12,E66-(AE$3-G66)*12)/E66,0)) | AF4: =IF(OR(D66=0,E66=0,F66=0),0,IF(AND(AF$3>=G66,AF$3<H66),F66*MIN(12,E66-(AF$3-G66)*12)/E66,0)) | AG4: =IF(OR(D66=0,E66=0,F66=0),0,IF(AND(AG$3>=G66,AG$3<H66),F66*MIN(12,E66-(AG$3-G66)*12)/E66,0)) | AH4: =IF(OR(D66=0,E66=0,F66=0),0,IF(AND(AH$3>=G66,AH$3<H66),F66*MIN(12,E66-(AH$3-G66)*12)/E66,0)) | AI4: =IF(OR(D66=0,E66=0,F66=0),0,IF(AND(AI$3>=G66,AI$3<H66),F66*MIN(12,E66-(AI$3-G66)*12)/E66,0)) | AJ4: =IF(OR(D66=0,E66=0,F66=0),0,IF(AND(AJ$3>=G66,AJ$3<H66),F66*MIN(12,E66-(AJ$3-G66)*12)/E66,0)) | AK4: =IF(OR(D66=0,E66=0,F66=0),0,IF(AND(AK$3>=G66,AK$3<H66),F66*MIN(12,E66-(AK$3-G66)*12)/E66,0)) | AL4: =IF(OR(D66=0,E66=0,F66=0),0,IF(AND(AL$3>=G66,AL$3<H66),F66*MIN(12,E66-(AL$3-G66)*12)/E66,0)) | AM4: =IF(OR(D66=0,E66=0,F66=0),0,IF(AND(AM$3>=G66,AM$3<H66),F66*MIN(12,E66-(AM$3-G66)*12)/E66,0)) | AN4: =IF(OR(D66=0,E66=0,F66=0),0,IF(AND(AN$3>=G66,AN$3<H66),F66*MIN(12,E66-(AN$3-G66)*12)/E66,0)) | AO4: =IF(OR(D66=0,E66=0,F66=0),0,IF(AND(AO$3>=G66,AO$3<H66),F66*MIN(12,E66-(AO$3-G66)*12)/E66,0)) | AP4: =IF(OR(D66=0,E66=0,F66=0),0,IF(AND(AP$3>=G66,AP$3<H66),F66*MIN(12,E66-(AP$3-G66)*12)/E66,0)) | AQ4: =IF(OR(D66=0,E66=0,F66=0),0,IF(AND(AQ$3>=G66,AQ$3<H66),F66*MIN(12,E66-(AQ$3-G66)*12)/E66,0)) | AR4: =IF(OR(D66=0,E66=0,F66=0),0,IF(AND(AR$3>=G66,AR$3<H66),F66*MIN(12,E66-(AR$3-G66)*12)/E66,0)) | AS4: =IF(OR(D66=0,E66=0,F66=0),0,IF(AND(AS$3>=G66,AS$3<H66),F66*MIN(12,E66-(AS$3-G66)*12)/E66,0)) | AT4: =IF(OR(D66=0,E66=0,F66=0),0,IF(AND(AT$3>=G66,AT$3<H66),F66*MIN(12,E66-(AT$3-G66)*12)/E66,0)) | AU4: =IF(OR(D66=0,E66=0,F66=0),0,IF(AND(AU$3>=G66,AU$3<H66),F66*MIN(12,E66-(AU$3-G66)*12)/E66,0)) | AV4: =IF(OR(D66=0,E66=0,F66=0),0,IF(AND(AV$3>=G66,AV$3<H66),F66*MIN(12,E66-(AV$3-G66)*12)/E66,0)) | AW4: =IF(OR(D66=0,E66=0,F66=0),0,IF(AND(AW$3>=G66,AW$3<H66),F66*MIN(12,E66-(AW$3-G66)*12)/E66,0)) | AX4: =IF(OR(D66=0,E66=0,F66=0),0,IF(AND(AX$3>=G66,AX$3<H66),F66*MIN(12,E66-(AX$3-G66)*12)/E66,0)) | AY4: =IF(OR(D66=0,E66=0,F66=0),0,IF(AND(AY$3>=G66,AY$3<H66),F66*MIN(12,E66-(AY$3-G66)*12)/E66,0)) | AZ4: =IF(OR(D66=0,E66=0,F66=0),0,IF(AND(AZ$3>=G66,AZ$3<H66),F66*MIN(12,E66-(AZ$3-G66)*12)/E66,0)) | BA4: =IF(OR(D66=0,E66=0,F66=0),0,IF(AND(BA$3>=G66,BA$3<H66),F66*MIN(12,E66-(BA$3-G66)*12)/E66,0)) | BB4: =IF(OR(D66=0,E66=0,F66=0),0,IF(AND(BB$3>=G66,BB$3<H66),F66*MIN(12,E66-(BB$3-G66)*12)/E66,0))
A5: =A67 | B5: =B67 | C5: =C67 | D5: =SUM(E5:BB5) | E5: =IF(OR(D67=0,E67=0,F67=0),0,IF(AND(E$3>=G67,E$3<H67),F67*MIN(12,E67-(E$3-G67)*12)/E67,0)) | F5: =IF(OR(D67=0,E67=0,F67=0),0,IF(AND(F$3>=G67,F$3<H67),F67*MIN(12,E67-(F$3-G67)*12)/E67,0)) | G5: =IF(OR(D67=0,E67=0,F67=0),0,IF(AND(G$3>=G67,G$3<H67),F67*MIN(12,E67-(G$3-G67)*12)/E67,0)) | H5: =IF(OR(D67=0,E67=0,F67=0),0,IF(AND(H$3>=G67,H$3<H67),F67*MIN(12,E67-(H$3-G67)*12)/E67,0)) | I5: =IF(OR(D67=0,E67=0,F67=0),0,IF(AND(I$3>=G67,I$3<H67),F67*MIN(12,E67-(I$3-G67)*12)/E67,0)) | J5: =IF(OR(D67=0,E67=0,F67=0),0,IF(AND(J$3>=G67,J$3<H67),F67*MIN(12,E67-(J$3-G67)*12)/E67,0)) | K5: =IF(OR(D67=0,E67=0,F67=0),0,IF(AND(K$3>=G67,K$3<H67),F67*MIN(12,E67-(K$3-G67)*12)/E67,0)) | L5: =IF(OR(D67=0,E67=0,F67=0),0,IF(AND(L$3>=G67,L$3<H67),F67*MIN(12,E67-(L$3-G67)*12)/E67,0)) | M5: =IF(OR(D67=0,E67=0,F67=0),0,IF(AND(M$3>=G67,M$3<H67),F67*MIN(12,E67-(M$3-G67)*12)/E67,0)) | N5: =IF(OR(D67=0,E67=0,F67=0),0,IF(AND(N$3>=G67,N$3<H67),F67*MIN(12,E67-(N$3-G67)*12)/E67,0)) | O5: =IF(OR(D67=0,E67=0,F67=0),0,IF(AND(O$3>=G67,O$3<H67),F67*MIN(12,E67-(O$3-G67)*12)/E67,0)) | P5: =IF(OR(D67=0,E67=0,F67=0),0,IF(AND(P$3>=G67,P$3<H67),F67*MIN(12,E67-(P$3-G67)*12)/E67,0)) | Q5: =IF(OR(D67=0,E67=0,F67=0),0,IF(AND(Q$3>=G67,Q$3<H67),F67*MIN(12,E67-(Q$3-G67)*12)/E67,0)) | R5: =IF(OR(D67=0,E67=0,F67=0),0,IF(AND(R$3>=G67,R$3<H67),F67*MIN(12,E67-(R$3-G67)*12)/E67,0)) | S5: =IF(OR(D67=0,E67=0,F67=0),0,IF(AND(S$3>=G67,S$3<H67),F67*MIN(12,E67-(S$3-G67)*12)/E67,0)) | T5: =IF(OR(D67=0,E67=0,F67=0),0,IF(AND(T$3>=G67,T$3<H67),F67*MIN(12,E67-(T$3-G67)*12)/E67,0)) | U5: =IF(OR(D67=0,E67=0,F67=0),0,IF(AND(U$3>=G67,U$3<H67),F67*MIN(12,E67-(U$3-G67)*12)/E67,0)) | V5: =IF(OR(D67=0,E67=0,F67=0),0,IF(AND(V$3>=G67,V$3<H67),F67*MIN(12,E67-(V$3-G67)*12)/E67,0)) | W5: =IF(OR(D67=0,E67=0,F67=0),0,IF(AND(W$3>=G67,W$3<H67),F67*MIN(12,E67-(W$3-G67)*12)/E67,0)) | X5: =IF(OR(D67=0,E67=0,F67=0),0,IF(AND(X$3>=G67,X$3<H67),F67*MIN(12,E67-(X$3-G67)*12)/E67,0)) | Y5: =IF(OR(D67=0,E67=0,F67=0),0,IF(AND(Y$3>=G67,Y$3<H67),F67*MIN(12,E67-(Y$3-G67)*12)/E67,0)) | Z5: =IF(OR(D67=0,E67=0,F67=0),0,IF(AND(Z$3>=G67,Z$3<H67),F67*MIN(12,E67-(Z$3-G67)*12)/E67,0)) | AA5: =IF(OR(D67=0,E67=0,F67=0),0,IF(AND(AA$3>=G67,AA$3<H67),F67*MIN(12,E67-(AA$3-G67)*12)/E67,0)) | AB5: =IF(OR(D67=0,E67=0,F67=0),0,IF(AND(AB$3>=G67,AB$3<H67),F67*MIN(12,E67-(AB$3-G67)*12)/E67,0)) | AC5: =IF(OR(D67=0,E67=0,F67=0),0,IF(AND(AC$3>=G67,AC$3<H67),F67*MIN(12,E67-(AC$3-G67)*12)/E67,0)) | AD5: =IF(OR(D67=0,E67=0,F67=0),0,IF(AND(AD$3>=G67,AD$3<H67),F67*MIN(12,E67-(AD$3-G67)*12)/E67,0)) | AE5: =IF(OR(D67=0,E67=0,F67=0),0,IF(AND(AE$3>=G67,AE$3<H67),F67*MIN(12,E67-(AE$3-G67)*12)/E67,0)) | AF5: =IF(OR(D67=0,E67=0,F67=0),0,IF(AND(AF$3>=G67,AF$3<H67),F67*MIN(12,E67-(AF$3-G67)*12)/E67,0)) | AG5: =IF(OR(D67=0,E67=0,F67=0),0,IF(AND(AG$3>=G67,AG$3<H67),F67*MIN(12,E67-(AG$3-G67)*12)/E67,0)) | AH5: =IF(OR(D67=0,E67=0,F67=0),0,IF(AND(AH$3>=G67,AH$3<H67),F67*MIN(12,E67-(AH$3-G67)*12)/E67,0)) | AI5: =IF(OR(D67=0,E67=0,F67=0),0,IF(AND(AI$3>=G67,AI$3<H67),F67*MIN(12,E67-(AI$3-G67)*12)/E67,0)) | AJ5: =IF(OR(D67=0,E67=0,F67=0),0,IF(AND(AJ$3>=G67,AJ$3<H67),F67*MIN(12,E67-(AJ$3-G67)*12)/E67,0)) | AK5: =IF(OR(D67=0,E67=0,F67=0),0,IF(AND(AK$3>=G67,AK$3<H67),F67*MIN(12,E67-(AK$3-G67)*12)/E67,0)) | AL5: =IF(OR(D67=0,E67=0,F67=0),0,IF(AND(AL$3>=G67,AL$3<H67),F67*MIN(12,E67-(AL$3-G67)*12)/E67,0)) | AM5: =IF(OR(D67=0,E67=0,F67=0),0,IF(AND(AM$3>=G67,AM$3<H67),F67*MIN(12,E67-(AM$3-G67)*12)/E67,0)) | AN5: =IF(OR(D67=0,E67=0,F67=0),0,IF(AND(AN$3>=G67,AN$3<H67),F67*MIN(12,E67-(AN$3-G67)*12)/E67,0)) | AO5: =IF(OR(D67=0,E67=0,F67=0),0,IF(AND(AO$3>=G67,AO$3<H67),F67*MIN(12,E67-(AO$3-G67)*12)/E67,0)) | AP5: =IF(OR(D67=0,E67=0,F67=0),0,IF(AND(AP$3>=G67,AP$3<H67),F67*MIN(12,E67-(AP$3-G67)*12)/E67,0)) | AQ5: =IF(OR(D67=0,E67=0,F67=0),0,IF(AND(AQ$3>=G67,AQ$3<H67),F67*MIN(12,E67-(AQ$3-G67)*12)/E67,0)) | AR5: =IF(OR(D67=0,E67=0,F67=0),0,IF(AND(AR$3>=G67,AR$3<H67),F67*MIN(12,E67-(AR$3-G67)*12)/E67,0)) | AS5: =IF(OR(D67=0,E67=0,F67=0),0,IF(AND(AS$3>=G67,AS$3<H67),F67*MIN(12,E67-(AS$3-G67)*12)/E67,0)) | AT5: =IF(OR(D67=0,E67=0,F67=0),0,IF(AND(AT$3>=G67,AT$3<H67),F67*MIN(12,E67-(AT$3-G67)*12)/E67,0)) | AU5: =IF(OR(D67=0,E67=0,F67=0),0,IF(AND(AU$3>=G67,AU$3<H67),F67*MIN(12,E67-(AU$3-G67)*12)/E67,0)) | AV5: =IF(OR(D67=0,E67=0,F67=0),0,IF(AND(AV$3>=G67,AV$3<H67),F67*MIN(12,E67-(AV$3-G67)*12)/E67,0)) | AW5: =IF(OR(D67=0,E67=0,F67=0),0,IF(AND(AW$3>=G67,AW$3<H67),F67*MIN(12,E67-(AW$3-G67)*12)/E67,0)) | AX5: =IF(OR(D67=0,E67=0,F67=0),0,IF(AND(AX$3>=G67,AX$3<H67),F67*MIN(12,E67-(AX$3-G67)*12)/E67,0)) | AY5: =IF(OR(D67=0,E67=0,F67=0),0,IF(AND(AY$3>=G67,AY$3<H67),F67*MIN(12,E67-(AY$3-G67)*12)/E67,0)) | AZ5: =IF(OR(D67=0,E67=0,F67=0),0,IF(AND(AZ$3>=G67,AZ$3<H67),F67*MIN(12,E67-(AZ$3-G67)*12)/E67,0)) | BA5: =IF(OR(D67=0,E67=0,F67=0),0,IF(AND(BA$3>=G67,BA$3<H67),F67*MIN(12,E67-(BA$3-G67)*12)/E67,0)) | BB5: =IF(OR(D67=0,E67=0,F67=0),0,IF(AND(BB$3>=G67,BB$3<H67),F67*MIN(12,E67-(BB$3-G67)*12)/E67,0))
A6: =A68 | B6: =B68 | C6: =C68 | D6: =SUM(E6:BB6) | E6: =IF(OR(D68=0,E68=0,F68=0),0,IF(AND(E$3>=G68,E$3<H68),F68*MIN(12,E68-(E$3-G68)*12)/E68,0)) | F6: =IF(OR(D68=0,E68=0,F68=0),0,IF(AND(F$3>=G68,F$3<H68),F68*MIN(12,E68-(F$3-G68)*12)/E68,0)) | G6: =IF(OR(D68=0,E68=0,F68=0),0,IF(AND(G$3>=G68,G$3<H68),F68*MIN(12,E68-(G$3-G68)*12)/E68,0)) | H6: =IF(OR(D68=0,E68=0,F68=0),0,IF(AND(H$3>=G68,H$3<H68),F68*MIN(12,E68-(H$3-G68)*12)/E68,0)) | I6: =IF(OR(D68=0,E68=0,F68=0),0,IF(AND(I$3>=G68,I$3<H68),F68*MIN(12,E68-(I$3-G68)*12)/E68,0)) | J6: =IF(OR(D68=0,E68=0,F68=0),0,IF(AND(J$3>=G68,J$3<H68),F68*MIN(12,E68-(J$3-G68)*12)/E68,0)) | K6: =IF(OR(D68=0,E68=0,F68=0),0,IF(AND(K$3>=G68,K$3<H68),F68*MIN(12,E68-(K$3-G68)*12)/E68,0)) | L6: =IF(OR(D68=0,E68=0,F68=0),0,IF(AND(L$3>=G68,L$3<H68),F68*MIN(12,E68-(L$3-G68)*12)/E68,0)) | M6: =IF(OR(D68=0,E68=0,F68=0),0,IF(AND(M$3>=G68,M$3<H68),F68*MIN(12,E68-(M$3-G68)*12)/E68,0)) | N6: =IF(OR(D68=0,E68=0,F68=0),0,IF(AND(N$3>=G68,N$3<H68),F68*MIN(12,E68-(N$3-G68)*12)/E68,0)) | O6: =IF(OR(D68=0,E68=0,F68=0),0,IF(AND(O$3>=G68,O$3<H68),F68*MIN(12,E68-(O$3-G68)*12)/E68,0)) | P6: =IF(OR(D68=0,E68=0,F68=0),0,IF(AND(P$3>=G68,P$3<H68),F68*MIN(12,E68-(P$3-G68)*12)/E68,0)) | Q6: =IF(OR(D68=0,E68=0,F68=0),0,IF(AND(Q$3>=G68,Q$3<H68),F68*MIN(12,E68-(Q$3-G68)*12)/E68,0)) | R6: =IF(OR(D68=0,E68=0,F68=0),0,IF(AND(R$3>=G68,R$3<H68),F68*MIN(12,E68-(R$3-G68)*12)/E68,0)) | S6: =IF(OR(D68=0,E68=0,F68=0),0,IF(AND(S$3>=G68,S$3<H68),F68*MIN(12,E68-(S$3-G68)*12)/E68,0)) | T6: =IF(OR(D68=0,E68=0,F68=0),0,IF(AND(T$3>=G68,T$3<H68),F68*MIN(12,E68-(T$3-G68)*12)/E68,0)) | U6: =IF(OR(D68=0,E68=0,F68=0),0,IF(AND(U$3>=G68,U$3<H68),F68*MIN(12,E68-(U$3-G68)*12)/E68,0)) | V6: =IF(OR(D68=0,E68=0,F68=0),0,IF(AND(V$3>=G68,V$3<H68),F68*MIN(12,E68-(V$3-G68)*12)/E68,0)) | W6: =IF(OR(D68=0,E68=0,F68=0),0,IF(AND(W$3>=G68,W$3<H68),F68*MIN(12,E68-(W$3-G68)*12)/E68,0)) | X6: =IF(OR(D68=0,E68=0,F68=0),0,IF(AND(X$3>=G68,X$3<H68),F68*MIN(12,E68-(X$3-G68)*12)/E68,0)) | Y6: =IF(OR(D68=0,E68=0,F68=0),0,IF(AND(Y$3>=G68,Y$3<H68),F68*MIN(12,E68-(Y$3-G68)*12)/E68,0)) | Z6: =IF(OR(D68=0,E68=0,F68=0),0,IF(AND(Z$3>=G68,Z$3<H68),F68*MIN(12,E68-(Z$3-G68)*12)/E68,0)) | AA6: =IF(OR(D68=0,E68=0,F68=0),0,IF(AND(AA$3>=G68,AA$3<H68),F68*MIN(12,E68-(AA$3-G68)*12)/E68,0)) | AB6: =IF(OR(D68=0,E68=0,F68=0),0,IF(AND(AB$3>=G68,AB$3<H68),F68*MIN(12,E68-(AB$3-G68)*12)/E68,0)) | AC6: =IF(OR(D68=0,E68=0,F68=0),0,IF(AND(AC$3>=G68,AC$3<H68),F68*MIN(12,E68-(AC$3-G68)*12)/E68,0)) | AD6: =IF(OR(D68=0,E68=0,F68=0),0,IF(AND(AD$3>=G68,AD$3<H68),F68*MIN(12,E68-(AD$3-G68)*12)/E68,0)) | AE6: =IF(OR(D68=0,E68=0,F68=0),0,IF(AND(AE$3>=G68,AE$3<H68),F68*MIN(12,E68-(AE$3-G68)*12)/E68,0)) | AF6: =IF(OR(D68=0,E68=0,F68=0),0,IF(AND(AF$3>=G68,AF$3<H68),F68*MIN(12,E68-(AF$3-G68)*12)/E68,0)) | AG6: =IF(OR(D68=0,E68=0,F68=0),0,IF(AND(AG$3>=G68,AG$3<H68),F68*MIN(12,E68-(AG$3-G68)*12)/E68,0)) | AH6: =IF(OR(D68=0,E68=0,F68=0),0,IF(AND(AH$3>=G68,AH$3<H68),F68*MIN(12,E68-(AH$3-G68)*12)/E68,0)) | AI6: =IF(OR(D68=0,E68=0,F68=0),0,IF(AND(AI$3>=G68,AI$3<H68),F68*MIN(12,E68-(AI$3-G68)*12)/E68,0)) | AJ6: =IF(OR(D68=0,E68=0,F68=0),0,IF(AND(AJ$3>=G68,AJ$3<H68),F68*MIN(12,E68-(AJ$3-G68)*12)/E68,0)) | AK6: =IF(OR(D68=0,E68=0,F68=0),0,IF(AND(AK$3>=G68,AK$3<H68),F68*MIN(12,E68-(AK$3-G68)*12)/E68,0)) | AL6: =IF(OR(D68=0,E68=0,F68=0),0,IF(AND(AL$3>=G68,AL$3<H68),F68*MIN(12,E68-(AL$3-G68)*12)/E68,0)) | AM6: =IF(OR(D68=0,E68=0,F68=0),0,IF(AND(AM$3>=G68,AM$3<H68),F68*MIN(12,E68-(AM$3-G68)*12)/E68,0)) | AN6: =IF(OR(D68=0,E68=0,F68=0),0,IF(AND(AN$3>=G68,AN$3<H68),F68*MIN(12,E68-(AN$3-G68)*12)/E68,0)) | AO6: =IF(OR(D68=0,E68=0,F68=0),0,IF(AND(AO$3>=G68,AO$3<H68),F68*MIN(12,E68-(AO$3-G68)*12)/E68,0)) | AP6: =IF(OR(D68=0,E68=0,F68=0),0,IF(AND(AP$3>=G68,AP$3<H68),F68*MIN(12,E68-(AP$3-G68)*12)/E68,0)) | AQ6: =IF(OR(D68=0,E68=0,F68=0),0,IF(AND(AQ$3>=G68,AQ$3<H68),F68*MIN(12,E68-(AQ$3-G68)*12)/E68,0)) | AR6: =IF(OR(D68=0,E68=0,F68=0),0,IF(AND(AR$3>=G68,AR$3<H68),F68*MIN(12,E68-(AR$3-G68)*12)/E68,0)) | AS6: =IF(OR(D68=0,E68=0,F68=0),0,IF(AND(AS$3>=G68,AS$3<H68),F68*MIN(12,E68-(AS$3-G68)*12)/E68,0)) | AT6: =IF(OR(D68=0,E68=0,F68=0),0,IF(AND(AT$3>=G68,AT$3<H68),F68*MIN(12,E68-(AT$3-G68)*12)/E68,0)) | AU6: =IF(OR(D68=0,E68=0,F68=0),0,IF(AND(AU$3>=G68,AU$3<H68),F68*MIN(12,E68-(AU$3-G68)*12)/E68,0)) | AV6: =IF(OR(D68=0,E68=0,F68=0),0,IF(AND(AV$3>=G68,AV$3<H68),F68*MIN(12,E68-(AV$3-G68)*12)/E68,0)) | AW6: =IF(OR(D68=0,E68=0,F68=0),0,IF(AND(AW$3>=G68,AW$3<H68),F68*MIN(12,E68-(AW$3-G68)*12)/E68,0)) | AX6: =IF(OR(D68=0,E68=0,F68=0),0,IF(AND(AX$3>=G68,AX$3<H68),F68*MIN(12,E68-(AX$3-G68)*12)/E68,0)) | AY6: =IF(OR(D68=0,E68=0,F68=0),0,IF(AND(AY$3>=G68,AY$3<H68),F68*MIN(12,E68-(AY$3-G68)*12)/E68,0)) | AZ6: =IF(OR(D68=0,E68=0,F68=0),0,IF(AND(AZ$3>=G68,AZ$3<H68),F68*MIN(12,E68-(AZ$3-G68)*12)/E68,0)) | BA6: =IF(OR(D68=0,E68=0,F68=0),0,IF(AND(BA$3>=G68,BA$3<H68),F68*MIN(12,E68-(BA$3-G68)*12)/E68,0)) | BB6: =IF(OR(D68=0,E68=0,F68=0),0,IF(AND(BB$3>=G68,BB$3<H68),F68*MIN(12,E68-(BB$3-G68)*12)/E68,0))
A7: =A69 | B7: =B69 | C7: =C69 | D7: =SUM(E7:BB7) | E7: =IF(OR(D69=0,E69=0,F69=0),0,IF(AND(E$3>=G69,E$3<H69),F69*MIN(12,E69-(E$3-G69)*12)/E69,0)) | F7: =IF(OR(D69=0,E69=0,F69=0),0,IF(AND(F$3>=G69,F$3<H69),F69*MIN(12,E69-(F$3-G69)*12)/E69,0)) | G7: =IF(OR(D69=0,E69=0,F69=0),0,IF(AND(G$3>=G69,G$3<H69),F69*MIN(12,E69-(G$3-G69)*12)/E69,0)) | H7: =IF(OR(D69=0,E69=0,F69=0),0,IF(AND(H$3>=G69,H$3<H69),F69*MIN(12,E69-(H$3-G69)*12)/E69,0)) | I7: =IF(OR(D69=0,E69=0,F69=0),0,IF(AND(I$3>=G69,I$3<H69),F69*MIN(12,E69-(I$3-G69)*12)/E69,0)) | J7: =IF(OR(D69=0,E69=0,F69=0),0,IF(AND(J$3>=G69,J$3<H69),F69*MIN(12,E69-(J$3-G69)*12)/E69,0)) | K7: =IF(OR(D69=0,E69=0,F69=0),0,IF(AND(K$3>=G69,K$3<H69),F69*MIN(12,E69-(K$3-G69)*12)/E69,0)) | L7: =IF(OR(D69=0,E69=0,F69=0),0,IF(AND(L$3>=G69,L$3<H69),F69*MIN(12,E69-(L$3-G69)*12)/E69,0)) | M7: =IF(OR(D69=0,E69=0,F69=0),0,IF(AND(M$3>=G69,M$3<H69),F69*MIN(12,E69-(M$3-G69)*12)/E69,0)) | N7: =IF(OR(D69=0,E69=0,F69=0),0,IF(AND(N$3>=G69,N$3<H69),F69*MIN(12,E69-(N$3-G69)*12)/E69,0)) | O7: =IF(OR(D69=0,E69=0,F69=0),0,IF(AND(O$3>=G69,O$3<H69),F69*MIN(12,E69-(O$3-G69)*12)/E69,0)) | P7: =IF(OR(D69=0,E69=0,F69=0),0,IF(AND(P$3>=G69,P$3<H69),F69*MIN(12,E69-(P$3-G69)*12)/E69,0)) | Q7: =IF(OR(D69=0,E69=0,F69=0),0,IF(AND(Q$3>=G69,Q$3<H69),F69*MIN(12,E69-(Q$3-G69)*12)/E69,0)) | R7: =IF(OR(D69=0,E69=0,F69=0),0,IF(AND(R$3>=G69,R$3<H69),F69*MIN(12,E69-(R$3-G69)*12)/E69,0)) | S7: =IF(OR(D69=0,E69=0,F69=0),0,IF(AND(S$3>=G69,S$3<H69),F69*MIN(12,E69-(S$3-G69)*12)/E69,0)) | T7: =IF(OR(D69=0,E69=0,F69=0),0,IF(AND(T$3>=G69,T$3<H69),F69*MIN(12,E69-(T$3-G69)*12)/E69,0)) | U7: =IF(OR(D69=0,E69=0,F69=0),0,IF(AND(U$3>=G69,U$3<H69),F69*MIN(12,E69-(U$3-G69)*12)/E69,0)) | V7: =IF(OR(D69=0,E69=0,F69=0),0,IF(AND(V$3>=G69,V$3<H69),F69*MIN(12,E69-(V$3-G69)*12)/E69,0)) | W7: =IF(OR(D69=0,E69=0,F69=0),0,IF(AND(W$3>=G69,W$3<H69),F69*MIN(12,E69-(W$3-G69)*12)/E69,0)) | X7: =IF(OR(D69=0,E69=0,F69=0),0,IF(AND(X$3>=G69,X$3<H69),F69*MIN(12,E69-(X$3-G69)*12)/E69,0)) | Y7: =IF(OR(D69=0,E69=0,F69=0),0,IF(AND(Y$3>=G69,Y$3<H69),F69*MIN(12,E69-(Y$3-G69)*12)/E69,0)) | Z7: =IF(OR(D69=0,E69=0,F69=0),0,IF(AND(Z$3>=G69,Z$3<H69),F69*MIN(12,E69-(Z$3-G69)*12)/E69,0)) | AA7: =IF(OR(D69=0,E69=0,F69=0),0,IF(AND(AA$3>=G69,AA$3<H69),F69*MIN(12,E69-(AA$3-G69)*12)/E69,0)) | AB7: =IF(OR(D69=0,E69=0,F69=0),0,IF(AND(AB$3>=G69,AB$3<H69),F69*MIN(12,E69-(AB$3-G69)*12)/E69,0)) | AC7: =IF(OR(D69=0,E69=0,F69=0),0,IF(AND(AC$3>=G69,AC$3<H69),F69*MIN(12,E69-(AC$3-G69)*12)/E69,0)) | AD7: =IF(OR(D69=0,E69=0,F69=0),0,IF(AND(AD$3>=G69,AD$3<H69),F69*MIN(12,E69-(AD$3-G69)*12)/E69,0)) | AE7: =IF(OR(D69=0,E69=0,F69=0),0,IF(AND(AE$3>=G69,AE$3<H69),F69*MIN(12,E69-(AE$3-G69)*12)/E69,0)) | AF7: =IF(OR(D69=0,E69=0,F69=0),0,IF(AND(AF$3>=G69,AF$3<H69),F69*MIN(12,E69-(AF$3-G69)*12)/E69,0)) | AG7: =IF(OR(D69=0,E69=0,F69=0),0,IF(AND(AG$3>=G69,AG$3<H69),F69*MIN(12,E69-(AG$3-G69)*12)/E69,0)) | AH7: =IF(OR(D69=0,E69=0,F69=0),0,IF(AND(AH$3>=G69,AH$3<H69),F69*MIN(12,E69-(AH$3-G69)*12)/E69,0)) | AI7: =IF(OR(D69=0,E69=0,F69=0),0,IF(AND(AI$3>=G69,AI$3<H69),F69*MIN(12,E69-(AI$3-G69)*12)/E69,0)) | AJ7: =IF(OR(D69=0,E69=0,F69=0),0,IF(AND(AJ$3>=G69,AJ$3<H69),F69*MIN(12,E69-(AJ$3-G69)*12)/E69,0)) | AK7: =IF(OR(D69=0,E69=0,F69=0),0,IF(AND(AK$3>=G69,AK$3<H69),F69*MIN(12,E69-(AK$3-G69)*12)/E69,0)) | AL7: =IF(OR(D69=0,E69=0,F69=0),0,IF(AND(AL$3>=G69,AL$3<H69),F69*MIN(12,E69-(AL$3-G69)*12)/E69,0)) | AM7: =IF(OR(D69=0,E69=0,F69=0),0,IF(AND(AM$3>=G69,AM$3<H69),F69*MIN(12,E69-(AM$3-G69)*12)/E69,0)) | AN7: =IF(OR(D69=0,E69=0,F69=0),0,IF(AND(AN$3>=G69,AN$3<H69),F69*MIN(12,E69-(AN$3-G69)*12)/E69,0)) | AO7: =IF(OR(D69=0,E69=0,F69=0),0,IF(AND(AO$3>=G69,AO$3<H69),F69*MIN(12,E69-(AO$3-G69)*12)/E69,0)) | AP7: =IF(OR(D69=0,E69=0,F69=0),0,IF(AND(AP$3>=G69,AP$3<H69),F69*MIN(12,E69-(AP$3-G69)*12)/E69,0)) | AQ7: =IF(OR(D69=0,E69=0,F69=0),0,IF(AND(AQ$3>=G69,AQ$3<H69),F69*MIN(12,E69-(AQ$3-G69)*12)/E69,0)) | AR7: =IF(OR(D69=0,E69=0,F69=0),0,IF(AND(AR$3>=G69,AR$3<H69),F69*MIN(12,E69-(AR$3-G69)*12)/E69,0)) | AS7: =IF(OR(D69=0,E69=0,F69=0),0,IF(AND(AS$3>=G69,AS$3<H69),F69*MIN(12,E69-(AS$3-G69)*12)/E69,0)) | AT7: =IF(OR(D69=0,E69=0,F69=0),0,IF(AND(AT$3>=G69,AT$3<H69),F69*MIN(12,E69-(AT$3-G69)*12)/E69,0)) | AU7: =IF(OR(D69=0,E69=0,F69=0),0,IF(AND(AU$3>=G69,AU$3<H69),F69*MIN(12,E69-(AU$3-G69)*12)/E69,0)) | AV7: =IF(OR(D69=0,E69=0,F69=0),0,IF(AND(AV$3>=G69,AV$3<H69),F69*MIN(12,E69-(AV$3-G69)*12)/E69,0)) | AW7: =IF(OR(D69=0,E69=0,F69=0),0,IF(AND(AW$3>=G69,AW$3<H69),F69*MIN(12,E69-(AW$3-G69)*12)/E69,0)) | AX7: =IF(OR(D69=0,E69=0,F69=0),0,IF(AND(AX$3>=G69,AX$3<H69),F69*MIN(12,E69-(AX$3-G69)*12)/E69,0)) | AY7: =IF(OR(D69=0,E69=0,F69=0),0,IF(AND(AY$3>=G69,AY$3<H69),F69*MIN(12,E69-(AY$3-G69)*12)/E69,0)) | AZ7: =IF(OR(D69=0,E69=0,F69=0),0,IF(AND(AZ$3>=G69,AZ$3<H69),F69*MIN(12,E69-(AZ$3-G69)*12)/E69,0)) | BA7: =IF(OR(D69=0,E69=0,F69=0),0,IF(AND(BA$3>=G69,BA$3<H69),F69*MIN(12,E69-(BA$3-G69)*12)/E69,0)) | BB7: =IF(OR(D69=0,E69=0,F69=0),0,IF(AND(BB$3>=G69,BB$3<H69),F69*MIN(12,E69-(BB$3-G69)*12)/E69,0))
A8: =A70 | B8: =B70 | C8: =C70 | D8: =SUM(E8:BB8) | E8: =IF(OR(D70=0,E70=0,F70=0),0,IF(AND(E$3>=G70,E$3<H70),F70*MIN(12,E70-(E$3-G70)*12)/E70,0)) | F8: =IF(OR(D70=0,E70=0,F70=0),0,IF(AND(F$3>=G70,F$3<H70),F70*MIN(12,E70-(F$3-G70)*12)/E70,0)) | G8: =IF(OR(D70=0,E70=0,F70=0),0,IF(AND(G$3>=G70,G$3<H70),F70*MIN(12,E70-(G$3-G70)*12)/E70,0)) | H8: =IF(OR(D70=0,E70=0,F70=0),0,IF(AND(H$3>=G70,H$3<H70),F70*MIN(12,E70-(H$3-G70)*12)/E70,0)) | I8: =IF(OR(D70=0,E70=0,F70=0),0,IF(AND(I$3>=G70,I$3<H70),F70*MIN(12,E70-(I$3-G70)*12)/E70,0)) | J8: =IF(OR(D70=0,E70=0,F70=0),0,IF(AND(J$3>=G70,J$3<H70),F70*MIN(12,E70-(J$3-G70)*12)/E70,0)) | K8: =IF(OR(D70=0,E70=0,F70=0),0,IF(AND(K$3>=G70,K$3<H70),F70*MIN(12,E70-(K$3-G70)*12)/E70,0)) | L8: =IF(OR(D70=0,E70=0,F70=0),0,IF(AND(L$3>=G70,L$3<H70),F70*MIN(12,E70-(L$3-G70)*12)/E70,0)) | M8: =IF(OR(D70=0,E70=0,F70=0),0,IF(AND(M$3>=G70,M$3<H70),F70*MIN(12,E70-(M$3-G70)*12)/E70,0)) | N8: =IF(OR(D70=0,E70=0,F70=0),0,IF(AND(N$3>=G70,N$3<H70),F70*MIN(12,E70-(N$3-G70)*12)/E70,0)) | O8: =IF(OR(D70=0,E70=0,F70=0),0,IF(AND(O$3>=G70,O$3<H70),F70*MIN(12,E70-(O$3-G70)*12)/E70,0)) | P8: =IF(OR(D70=0,E70=0,F70=0),0,IF(AND(P$3>=G70,P$3<H70),F70*MIN(12,E70-(P$3-G70)*12)/E70,0)) | Q8: =IF(OR(D70=0,E70=0,F70=0),0,IF(AND(Q$3>=G70,Q$3<H70),F70*MIN(12,E70-(Q$3-G70)*12)/E70,0)) | R8: =IF(OR(D70=0,E70=0,F70=0),0,IF(AND(R$3>=G70,R$3<H70),F70*MIN(12,E70-(R$3-G70)*12)/E70,0)) | S8: =IF(OR(D70=0,E70=0,F70=0),0,IF(AND(S$3>=G70,S$3<H70),F70*MIN(12,E70-(S$3-G70)*12)/E70,0)) | T8: =IF(OR(D70=0,E70=0,F70=0),0,IF(AND(T$3>=G70,T$3<H70),F70*MIN(12,E70-(T$3-G70)*12)/E70,0)) | U8: =IF(OR(D70=0,E70=0,F70=0),0,IF(AND(U$3>=G70,U$3<H70),F70*MIN(12,E70-(U$3-G70)*12)/E70,0)) | V8: =IF(OR(D70=0,E70=0,F70=0),0,IF(AND(V$3>=G70,V$3<H70),F70*MIN(12,E70-(V$3-G70)*12)/E70,0)) | W8: =IF(OR(D70=0,E70=0,F70=0),0,IF(AND(W$3>=G70,W$3<H70),F70*MIN(12,E70-(W$3-G70)*12)/E70,0)) | X8: =IF(OR(D70=0,E70=0,F70=0),0,IF(AND(X$3>=G70,X$3<H70),F70*MIN(12,E70-(X$3-G70)*12)/E70,0)) | Y8: =IF(OR(D70=0,E70=0,F70=0),0,IF(AND(Y$3>=G70,Y$3<H70),F70*MIN(12,E70-(Y$3-G70)*12)/E70,0)) | Z8: =IF(OR(D70=0,E70=0,F70=0),0,IF(AND(Z$3>=G70,Z$3<H70),F70*MIN(12,E70-(Z$3-G70)*12)/E70,0)) | AA8: =IF(OR(D70=0,E70=0,F70=0),0,IF(AND(AA$3>=G70,AA$3<H70),F70*MIN(12,E70-(AA$3-G70)*12)/E70,0)) | AB8: =IF(OR(D70=0,E70=0,F70=0),0,IF(AND(AB$3>=G70,AB$3<H70),F70*MIN(12,E70-(AB$3-G70)*12)/E70,0)) | AC8: =IF(OR(D70=0,E70=0,F70=0),0,IF(AND(AC$3>=G70,AC$3<H70),F70*MIN(12,E70-(AC$3-G70)*12)/E70,0)) | AD8: =IF(OR(D70=0,E70=0,F70=0),0,IF(AND(AD$3>=G70,AD$3<H70),F70*MIN(12,E70-(AD$3-G70)*12)/E70,0)) | AE8: =IF(OR(D70=0,E70=0,F70=0),0,IF(AND(AE$3>=G70,AE$3<H70),F70*MIN(12,E70-(AE$3-G70)*12)/E70,0)) | AF8: =IF(OR(D70=0,E70=0,F70=0),0,IF(AND(AF$3>=G70,AF$3<H70),F70*MIN(12,E70-(AF$3-G70)*12)/E70,0)) | AG8: =IF(OR(D70=0,E70=0,F70=0),0,IF(AND(AG$3>=G70,AG$3<H70),F70*MIN(12,E70-(AG$3-G70)*12)/E70,0)) | AH8: =IF(OR(D70=0,E70=0,F70=0),0,IF(AND(AH$3>=G70,AH$3<H70),F70*MIN(12,E70-(AH$3-G70)*12)/E70,0)) | AI8: =IF(OR(D70=0,E70=0,F70=0),0,IF(AND(AI$3>=G70,AI$3<H70),F70*MIN(12,E70-(AI$3-G70)*12)/E70,0)) | AJ8: =IF(OR(D70=0,E70=0,F70=0),0,IF(AND(AJ$3>=G70,AJ$3<H70),F70*MIN(12,E70-(AJ$3-G70)*12)/E70,0)) | AK8: =IF(OR(D70=0,E70=0,F70=0),0,IF(AND(AK$3>=G70,AK$3<H70),F70*MIN(12,E70-(AK$3-G70)*12)/E70,0)) | AL8: =IF(OR(D70=0,E70=0,F70=0),0,IF(AND(AL$3>=G70,AL$3<H70),F70*MIN(12,E70-(AL$3-G70)*12)/E70,0)) | AM8: =IF(OR(D70=0,E70=0,F70=0),0,IF(AND(AM$3>=G70,AM$3<H70),F70*MIN(12,E70-(AM$3-G70)*12)/E70,0)) | AN8: =IF(OR(D70=0,E70=0,F70=0),0,IF(AND(AN$3>=G70,AN$3<H70),F70*MIN(12,E70-(AN$3-G70)*12)/E70,0)) | AO8: =IF(OR(D70=0,E70=0,F70=0),0,IF(AND(AO$3>=G70,AO$3<H70),F70*MIN(12,E70-(AO$3-G70)*12)/E70,0)) | AP8: =IF(OR(D70=0,E70=0,F70=0),0,IF(AND(AP$3>=G70,AP$3<H70),F70*MIN(12,E70-(AP$3-G70)*12)/E70,0)) | AQ8: =IF(OR(D70=0,E70=0,F70=0),0,IF(AND(AQ$3>=G70,AQ$3<H70),F70*MIN(12,E70-(AQ$3-G70)*12)/E70,0)) | AR8: =IF(OR(D70=0,E70=0,F70=0),0,IF(AND(AR$3>=G70,AR$3<H70),F70*MIN(12,E70-(AR$3-G70)*12)/E70,0)) | AS8: =IF(OR(D70=0,E70=0,F70=0),0,IF(AND(AS$3>=G70,AS$3<H70),F70*MIN(12,E70-(AS$3-G70)*12)/E70,0)) | AT8: =IF(OR(D70=0,E70=0,F70=0),0,IF(AND(AT$3>=G70,AT$3<H70),F70*MIN(12,E70-(AT$3-G70)*12)/E70,0)) | AU8: =IF(OR(D70=0,E70=0,F70=0),0,IF(AND(AU$3>=G70,AU$3<H70),F70*MIN(12,E70-(AU$3-G70)*12)/E70,0)) | AV8: =IF(OR(D70=0,E70=0,F70=0),0,IF(AND(AV$3>=G70,AV$3<H70),F70*MIN(12,E70-(AV$3-G70)*12)/E70,0)) | AW8: =IF(OR(D70=0,E70=0,F70=0),0,IF(AND(AW$3>=G70,AW$3<H70),F70*MIN(12,E70-(AW$3-G70)*12)/E70,0)) | AX8: =IF(OR(D70=0,E70=0,F70=0),0,IF(AND(AX$3>=G70,AX$3<H70),F70*MIN(12,E70-(AX$3-G70)*12)/E70,0)) | AY8: =IF(OR(D70=0,E70=0,F70=0),0,IF(AND(AY$3>=G70,AY$3<H70),F70*MIN(12,E70-(AY$3-G70)*12)/E70,0)) | AZ8: =IF(OR(D70=0,E70=0,F70=0),0,IF(AND(AZ$3>=G70,AZ$3<H70),F70*MIN(12,E70-(AZ$3-G70)*12)/E70,0)) | BA8: =IF(OR(D70=0,E70=0,F70=0),0,IF(AND(BA$3>=G70,BA$3<H70),F70*MIN(12,E70-(BA$3-G70)*12)/E70,0)) | BB8: =IF(OR(D70=0,E70=0,F70=0),0,IF(AND(BB$3>=G70,BB$3<H70),F70*MIN(12,E70-(BB$3-G70)*12)/E70,0))
A9: =A71 | B9: =B71 | C9: =C71 | D9: =SUM(E9:BB9) | E9: =IF(OR(D71=0,E71=0,F71=0),0,IF(AND(E$3>=G71,E$3<H71),F71*MIN(12,E71-(E$3-G71)*12)/E71,0)) | F9: =IF(OR(D71=0,E71=0,F71=0),0,IF(AND(F$3>=G71,F$3<H71),F71*MIN(12,E71-(F$3-G71)*12)/E71,0)) | G9: =IF(OR(D71=0,E71=0,F71=0),0,IF(AND(G$3>=G71,G$3<H71),F71*MIN(12,E71-(G$3-G71)*12)/E71,0)) | H9: =IF(OR(D71=0,E71=0,F71=0),0,IF(AND(H$3>=G71,H$3<H71),F71*MIN(12,E71-(H$3-G71)*12)/E71,0)) | I9: =IF(OR(D71=0,E71=0,F71=0),0,IF(AND(I$3>=G71,I$3<H71),F71*MIN(12,E71-(I$3-G71)*12)/E71,0)) | J9: =IF(OR(D71=0,E71=0,F71=0),0,IF(AND(J$3>=G71,J$3<H71),F71*MIN(12,E71-(J$3-G71)*12)/E71,0)) | K9: =IF(OR(D71=0,E71=0,F71=0),0,IF(AND(K$3>=G71,K$3<H71),F71*MIN(12,E71-(K$3-G71)*12)/E71,0)) | L9: =IF(OR(D71=0,E71=0,F71=0),0,IF(AND(L$3>=G71,L$3<H71),F71*MIN(12,E71-(L$3-G71)*12)/E71,0)) | M9: =IF(OR(D71=0,E71=0,F71=0),0,IF(AND(M$3>=G71,M$3<H71),F71*MIN(12,E71-(M$3-G71)*12)/E71,0)) | N9: =IF(OR(D71=0,E71=0,F71=0),0,IF(AND(N$3>=G71,N$3<H71),F71*MIN(12,E71-(N$3-G71)*12)/E71,0)) | O9: =IF(OR(D71=0,E71=0,F71=0),0,IF(AND(O$3>=G71,O$3<H71),F71*MIN(12,E71-(O$3-G71)*12)/E71,0)) | P9: =IF(OR(D71=0,E71=0,F71=0),0,IF(AND(P$3>=G71,P$3<H71),F71*MIN(12,E71-(P$3-G71)*12)/E71,0)) | Q9: =IF(OR(D71=0,E71=0,F71=0),0,IF(AND(Q$3>=G71,Q$3<H71),F71*MIN(12,E71-(Q$3-G71)*12)/E71,0)) | R9: =IF(OR(D71=0,E71=0,F71=0),0,IF(AND(R$3>=G71,R$3<H71),F71*MIN(12,E71-(R$3-G71)*12)/E71,0)) | S9: =IF(OR(D71=0,E71=0,F71=0),0,IF(AND(S$3>=G71,S$3<H71),F71*MIN(12,E71-(S$3-G71)*12)/E71,0)) | T9: =IF(OR(D71=0,E71=0,F71=0),0,IF(AND(T$3>=G71,T$3<H71),F71*MIN(12,E71-(T$3-G71)*12)/E71,0)) | U9: =IF(OR(D71=0,E71=0,F71=0),0,IF(AND(U$3>=G71,U$3<H71),F71*MIN(12,E71-(U$3-G71)*12)/E71,0)) | V9: =IF(OR(D71=0,E71=0,F71=0),0,IF(AND(V$3>=G71,V$3<H71),F71*MIN(12,E71-(V$3-G71)*12)/E71,0)) | W9: =IF(OR(D71=0,E71=0,F71=0),0,IF(AND(W$3>=G71,W$3<H71),F71*MIN(12,E71-(W$3-G71)*12)/E71,0)) | X9: =IF(OR(D71=0,E71=0,F71=0),0,IF(AND(X$3>=G71,X$3<H71),F71*MIN(12,E71-(X$3-G71)*12)/E71,0)) | Y9: =IF(OR(D71=0,E71=0,F71=0),0,IF(AND(Y$3>=G71,Y$3<H71),F71*MIN(12,E71-(Y$3-G71)*12)/E71,0)) | Z9: =IF(OR(D71=0,E71=0,F71=0),0,IF(AND(Z$3>=G71,Z$3<H71),F71*MIN(12,E71-(Z$3-G71)*12)/E71,0)) | AA9: =IF(OR(D71=0,E71=0,F71=0),0,IF(AND(AA$3>=G71,AA$3<H71),F71*MIN(12,E71-(AA$3-G71)*12)/E71,0)) | AB9: =IF(OR(D71=0,E71=0,F71=0),0,IF(AND(AB$3>=G71,AB$3<H71),F71*MIN(12,E71-(AB$3-G71)*12)/E71,0)) | AC9: =IF(OR(D71=0,E71=0,F71=0),0,IF(AND(AC$3>=G71,AC$3<H71),F71*MIN(12,E71-(AC$3-G71)*12)/E71,0)) | AD9: =IF(OR(D71=0,E71=0,F71=0),0,IF(AND(AD$3>=G71,AD$3<H71),F71*MIN(12,E71-(AD$3-G71)*12)/E71,0)) | AE9: =IF(OR(D71=0,E71=0,F71=0),0,IF(AND(AE$3>=G71,AE$3<H71),F71*MIN(12,E71-(AE$3-G71)*12)/E71,0)) | AF9: =IF(OR(D71=0,E71=0,F71=0),0,IF(AND(AF$3>=G71,AF$3<H71),F71*MIN(12,E71-(AF$3-G71)*12)/E71,0)) | AG9: =IF(OR(D71=0,E71=0,F71=0),0,IF(AND(AG$3>=G71,AG$3<H71),F71*MIN(12,E71-(AG$3-G71)*12)/E71,0)) | AH9: =IF(OR(D71=0,E71=0,F71=0),0,IF(AND(AH$3>=G71,AH$3<H71),F71*MIN(12,E71-(AH$3-G71)*12)/E71,0)) | AI9: =IF(OR(D71=0,E71=0,F71=0),0,IF(AND(AI$3>=G71,AI$3<H71),F71*MIN(12,E71-(AI$3-G71)*12)/E71,0)) | AJ9: =IF(OR(D71=0,E71=0,F71=0),0,IF(AND(AJ$3>=G71,AJ$3<H71),F71*MIN(12,E71-(AJ$3-G71)*12)/E71,0)) | AK9: =IF(OR(D71=0,E71=0,F71=0),0,IF(AND(AK$3>=G71,AK$3<H71),F71*MIN(12,E71-(AK$3-G71)*12)/E71,0)) | AL9: =IF(OR(D71=0,E71=0,F71=0),0,IF(AND(AL$3>=G71,AL$3<H71),F71*MIN(12,E71-(AL$3-G71)*12)/E71,0)) | AM9: =IF(OR(D71=0,E71=0,F71=0),0,IF(AND(AM$3>=G71,AM$3<H71),F71*MIN(12,E71-(AM$3-G71)*12)/E71,0)) | AN9: =IF(OR(D71=0,E71=0,F71=0),0,IF(AND(AN$3>=G71,AN$3<H71),F71*MIN(12,E71-(AN$3-G71)*12)/E71,0)) | AO9: =IF(OR(D71=0,E71=0,F71=0),0,IF(AND(AO$3>=G71,AO$3<H71),F71*MIN(12,E71-(AO$3-G71)*12)/E71,0)) | AP9: =IF(OR(D71=0,E71=0,F71=0),0,IF(AND(AP$3>=G71,AP$3<H71),F71*MIN(12,E71-(AP$3-G71)*12)/E71,0)) | AQ9: =IF(OR(D71=0,E71=0,F71=0),0,IF(AND(AQ$3>=G71,AQ$3<H71),F71*MIN(12,E71-(AQ$3-G71)*12)/E71,0)) | AR9: =IF(OR(D71=0,E71=0,F71=0),0,IF(AND(AR$3>=G71,AR$3<H71),F71*MIN(12,E71-(AR$3-G71)*12)/E71,0)) | AS9: =IF(OR(D71=0,E71=0,F71=0),0,IF(AND(AS$3>=G71,AS$3<H71),F71*MIN(12,E71-(AS$3-G71)*12)/E71,0)) | AT9: =IF(OR(D71=0,E71=0,F71=0),0,IF(AND(AT$3>=G71,AT$3<H71),F71*MIN(12,E71-(AT$3-G71)*12)/E71,0)) | AU9: =IF(OR(D71=0,E71=0,F71=0),0,IF(AND(AU$3>=G71,AU$3<H71),F71*MIN(12,E71-(AU$3-G71)*12)/E71,0)) | AV9: =IF(OR(D71=0,E71=0,F71=0),0,IF(AND(AV$3>=G71,AV$3<H71),F71*MIN(12,E71-(AV$3-G71)*12)/E71,0)) | AW9: =IF(OR(D71=0,E71=0,F71=0),0,IF(AND(AW$3>=G71,AW$3<H71),F71*MIN(12,E71-(AW$3-G71)*12)/E71,0)) | AX9: =IF(OR(D71=0,E71=0,F71=0),0,IF(AND(AX$3>=G71,AX$3<H71),F71*MIN(12,E71-(AX$3-G71)*12)/E71,0)) | AY9: =IF(OR(D71=0,E71=0,F71=0),0,IF(AND(AY$3>=G71,AY$3<H71),F71*MIN(12,E71-(AY$3-G71)*12)/E71,0)) | AZ9: =IF(OR(D71=0,E71=0,F71=0),0,IF(AND(AZ$3>=G71,AZ$3<H71),F71*MIN(12,E71-(AZ$3-G71)*12)/E71,0)) | BA9: =IF(OR(D71=0,E71=0,F71=0),0,IF(AND(BA$3>=G71,BA$3<H71),F71*MIN(12,E71-(BA$3-G71)*12)/E71,0)) | BB9: =IF(OR(D71=0,E71=0,F71=0),0,IF(AND(BB$3>=G71,BB$3<H71),F71*MIN(12,E71-(BB$3-G71)*12)/E71,0))
A10: =A72 | B10: =B72 | C10: =C72 | D10: =SUM(E10:BB10) | E10: =IF(OR(D72=0,E72=0,F72=0),0,IF(AND(E$3>=G72,E$3<H72),F72*MIN(12,E72-(E$3-G72)*12)/E72,0)) | F10: =IF(OR(D72=0,E72=0,F72=0),0,IF(AND(F$3>=G72,F$3<H72),F72*MIN(12,E72-(F$3-G72)*12)/E72,0)) | G10: =IF(OR(D72=0,E72=0,F72=0),0,IF(AND(G$3>=G72,G$3<H72),F72*MIN(12,E72-(G$3-G72)*12)/E72,0)) | H10: =IF(OR(D72=0,E72=0,F72=0),0,IF(AND(H$3>=G72,H$3<H72),F72*MIN(12,E72-(H$3-G72)*12)/E72,0)) | I10: =IF(OR(D72=0,E72=0,F72=0),0,IF(AND(I$3>=G72,I$3<H72),F72*MIN(12,E72-(I$3-G72)*12)/E72,0)) | J10: =IF(OR(D72=0,E72=0,F72=0),0,IF(AND(J$3>=G72,J$3<H72),F72*MIN(12,E72-(J$3-G72)*12)/E72,0)) | K10: =IF(OR(D72=0,E72=0,F72=0),0,IF(AND(K$3>=G72,K$3<H72),F72*MIN(12,E72-(K$3-G72)*12)/E72,0)) | L10: =IF(OR(D72=0,E72=0,F72=0),0,IF(AND(L$3>=G72,L$3<H72),F72*MIN(12,E72-(L$3-G72)*12)/E72,0)) | M10: =IF(OR(D72=0,E72=0,F72=0),0,IF(AND(M$3>=G72,M$3<H72),F72*MIN(12,E72-(M$3-G72)*12)/E72,0)) | N10: =IF(OR(D72=0,E72=0,F72=0),0,IF(AND(N$3>=G72,N$3<H72),F72*MIN(12,E72-(N$3-G72)*12)/E72,0)) | O10: =IF(OR(D72=0,E72=0,F72=0),0,IF(AND(O$3>=G72,O$3<H72),F72*MIN(12,E72-(O$3-G72)*12)/E72,0)) | P10: =IF(OR(D72=0,E72=0,F72=0),0,IF(AND(P$3>=G72,P$3<H72),F72*MIN(12,E72-(P$3-G72)*12)/E72,0)) | Q10: =IF(OR(D72=0,E72=0,F72=0),0,IF(AND(Q$3>=G72,Q$3<H72),F72*MIN(12,E72-(Q$3-G72)*12)/E72,0)) | R10: =IF(OR(D72=0,E72=0,F72=0),0,IF(AND(R$3>=G72,R$3<H72),F72*MIN(12,E72-(R$3-G72)*12)/E72,0)) | S10: =IF(OR(D72=0,E72=0,F72=0),0,IF(AND(S$3>=G72,S$3<H72),F72*MIN(12,E72-(S$3-G72)*12)/E72,0)) | T10: =IF(OR(D72=0,E72=0,F72=0),0,IF(AND(T$3>=G72,T$3<H72),F72*MIN(12,E72-(T$3-G72)*12)/E72,0)) | U10: =IF(OR(D72=0,E72=0,F72=0),0,IF(AND(U$3>=G72,U$3<H72),F72*MIN(12,E72-(U$3-G72)*12)/E72,0)) | V10: =IF(OR(D72=0,E72=0,F72=0),0,IF(AND(V$3>=G72,V$3<H72),F72*MIN(12,E72-(V$3-G72)*12)/E72,0)) | W10: =IF(OR(D72=0,E72=0,F72=0),0,IF(AND(W$3>=G72,W$3<H72),F72*MIN(12,E72-(W$3-G72)*12)/E72,0)) | X10: =IF(OR(D72=0,E72=0,F72=0),0,IF(AND(X$3>=G72,X$3<H72),F72*MIN(12,E72-(X$3-G72)*12)/E72,0)) | Y10: =IF(OR(D72=0,E72=0,F72=0),0,IF(AND(Y$3>=G72,Y$3<H72),F72*MIN(12,E72-(Y$3-G72)*12)/E72,0)) | Z10: =IF(OR(D72=0,E72=0,F72=0),0,IF(AND(Z$3>=G72,Z$3<H72),F72*MIN(12,E72-(Z$3-G72)*12)/E72,0)) | AA10: =IF(OR(D72=0,E72=0,F72=0),0,IF(AND(AA$3>=G72,AA$3<H72),F72*MIN(12,E72-(AA$3-G72)*12)/E72,0)) | AB10: =IF(OR(D72=0,E72=0,F72=0),0,IF(AND(AB$3>=G72,AB$3<H72),F72*MIN(12,E72-(AB$3-G72)*12)/E72,0)) | AC10: =IF(OR(D72=0,E72=0,F72=0),0,IF(AND(AC$3>=G72,AC$3<H72),F72*MIN(12,E72-(AC$3-G72)*12)/E72,0)) | AD10: =IF(OR(D72=0,E72=0,F72=0),0,IF(AND(AD$3>=G72,AD$3<H72),F72*MIN(12,E72-(AD$3-G72)*12)/E72,0)) | AE10: =IF(OR(D72=0,E72=0,F72=0),0,IF(AND(AE$3>=G72,AE$3<H72),F72*MIN(12,E72-(AE$3-G72)*12)/E72,0)) | AF10: =IF(OR(D72=0,E72=0,F72=0),0,IF(AND(AF$3>=G72,AF$3<H72),F72*MIN(12,E72-(AF$3-G72)*12)/E72,0)) | AG10: =IF(OR(D72=0,E72=0,F72=0),0,IF(AND(AG$3>=G72,AG$3<H72),F72*MIN(12,E72-(AG$3-G72)*12)/E72,0)) | AH10: =IF(OR(D72=0,E72=0,F72=0),0,IF(AND(AH$3>=G72,AH$3<H72),F72*MIN(12,E72-(AH$3-G72)*12)/E72,0)) | AI10: =IF(OR(D72=0,E72=0,F72=0),0,IF(AND(AI$3>=G72,AI$3<H72),F72*MIN(12,E72-(AI$3-G72)*12)/E72,0)) | AJ10: =IF(OR(D72=0,E72=0,F72=0),0,IF(AND(AJ$3>=G72,AJ$3<H72),F72*MIN(12,E72-(AJ$3-G72)*12)/E72,0)) | AK10: =IF(OR(D72=0,E72=0,F72=0),0,IF(AND(AK$3>=G72,AK$3<H72),F72*MIN(12,E72-(AK$3-G72)*12)/E72,0)) | AL10: =IF(OR(D72=0,E72=0,F72=0),0,IF(AND(AL$3>=G72,AL$3<H72),F72*MIN(12,E72-(AL$3-G72)*12)/E72,0)) | AM10: =IF(OR(D72=0,E72=0,F72=0),0,IF(AND(AM$3>=G72,AM$3<H72),F72*MIN(12,E72-(AM$3-G72)*12)/E72,0)) | AN10: =IF(OR(D72=0,E72=0,F72=0),0,IF(AND(AN$3>=G72,AN$3<H72),F72*MIN(12,E72-(AN$3-G72)*12)/E72,0)) | AO10: =IF(OR(D72=0,E72=0,F72=0),0,IF(AND(AO$3>=G72,AO$3<H72),F72*MIN(12,E72-(AO$3-G72)*12)/E72,0)) | AP10: =IF(OR(D72=0,E72=0,F72=0),0,IF(AND(AP$3>=G72,AP$3<H72),F72*MIN(12,E72-(AP$3-G72)*12)/E72,0)) | AQ10: =IF(OR(D72=0,E72=0,F72=0),0,IF(AND(AQ$3>=G72,AQ$3<H72),F72*MIN(12,E72-(AQ$3-G72)*12)/E72,0)) | AR10: =IF(OR(D72=0,E72=0,F72=0),0,IF(AND(AR$3>=G72,AR$3<H72),F72*MIN(12,E72-(AR$3-G72)*12)/E72,0)) | AS10: =IF(OR(D72=0,E72=0,F72=0),0,IF(AND(AS$3>=G72,AS$3<H72),F72*MIN(12,E72-(AS$3-G72)*12)/E72,0)) | AT10: =IF(OR(D72=0,E72=0,F72=0),0,IF(AND(AT$3>=G72,AT$3<H72),F72*MIN(12,E72-(AT$3-G72)*12)/E72,0)) | AU10: =IF(OR(D72=0,E72=0,F72=0),0,IF(AND(AU$3>=G72,AU$3<H72),F72*MIN(12,E72-(AU$3-G72)*12)/E72,0)) | AV10: =IF(OR(D72=0,E72=0,F72=0),0,IF(AND(AV$3>=G72,AV$3<H72),F72*MIN(12,E72-(AV$3-G72)*12)/E72,0)) | AW10: =IF(OR(D72=0,E72=0,F72=0),0,IF(AND(AW$3>=G72,AW$3<H72),F72*MIN(12,E72-(AW$3-G72)*12)/E72,0)) | AX10: =IF(OR(D72=0,E72=0,F72=0),0,IF(AND(AX$3>=G72,AX$3<H72),F72*MIN(12,E72-(AX$3-G72)*12)/E72,0)) | AY10: =IF(OR(D72=0,E72=0,F72=0),0,IF(AND(AY$3>=G72,AY$3<H72),F72*MIN(12,E72-(AY$3-G72)*12)/E72,0)) | AZ10: =IF(OR(D72=0,E72=0,F72=0),0,IF(AND(AZ$3>=G72,AZ$3<H72),F72*MIN(12,E72-(AZ$3-G72)*12)/E72,0)) | BA10: =IF(OR(D72=0,E72=0,F72=0),0,IF(AND(BA$3>=G72,BA$3<H72),F72*MIN(12,E72-(BA$3-G72)*12)/E72,0)) | BB10: =IF(OR(D72=0,E72=0,F72=0),0,IF(AND(BB$3>=G72,BB$3<H72),F72*MIN(12,E72-(BB$3-G72)*12)/E72,0))
A11: =A73 | B11: =B73 | C11: =C73 | D11: =SUM(E11:BB11) | E11: =IF(OR(D73=0,E73=0,F73=0),0,IF(AND(E$3>=G73,E$3<H73),F73*MIN(12,E73-(E$3-G73)*12)/E73,0)) | F11: =IF(OR(D73=0,E73=0,F73=0),0,IF(AND(F$3>=G73,F$3<H73),F73*MIN(12,E73-(F$3-G73)*12)/E73,0)) | G11: =IF(OR(D73=0,E73=0,F73=0),0,IF(AND(G$3>=G73,G$3<H73),F73*MIN(12,E73-(G$3-G73)*12)/E73,0)) | H11: =IF(OR(D73=0,E73=0,F73=0),0,IF(AND(H$3>=G73,H$3<H73),F73*MIN(12,E73-(H$3-G73)*12)/E73,0)) | I11: =IF(OR(D73=0,E73=0,F73=0),0,IF(AND(I$3>=G73,I$3<H73),F73*MIN(12,E73-(I$3-G73)*12)/E73,0)) | J11: =IF(OR(D73=0,E73=0,F73=0),0,IF(AND(J$3>=G73,J$3<H73),F73*MIN(12,E73-(J$3-G73)*12)/E73,0)) | K11: =IF(OR(D73=0,E73=0,F73=0),0,IF(AND(K$3>=G73,K$3<H73),F73*MIN(12,E73-(K$3-G73)*12)/E73,0)) | L11: =IF(OR(D73=0,E73=0,F73=0),0,IF(AND(L$3>=G73,L$3<H73),F73*MIN(12,E73-(L$3-G73)*12)/E73,0)) | M11: =IF(OR(D73=0,E73=0,F73=0),0,IF(AND(M$3>=G73,M$3<H73),F73*MIN(12,E73-(M$3-G73)*12)/E73,0)) | N11: =IF(OR(D73=0,E73=0,F73=0),0,IF(AND(N$3>=G73,N$3<H73),F73*MIN(12,E73-(N$3-G73)*12)/E73,0)) | O11: =IF(OR(D73=0,E73=0,F73=0),0,IF(AND(O$3>=G73,O$3<H73),F73*MIN(12,E73-(O$3-G73)*12)/E73,0)) | P11: =IF(OR(D73=0,E73=0,F73=0),0,IF(AND(P$3>=G73,P$3<H73),F73*MIN(12,E73-(P$3-G73)*12)/E73,0)) | Q11: =IF(OR(D73=0,E73=0,F73=0),0,IF(AND(Q$3>=G73,Q$3<H73),F73*MIN(12,E73-(Q$3-G73)*12)/E73,0)) | R11: =IF(OR(D73=0,E73=0,F73=0),0,IF(AND(R$3>=G73,R$3<H73),F73*MIN(12,E73-(R$3-G73)*12)/E73,0)) | S11: =IF(OR(D73=0,E73=0,F73=0),0,IF(AND(S$3>=G73,S$3<H73),F73*MIN(12,E73-(S$3-G73)*12)/E73,0)) | T11: =IF(OR(D73=0,E73=0,F73=0),0,IF(AND(T$3>=G73,T$3<H73),F73*MIN(12,E73-(T$3-G73)*12)/E73,0)) | U11: =IF(OR(D73=0,E73=0,F73=0),0,IF(AND(U$3>=G73,U$3<H73),F73*MIN(12,E73-(U$3-G73)*12)/E73,0)) | V11: =IF(OR(D73=0,E73=0,F73=0),0,IF(AND(V$3>=G73,V$3<H73),F73*MIN(12,E73-(V$3-G73)*12)/E73,0)) | W11: =IF(OR(D73=0,E73=0,F73=0),0,IF(AND(W$3>=G73,W$3<H73),F73*MIN(12,E73-(W$3-G73)*12)/E73,0)) | X11: =IF(OR(D73=0,E73=0,F73=0),0,IF(AND(X$3>=G73,X$3<H73),F73*MIN(12,E73-(X$3-G73)*12)/E73,0)) | Y11: =IF(OR(D73=0,E73=0,F73=0),0,IF(AND(Y$3>=G73,Y$3<H73),F73*MIN(12,E73-(Y$3-G73)*12)/E73,0)) | Z11: =IF(OR(D73=0,E73=0,F73=0),0,IF(AND(Z$3>=G73,Z$3<H73),F73*MIN(12,E73-(Z$3-G73)*12)/E73,0)) | AA11: =IF(OR(D73=0,E73=0,F73=0),0,IF(AND(AA$3>=G73,AA$3<H73),F73*MIN(12,E73-(AA$3-G73)*12)/E73,0)) | AB11: =IF(OR(D73=0,E73=0,F73=0),0,IF(AND(AB$3>=G73,AB$3<H73),F73*MIN(12,E73-(AB$3-G73)*12)/E73,0)) | AC11: =IF(OR(D73=0,E73=0,F73=0),0,IF(AND(AC$3>=G73,AC$3<H73),F73*MIN(12,E73-(AC$3-G73)*12)/E73,0)) | AD11: =IF(OR(D73=0,E73=0,F73=0),0,IF(AND(AD$3>=G73,AD$3<H73),F73*MIN(12,E73-(AD$3-G73)*12)/E73,0)) | AE11: =IF(OR(D73=0,E73=0,F73=0),0,IF(AND(AE$3>=G73,AE$3<H73),F73*MIN(12,E73-(AE$3-G73)*12)/E73,0)) | AF11: =IF(OR(D73=0,E73=0,F73=0),0,IF(AND(AF$3>=G73,AF$3<H73),F73*MIN(12,E73-(AF$3-G73)*12)/E73,0)) | AG11: =IF(OR(D73=0,E73=0,F73=0),0,IF(AND(AG$3>=G73,AG$3<H73),F73*MIN(12,E73-(AG$3-G73)*12)/E73,0)) | AH11: =IF(OR(D73=0,E73=0,F73=0),0,IF(AND(AH$3>=G73,AH$3<H73),F73*MIN(12,E73-(AH$3-G73)*12)/E73,0)) | AI11: =IF(OR(D73=0,E73=0,F73=0),0,IF(AND(AI$3>=G73,AI$3<H73),F73*MIN(12,E73-(AI$3-G73)*12)/E73,0)) | AJ11: =IF(OR(D73=0,E73=0,F73=0),0,IF(AND(AJ$3>=G73,AJ$3<H73),F73*MIN(12,E73-(AJ$3-G73)*12)/E73,0)) | AK11: =IF(OR(D73=0,E73=0,F73=0),0,IF(AND(AK$3>=G73,AK$3<H73),F73*MIN(12,E73-(AK$3-G73)*12)/E73,0)) | AL11: =IF(OR(D73=0,E73=0,F73=0),0,IF(AND(AL$3>=G73,AL$3<H73),F73*MIN(12,E73-(AL$3-G73)*12)/E73,0)) | AM11: =IF(OR(D73=0,E73=0,F73=0),0,IF(AND(AM$3>=G73,AM$3<H73),F73*MIN(12,E73-(AM$3-G73)*12)/E73,0)) | AN11: =IF(OR(D73=0,E73=0,F73=0),0,IF(AND(AN$3>=G73,AN$3<H73),F73*MIN(12,E73-(AN$3-G73)*12)/E73,0)) | AO11: =IF(OR(D73=0,E73=0,F73=0),0,IF(AND(AO$3>=G73,AO$3<H73),F73*MIN(12,E73-(AO$3-G73)*12)/E73,0)) | AP11: =IF(OR(D73=0,E73=0,F73=0),0,IF(AND(AP$3>=G73,AP$3<H73),F73*MIN(12,E73-(AP$3-G73)*12)/E73,0)) | AQ11: =IF(OR(D73=0,E73=0,F73=0),0,IF(AND(AQ$3>=G73,AQ$3<H73),F73*MIN(12,E73-(AQ$3-G73)*12)/E73,0)) | AR11: =IF(OR(D73=0,E73=0,F73=0),0,IF(AND(AR$3>=G73,AR$3<H73),F73*MIN(12,E73-(AR$3-G73)*12)/E73,0)) | AS11: =IF(OR(D73=0,E73=0,F73=0),0,IF(AND(AS$3>=G73,AS$3<H73),F73*MIN(12,E73-(AS$3-G73)*12)/E73,0)) | AT11: =IF(OR(D73=0,E73=0,F73=0),0,IF(AND(AT$3>=G73,AT$3<H73),F73*MIN(12,E73-(AT$3-G73)*12)/E73,0)) | AU11: =IF(OR(D73=0,E73=0,F73=0),0,IF(AND(AU$3>=G73,AU$3<H73),F73*MIN(12,E73-(AU$3-G73)*12)/E73,0)) | AV11: =IF(OR(D73=0,E73=0,F73=0),0,IF(AND(AV$3>=G73,AV$3<H73),F73*MIN(12,E73-(AV$3-G73)*12)/E73,0)) | AW11: =IF(OR(D73=0,E73=0,F73=0),0,IF(AND(AW$3>=G73,AW$3<H73),F73*MIN(12,E73-(AW$3-G73)*12)/E73,0)) | AX11: =IF(OR(D73=0,E73=0,F73=0),0,IF(AND(AX$3>=G73,AX$3<H73),F73*MIN(12,E73-(AX$3-G73)*12)/E73,0)) | AY11: =IF(OR(D73=0,E73=0,F73=0),0,IF(AND(AY$3>=G73,AY$3<H73),F73*MIN(12,E73-(AY$3-G73)*12)/E73,0)) | AZ11: =IF(OR(D73=0,E73=0,F73=0),0,IF(AND(AZ$3>=G73,AZ$3<H73),F73*MIN(12,E73-(AZ$3-G73)*12)/E73,0)) | BA11: =IF(OR(D73=0,E73=0,F73=0),0,IF(AND(BA$3>=G73,BA$3<H73),F73*MIN(12,E73-(BA$3-G73)*12)/E73,0)) | BB11: =IF(OR(D73=0,E73=0,F73=0),0,IF(AND(BB$3>=G73,BB$3<H73),F73*MIN(12,E73-(BB$3-G73)*12)/E73,0))
A12: =A74 | B12: =B74 | C12: =C74 | D12: =SUM(E12:BB12) | E12: =IF(OR(D74=0,E74=0,F74=0),0,IF(AND(E$3>=G74,E$3<H74),F74*MIN(12,E74-(E$3-G74)*12)/E74,0)) | F12: =IF(OR(D74=0,E74=0,F74=0),0,IF(AND(F$3>=G74,F$3<H74),F74*MIN(12,E74-(F$3-G74)*12)/E74,0)) | G12: =IF(OR(D74=0,E74=0,F74=0),0,IF(AND(G$3>=G74,G$3<H74),F74*MIN(12,E74-(G$3-G74)*12)/E74,0)) | H12: =IF(OR(D74=0,E74=0,F74=0),0,IF(AND(H$3>=G74,H$3<H74),F74*MIN(12,E74-(H$3-G74)*12)/E74,0)) | I12: =IF(OR(D74=0,E74=0,F74=0),0,IF(AND(I$3>=G74,I$3<H74),F74*MIN(12,E74-(I$3-G74)*12)/E74,0)) | J12: =IF(OR(D74=0,E74=0,F74=0),0,IF(AND(J$3>=G74,J$3<H74),F74*MIN(12,E74-(J$3-G74)*12)/E74,0)) | K12: =IF(OR(D74=0,E74=0,F74=0),0,IF(AND(K$3>=G74,K$3<H74),F74*MIN(12,E74-(K$3-G74)*12)/E74,0)) | L12: =IF(OR(D74=0,E74=0,F74=0),0,IF(AND(L$3>=G74,L$3<H74),F74*MIN(12,E74-(L$3-G74)*12)/E74,0)) | M12: =IF(OR(D74=0,E74=0,F74=0),0,IF(AND(M$3>=G74,M$3<H74),F74*MIN(12,E74-(M$3-G74)*12)/E74,0)) | N12: =IF(OR(D74=0,E74=0,F74=0),0,IF(AND(N$3>=G74,N$3<H74),F74*MIN(12,E74-(N$3-G74)*12)/E74,0)) | O12: =IF(OR(D74=0,E74=0,F74=0),0,IF(AND(O$3>=G74,O$3<H74),F74*MIN(12,E74-(O$3-G74)*12)/E74,0)) | P12: =IF(OR(D74=0,E74=0,F74=0),0,IF(AND(P$3>=G74,P$3<H74),F74*MIN(12,E74-(P$3-G74)*12)/E74,0)) | Q12: =IF(OR(D74=0,E74=0,F74=0),0,IF(AND(Q$3>=G74,Q$3<H74),F74*MIN(12,E74-(Q$3-G74)*12)/E74,0)) | R12: =IF(OR(D74=0,E74=0,F74=0),0,IF(AND(R$3>=G74,R$3<H74),F74*MIN(12,E74-(R$3-G74)*12)/E74,0)) | S12: =IF(OR(D74=0,E74=0,F74=0),0,IF(AND(S$3>=G74,S$3<H74),F74*MIN(12,E74-(S$3-G74)*12)/E74,0)) | T12: =IF(OR(D74=0,E74=0,F74=0),0,IF(AND(T$3>=G74,T$3<H74),F74*MIN(12,E74-(T$3-G74)*12)/E74,0)) | U12: =IF(OR(D74=0,E74=0,F74=0),0,IF(AND(U$3>=G74,U$3<H74),F74*MIN(12,E74-(U$3-G74)*12)/E74,0)) | V12: =IF(OR(D74=0,E74=0,F74=0),0,IF(AND(V$3>=G74,V$3<H74),F74*MIN(12,E74-(V$3-G74)*12)/E74,0)) | W12: =IF(OR(D74=0,E74=0,F74=0),0,IF(AND(W$3>=G74,W$3<H74),F74*MIN(12,E74-(W$3-G74)*12)/E74,0)) | X12: =IF(OR(D74=0,E74=0,F74=0),0,IF(AND(X$3>=G74,X$3<H74),F74*MIN(12,E74-(X$3-G74)*12)/E74,0)) | Y12: =IF(OR(D74=0,E74=0,F74=0),0,IF(AND(Y$3>=G74,Y$3<H74),F74*MIN(12,E74-(Y$3-G74)*12)/E74,0)) | Z12: =IF(OR(D74=0,E74=0,F74=0),0,IF(AND(Z$3>=G74,Z$3<H74),F74*MIN(12,E74-(Z$3-G74)*12)/E74,0)) | AA12: =IF(OR(D74=0,E74=0,F74=0),0,IF(AND(AA$3>=G74,AA$3<H74),F74*MIN(12,E74-(AA$3-G74)*12)/E74,0)) | AB12: =IF(OR(D74=0,E74=0,F74=0),0,IF(AND(AB$3>=G74,AB$3<H74),F74*MIN(12,E74-(AB$3-G74)*12)/E74,0)) | AC12: =IF(OR(D74=0,E74=0,F74=0),0,IF(AND(AC$3>=G74,AC$3<H74),F74*MIN(12,E74-(AC$3-G74)*12)/E74,0)) | AD12: =IF(OR(D74=0,E74=0,F74=0),0,IF(AND(AD$3>=G74,AD$3<H74),F74*MIN(12,E74-(AD$3-G74)*12)/E74,0)) | AE12: =IF(OR(D74=0,E74=0,F74=0),0,IF(AND(AE$3>=G74,AE$3<H74),F74*MIN(12,E74-(AE$3-G74)*12)/E74,0)) | AF12: =IF(OR(D74=0,E74=0,F74=0),0,IF(AND(AF$3>=G74,AF$3<H74),F74*MIN(12,E74-(AF$3-G74)*12)/E74,0)) | AG12: =IF(OR(D74=0,E74=0,F74=0),0,IF(AND(AG$3>=G74,AG$3<H74),F74*MIN(12,E74-(AG$3-G74)*12)/E74,0)) | AH12: =IF(OR(D74=0,E74=0,F74=0),0,IF(AND(AH$3>=G74,AH$3<H74),F74*MIN(12,E74-(AH$3-G74)*12)/E74,0)) | AI12: =IF(OR(D74=0,E74=0,F74=0),0,IF(AND(AI$3>=G74,AI$3<H74),F74*MIN(12,E74-(AI$3-G74)*12)/E74,0)) | AJ12: =IF(OR(D74=0,E74=0,F74=0),0,IF(AND(AJ$3>=G74,AJ$3<H74),F74*MIN(12,E74-(AJ$3-G74)*12)/E74,0)) | AK12: =IF(OR(D74=0,E74=0,F74=0),0,IF(AND(AK$3>=G74,AK$3<H74),F74*MIN(12,E74-(AK$3-G74)*12)/E74,0)) | AL12: =IF(OR(D74=0,E74=0,F74=0),0,IF(AND(AL$3>=G74,AL$3<H74),F74*MIN(12,E74-(AL$3-G74)*12)/E74,0)) | AM12: =IF(OR(D74=0,E74=0,F74=0),0,IF(AND(AM$3>=G74,AM$3<H74),F74*MIN(12,E74-(AM$3-G74)*12)/E74,0)) | AN12: =IF(OR(D74=0,E74=0,F74=0),0,IF(AND(AN$3>=G74,AN$3<H74),F74*MIN(12,E74-(AN$3-G74)*12)/E74,0)) | AO12: =IF(OR(D74=0,E74=0,F74=0),0,IF(AND(AO$3>=G74,AO$3<H74),F74*MIN(12,E74-(AO$3-G74)*12)/E74,0)) | AP12: =IF(OR(D74=0,E74=0,F74=0),0,IF(AND(AP$3>=G74,AP$3<H74),F74*MIN(12,E74-(AP$3-G74)*12)/E74,0)) | AQ12: =IF(OR(D74=0,E74=0,F74=0),0,IF(AND(AQ$3>=G74,AQ$3<H74),F74*MIN(12,E74-(AQ$3-G74)*12)/E74,0)) | AR12: =IF(OR(D74=0,E74=0,F74=0),0,IF(AND(AR$3>=G74,AR$3<H74),F74*MIN(12,E74-(AR$3-G74)*12)/E74,0)) | AS12: =IF(OR(D74=0,E74=0,F74=0),0,IF(AND(AS$3>=G74,AS$3<H74),F74*MIN(12,E74-(AS$3-G74)*12)/E74,0)) | AT12: =IF(OR(D74=0,E74=0,F74=0),0,IF(AND(AT$3>=G74,AT$3<H74),F74*MIN(12,E74-(AT$3-G74)*12)/E74,0)) | AU12: =IF(OR(D74=0,E74=0,F74=0),0,IF(AND(AU$3>=G74,AU$3<H74),F74*MIN(12,E74-(AU$3-G74)*12)/E74,0)) | AV12: =IF(OR(D74=0,E74=0,F74=0),0,IF(AND(AV$3>=G74,AV$3<H74),F74*MIN(12,E74-(AV$3-G74)*12)/E74,0)) | AW12: =IF(OR(D74=0,E74=0,F74=0),0,IF(AND(AW$3>=G74,AW$3<H74),F74*MIN(12,E74-(AW$3-G74)*12)/E74,0)) | AX12: =IF(OR(D74=0,E74=0,F74=0),0,IF(AND(AX$3>=G74,AX$3<H74),F74*MIN(12,E74-(AX$3-G74)*12)/E74,0)) | AY12: =IF(OR(D74=0,E74=0,F74=0),0,IF(AND(AY$3>=G74,AY$3<H74),F74*MIN(12,E74-(AY$3-G74)*12)/E74,0)) | AZ12: =IF(OR(D74=0,E74=0,F74=0),0,IF(AND(AZ$3>=G74,AZ$3<H74),F74*MIN(12,E74-(AZ$3-G74)*12)/E74,0)) | BA12: =IF(OR(D74=0,E74=0,F74=0),0,IF(AND(BA$3>=G74,BA$3<H74),F74*MIN(12,E74-(BA$3-G74)*12)/E74,0)) | BB12: =IF(OR(D74=0,E74=0,F74=0),0,IF(AND(BB$3>=G74,BB$3<H74),F74*MIN(12,E74-(BB$3-G74)*12)/E74,0))
A13: =A75 | B13: =B75 | C13: =C75 | D13: =SUM(E13:BB13) | E13: =IF(OR(D75=0,E75=0,F75=0),0,IF(AND(E$3>=G75,E$3<H75),F75*MIN(12,E75-(E$3-G75)*12)/E75,0)) | F13: =IF(OR(D75=0,E75=0,F75=0),0,IF(AND(F$3>=G75,F$3<H75),F75*MIN(12,E75-(F$3-G75)*12)/E75,0)) | G13: =IF(OR(D75=0,E75=0,F75=0),0,IF(AND(G$3>=G75,G$3<H75),F75*MIN(12,E75-(G$3-G75)*12)/E75,0)) | H13: =IF(OR(D75=0,E75=0,F75=0),0,IF(AND(H$3>=G75,H$3<H75),F75*MIN(12,E75-(H$3-G75)*12)/E75,0)) | I13: =IF(OR(D75=0,E75=0,F75=0),0,IF(AND(I$3>=G75,I$3<H75),F75*MIN(12,E75-(I$3-G75)*12)/E75,0)) | J13: =IF(OR(D75=0,E75=0,F75=0),0,IF(AND(J$3>=G75,J$3<H75),F75*MIN(12,E75-(J$3-G75)*12)/E75,0)) | K13: =IF(OR(D75=0,E75=0,F75=0),0,IF(AND(K$3>=G75,K$3<H75),F75*MIN(12,E75-(K$3-G75)*12)/E75,0)) | L13: =IF(OR(D75=0,E75=0,F75=0),0,IF(AND(L$3>=G75,L$3<H75),F75*MIN(12,E75-(L$3-G75)*12)/E75,0)) | M13: =IF(OR(D75=0,E75=0,F75=0),0,IF(AND(M$3>=G75,M$3<H75),F75*MIN(12,E75-(M$3-G75)*12)/E75,0)) | N13: =IF(OR(D75=0,E75=0,F75=0),0,IF(AND(N$3>=G75,N$3<H75),F75*MIN(12,E75-(N$3-G75)*12)/E75,0)) | O13: =IF(OR(D75=0,E75=0,F75=0),0,IF(AND(O$3>=G75,O$3<H75),F75*MIN(12,E75-(O$3-G75)*12)/E75,0)) | P13: =IF(OR(D75=0,E75=0,F75=0),0,IF(AND(P$3>=G75,P$3<H75),F75*MIN(12,E75-(P$3-G75)*12)/E75,0)) | Q13: =IF(OR(D75=0,E75=0,F75=0),0,IF(AND(Q$3>=G75,Q$3<H75),F75*MIN(12,E75-(Q$3-G75)*12)/E75,0)) | R13: =IF(OR(D75=0,E75=0,F75=0),0,IF(AND(R$3>=G75,R$3<H75),F75*MIN(12,E75-(R$3-G75)*12)/E75,0)) | S13: =IF(OR(D75=0,E75=0,F75=0),0,IF(AND(S$3>=G75,S$3<H75),F75*MIN(12,E75-(S$3-G75)*12)/E75,0)) | T13: =IF(OR(D75=0,E75=0,F75=0),0,IF(AND(T$3>=G75,T$3<H75),F75*MIN(12,E75-(T$3-G75)*12)/E75,0)) | U13: =IF(OR(D75=0,E75=0,F75=0),0,IF(AND(U$3>=G75,U$3<H75),F75*MIN(12,E75-(U$3-G75)*12)/E75,0)) | V13: =IF(OR(D75=0,E75=0,F75=0),0,IF(AND(V$3>=G75,V$3<H75),F75*MIN(12,E75-(V$3-G75)*12)/E75,0)) | W13: =IF(OR(D75=0,E75=0,F75=0),0,IF(AND(W$3>=G75,W$3<H75),F75*MIN(12,E75-(W$3-G75)*12)/E75,0)) | X13: =IF(OR(D75=0,E75=0,F75=0),0,IF(AND(X$3>=G75,X$3<H75),F75*MIN(12,E75-(X$3-G75)*12)/E75,0)) | Y13: =IF(OR(D75=0,E75=0,F75=0),0,IF(AND(Y$3>=G75,Y$3<H75),F75*MIN(12,E75-(Y$3-G75)*12)/E75,0)) | Z13: =IF(OR(D75=0,E75=0,F75=0),0,IF(AND(Z$3>=G75,Z$3<H75),F75*MIN(12,E75-(Z$3-G75)*12)/E75,0)) | AA13: =IF(OR(D75=0,E75=0,F75=0),0,IF(AND(AA$3>=G75,AA$3<H75),F75*MIN(12,E75-(AA$3-G75)*12)/E75,0)) | AB13: =IF(OR(D75=0,E75=0,F75=0),0,IF(AND(AB$3>=G75,AB$3<H75),F75*MIN(12,E75-(AB$3-G75)*12)/E75,0)) | AC13: =IF(OR(D75=0,E75=0,F75=0),0,IF(AND(AC$3>=G75,AC$3<H75),F75*MIN(12,E75-(AC$3-G75)*12)/E75,0)) | AD13: =IF(OR(D75=0,E75=0,F75=0),0,IF(AND(AD$3>=G75,AD$3<H75),F75*MIN(12,E75-(AD$3-G75)*12)/E75,0)) | AE13: =IF(OR(D75=0,E75=0,F75=0),0,IF(AND(AE$3>=G75,AE$3<H75),F75*MIN(12,E75-(AE$3-G75)*12)/E75,0)) | AF13: =IF(OR(D75=0,E75=0,F75=0),0,IF(AND(AF$3>=G75,AF$3<H75),F75*MIN(12,E75-(AF$3-G75)*12)/E75,0)) | AG13: =IF(OR(D75=0,E75=0,F75=0),0,IF(AND(AG$3>=G75,AG$3<H75),F75*MIN(12,E75-(AG$3-G75)*12)/E75,0)) | AH13: =IF(OR(D75=0,E75=0,F75=0),0,IF(AND(AH$3>=G75,AH$3<H75),F75*MIN(12,E75-(AH$3-G75)*12)/E75,0)) | AI13: =IF(OR(D75=0,E75=0,F75=0),0,IF(AND(AI$3>=G75,AI$3<H75),F75*MIN(12,E75-(AI$3-G75)*12)/E75,0)) | AJ13: =IF(OR(D75=0,E75=0,F75=0),0,IF(AND(AJ$3>=G75,AJ$3<H75),F75*MIN(12,E75-(AJ$3-G75)*12)/E75,0)) | AK13: =IF(OR(D75=0,E75=0,F75=0),0,IF(AND(AK$3>=G75,AK$3<H75),F75*MIN(12,E75-(AK$3-G75)*12)/E75,0)) | AL13: =IF(OR(D75=0,E75=0,F75=0),0,IF(AND(AL$3>=G75,AL$3<H75),F75*MIN(12,E75-(AL$3-G75)*12)/E75,0)) | AM13: =IF(OR(D75=0,E75=0,F75=0),0,IF(AND(AM$3>=G75,AM$3<H75),F75*MIN(12,E75-(AM$3-G75)*12)/E75,0)) | AN13: =IF(OR(D75=0,E75=0,F75=0),0,IF(AND(AN$3>=G75,AN$3<H75),F75*MIN(12,E75-(AN$3-G75)*12)/E75,0)) | AO13: =IF(OR(D75=0,E75=0,F75=0),0,IF(AND(AO$3>=G75,AO$3<H75),F75*MIN(12,E75-(AO$3-G75)*12)/E75,0)) | AP13: =IF(OR(D75=0,E75=0,F75=0),0,IF(AND(AP$3>=G75,AP$3<H75),F75*MIN(12,E75-(AP$3-G75)*12)/E75,0)) | AQ13: =IF(OR(D75=0,E75=0,F75=0),0,IF(AND(AQ$3>=G75,AQ$3<H75),F75*MIN(12,E75-(AQ$3-G75)*12)/E75,0)) | AR13: =IF(OR(D75=0,E75=0,F75=0),0,IF(AND(AR$3>=G75,AR$3<H75),F75*MIN(12,E75-(AR$3-G75)*12)/E75,0)) | AS13: =IF(OR(D75=0,E75=0,F75=0),0,IF(AND(AS$3>=G75,AS$3<H75),F75*MIN(12,E75-(AS$3-G75)*12)/E75,0)) | AT13: =IF(OR(D75=0,E75=0,F75=0),0,IF(AND(AT$3>=G75,AT$3<H75),F75*MIN(12,E75-(AT$3-G75)*12)/E75,0)) | AU13: =IF(OR(D75=0,E75=0,F75=0),0,IF(AND(AU$3>=G75,AU$3<H75),F75*MIN(12,E75-(AU$3-G75)*12)/E75,0)) | AV13: =IF(OR(D75=0,E75=0,F75=0),0,IF(AND(AV$3>=G75,AV$3<H75),F75*MIN(12,E75-(AV$3-G75)*12)/E75,0)) | AW13: =IF(OR(D75=0,E75=0,F75=0),0,IF(AND(AW$3>=G75,AW$3<H75),F75*MIN(12,E75-(AW$3-G75)*12)/E75,0)) | AX13: =IF(OR(D75=0,E75=0,F75=0),0,IF(AND(AX$3>=G75,AX$3<H75),F75*MIN(12,E75-(AX$3-G75)*12)/E75,0)) | AY13: =IF(OR(D75=0,E75=0,F75=0),0,IF(AND(AY$3>=G75,AY$3<H75),F75*MIN(12,E75-(AY$3-G75)*12)/E75,0)) | AZ13: =IF(OR(D75=0,E75=0,F75=0),0,IF(AND(AZ$3>=G75,AZ$3<H75),F75*MIN(12,E75-(AZ$3-G75)*12)/E75,0)) | BA13: =IF(OR(D75=0,E75=0,F75=0),0,IF(AND(BA$3>=G75,BA$3<H75),F75*MIN(12,E75-(BA$3-G75)*12)/E75,0)) | BB13: =IF(OR(D75=0,E75=0,F75=0),0,IF(AND(BB$3>=G75,BB$3<H75),F75*MIN(12,E75-(BB$3-G75)*12)/E75,0))
A14: =A76 | B14: =B76 | C14: =C76 | D14: =SUM(E14:BB14) | E14: =IF(OR(D76=0,E76=0,F76=0),0,IF(AND(E$3>=G76,E$3<H76),F76*MIN(12,E76-(E$3-G76)*12)/E76,0)) | F14: =IF(OR(D76=0,E76=0,F76=0),0,IF(AND(F$3>=G76,F$3<H76),F76*MIN(12,E76-(F$3-G76)*12)/E76,0)) | G14: =IF(OR(D76=0,E76=0,F76=0),0,IF(AND(G$3>=G76,G$3<H76),F76*MIN(12,E76-(G$3-G76)*12)/E76,0)) | H14: =IF(OR(D76=0,E76=0,F76=0),0,IF(AND(H$3>=G76,H$3<H76),F76*MIN(12,E76-(H$3-G76)*12)/E76,0)) | I14: =IF(OR(D76=0,E76=0,F76=0),0,IF(AND(I$3>=G76,I$3<H76),F76*MIN(12,E76-(I$3-G76)*12)/E76,0)) | J14: =IF(OR(D76=0,E76=0,F76=0),0,IF(AND(J$3>=G76,J$3<H76),F76*MIN(12,E76-(J$3-G76)*12)/E76,0)) | K14: =IF(OR(D76=0,E76=0,F76=0),0,IF(AND(K$3>=G76,K$3<H76),F76*MIN(12,E76-(K$3-G76)*12)/E76,0)) | L14: =IF(OR(D76=0,E76=0,F76=0),0,IF(AND(L$3>=G76,L$3<H76),F76*MIN(12,E76-(L$3-G76)*12)/E76,0)) | M14: =IF(OR(D76=0,E76=0,F76=0),0,IF(AND(M$3>=G76,M$3<H76),F76*MIN(12,E76-(M$3-G76)*12)/E76,0)) | N14: =IF(OR(D76=0,E76=0,F76=0),0,IF(AND(N$3>=G76,N$3<H76),F76*MIN(12,E76-(N$3-G76)*12)/E76,0)) | O14: =IF(OR(D76=0,E76=0,F76=0),0,IF(AND(O$3>=G76,O$3<H76),F76*MIN(12,E76-(O$3-G76)*12)/E76,0)) | P14: =IF(OR(D76=0,E76=0,F76=0),0,IF(AND(P$3>=G76,P$3<H76),F76*MIN(12,E76-(P$3-G76)*12)/E76,0)) | Q14: =IF(OR(D76=0,E76=0,F76=0),0,IF(AND(Q$3>=G76,Q$3<H76),F76*MIN(12,E76-(Q$3-G76)*12)/E76,0)) | R14: =IF(OR(D76=0,E76=0,F76=0),0,IF(AND(R$3>=G76,R$3<H76),F76*MIN(12,E76-(R$3-G76)*12)/E76,0)) | S14: =IF(OR(D76=0,E76=0,F76=0),0,IF(AND(S$3>=G76,S$3<H76),F76*MIN(12,E76-(S$3-G76)*12)/E76,0)) | T14: =IF(OR(D76=0,E76=0,F76=0),0,IF(AND(T$3>=G76,T$3<H76),F76*MIN(12,E76-(T$3-G76)*12)/E76,0)) | U14: =IF(OR(D76=0,E76=0,F76=0),0,IF(AND(U$3>=G76,U$3<H76),F76*MIN(12,E76-(U$3-G76)*12)/E76,0)) | V14: =IF(OR(D76=0,E76=0,F76=0),0,IF(AND(V$3>=G76,V$3<H76),F76*MIN(12,E76-(V$3-G76)*12)/E76,0)) | W14: =IF(OR(D76=0,E76=0,F76=0),0,IF(AND(W$3>=G76,W$3<H76),F76*MIN(12,E76-(W$3-G76)*12)/E76,0)) | X14: =IF(OR(D76=0,E76=0,F76=0),0,IF(AND(X$3>=G76,X$3<H76),F76*MIN(12,E76-(X$3-G76)*12)/E76,0)) | Y14: =IF(OR(D76=0,E76=0,F76=0),0,IF(AND(Y$3>=G76,Y$3<H76),F76*MIN(12,E76-(Y$3-G76)*12)/E76,0)) | Z14: =IF(OR(D76=0,E76=0,F76=0),0,IF(AND(Z$3>=G76,Z$3<H76),F76*MIN(12,E76-(Z$3-G76)*12)/E76,0)) | AA14: =IF(OR(D76=0,E76=0,F76=0),0,IF(AND(AA$3>=G76,AA$3<H76),F76*MIN(12,E76-(AA$3-G76)*12)/E76,0)) | AB14: =IF(OR(D76=0,E76=0,F76=0),0,IF(AND(AB$3>=G76,AB$3<H76),F76*MIN(12,E76-(AB$3-G76)*12)/E76,0)) | AC14: =IF(OR(D76=0,E76=0,F76=0),0,IF(AND(AC$3>=G76,AC$3<H76),F76*MIN(12,E76-(AC$3-G76)*12)/E76,0)) | AD14: =IF(OR(D76=0,E76=0,F76=0),0,IF(AND(AD$3>=G76,AD$3<H76),F76*MIN(12,E76-(AD$3-G76)*12)/E76,0)) | AE14: =IF(OR(D76=0,E76=0,F76=0),0,IF(AND(AE$3>=G76,AE$3<H76),F76*MIN(12,E76-(AE$3-G76)*12)/E76,0)) | AF14: =IF(OR(D76=0,E76=0,F76=0),0,IF(AND(AF$3>=G76,AF$3<H76),F76*MIN(12,E76-(AF$3-G76)*12)/E76,0)) | AG14: =IF(OR(D76=0,E76=0,F76=0),0,IF(AND(AG$3>=G76,AG$3<H76),F76*MIN(12,E76-(AG$3-G76)*12)/E76,0)) | AH14: =IF(OR(D76=0,E76=0,F76=0),0,IF(AND(AH$3>=G76,AH$3<H76),F76*MIN(12,E76-(AH$3-G76)*12)/E76,0)) | AI14: =IF(OR(D76=0,E76=0,F76=0),0,IF(AND(AI$3>=G76,AI$3<H76),F76*MIN(12,E76-(AI$3-G76)*12)/E76,0)) | AJ14: =IF(OR(D76=0,E76=0,F76=0),0,IF(AND(AJ$3>=G76,AJ$3<H76),F76*MIN(12,E76-(AJ$3-G76)*12)/E76,0)) | AK14: =IF(OR(D76=0,E76=0,F76=0),0,IF(AND(AK$3>=G76,AK$3<H76),F76*MIN(12,E76-(AK$3-G76)*12)/E76,0)) | AL14: =IF(OR(D76=0,E76=0,F76=0),0,IF(AND(AL$3>=G76,AL$3<H76),F76*MIN(12,E76-(AL$3-G76)*12)/E76,0)) | AM14: =IF(OR(D76=0,E76=0,F76=0),0,IF(AND(AM$3>=G76,AM$3<H76),F76*MIN(12,E76-(AM$3-G76)*12)/E76,0)) | AN14: =IF(OR(D76=0,E76=0,F76=0),0,IF(AND(AN$3>=G76,AN$3<H76),F76*MIN(12,E76-(AN$3-G76)*12)/E76,0)) | AO14: =IF(OR(D76=0,E76=0,F76=0),0,IF(AND(AO$3>=G76,AO$3<H76),F76*MIN(12,E76-(AO$3-G76)*12)/E76,0)) | AP14: =IF(OR(D76=0,E76=0,F76=0),0,IF(AND(AP$3>=G76,AP$3<H76),F76*MIN(12,E76-(AP$3-G76)*12)/E76,0)) | AQ14: =IF(OR(D76=0,E76=0,F76=0),0,IF(AND(AQ$3>=G76,AQ$3<H76),F76*MIN(12,E76-(AQ$3-G76)*12)/E76,0)) | AR14: =IF(OR(D76=0,E76=0,F76=0),0,IF(AND(AR$3>=G76,AR$3<H76),F76*MIN(12,E76-(AR$3-G76)*12)/E76,0)) | AS14: =IF(OR(D76=0,E76=0,F76=0),0,IF(AND(AS$3>=G76,AS$3<H76),F76*MIN(12,E76-(AS$3-G76)*12)/E76,0)) | AT14: =IF(OR(D76=0,E76=0,F76=0),0,IF(AND(AT$3>=G76,AT$3<H76),F76*MIN(12,E76-(AT$3-G76)*12)/E76,0)) | AU14: =IF(OR(D76=0,E76=0,F76=0),0,IF(AND(AU$3>=G76,AU$3<H76),F76*MIN(12,E76-(AU$3-G76)*12)/E76,0)) | AV14: =IF(OR(D76=0,E76=0,F76=0),0,IF(AND(AV$3>=G76,AV$3<H76),F76*MIN(12,E76-(AV$3-G76)*12)/E76,0)) | AW14: =IF(OR(D76=0,E76=0,F76=0),0,IF(AND(AW$3>=G76,AW$3<H76),F76*MIN(12,E76-(AW$3-G76)*12)/E76,0)) | AX14: =IF(OR(D76=0,E76=0,F76=0),0,IF(AND(AX$3>=G76,AX$3<H76),F76*MIN(12,E76-(AX$3-G76)*12)/E76,0)) | AY14: =IF(OR(D76=0,E76=0,F76=0),0,IF(AND(AY$3>=G76,AY$3<H76),F76*MIN(12,E76-(AY$3-G76)*12)/E76,0)) | AZ14: =IF(OR(D76=0,E76=0,F76=0),0,IF(AND(AZ$3>=G76,AZ$3<H76),F76*MIN(12,E76-(AZ$3-G76)*12)/E76,0)) | BA14: =IF(OR(D76=0,E76=0,F76=0),0,IF(AND(BA$3>=G76,BA$3<H76),F76*MIN(12,E76-(BA$3-G76)*12)/E76,0)) | BB14: =IF(OR(D76=0,E76=0,F76=0),0,IF(AND(BB$3>=G76,BB$3<H76),F76*MIN(12,E76-(BB$3-G76)*12)/E76,0))
A15: =A77 | B15: =B77 | C15: =C77 | D15: =SUM(E15:BB15) | E15: =IF(OR(D77=0,E77=0,F77=0),0,IF(AND(E$3>=G77,E$3<H77),F77*MIN(12,E77-(E$3-G77)*12)/E77,0)) | F15: =IF(OR(D77=0,E77=0,F77=0),0,IF(AND(F$3>=G77,F$3<H77),F77*MIN(12,E77-(F$3-G77)*12)/E77,0)) | G15: =IF(OR(D77=0,E77=0,F77=0),0,IF(AND(G$3>=G77,G$3<H77),F77*MIN(12,E77-(G$3-G77)*12)/E77,0)) | H15: =IF(OR(D77=0,E77=0,F77=0),0,IF(AND(H$3>=G77,H$3<H77),F77*MIN(12,E77-(H$3-G77)*12)/E77,0)) | I15: =IF(OR(D77=0,E77=0,F77=0),0,IF(AND(I$3>=G77,I$3<H77),F77*MIN(12,E77-(I$3-G77)*12)/E77,0)) | J15: =IF(OR(D77=0,E77=0,F77=0),0,IF(AND(J$3>=G77,J$3<H77),F77*MIN(12,E77-(J$3-G77)*12)/E77,0)) | K15: =IF(OR(D77=0,E77=0,F77=0),0,IF(AND(K$3>=G77,K$3<H77),F77*MIN(12,E77-(K$3-G77)*12)/E77,0)) | L15: =IF(OR(D77=0,E77=0,F77=0),0,IF(AND(L$3>=G77,L$3<H77),F77*MIN(12,E77-(L$3-G77)*12)/E77,0)) | M15: =IF(OR(D77=0,E77=0,F77=0),0,IF(AND(M$3>=G77,M$3<H77),F77*MIN(12,E77-(M$3-G77)*12)/E77,0)) | N15: =IF(OR(D77=0,E77=0,F77=0),0,IF(AND(N$3>=G77,N$3<H77),F77*MIN(12,E77-(N$3-G77)*12)/E77,0)) | O15: =IF(OR(D77=0,E77=0,F77=0),0,IF(AND(O$3>=G77,O$3<H77),F77*MIN(12,E77-(O$3-G77)*12)/E77,0)) | P15: =IF(OR(D77=0,E77=0,F77=0),0,IF(AND(P$3>=G77,P$3<H77),F77*MIN(12,E77-(P$3-G77)*12)/E77,0)) | Q15: =IF(OR(D77=0,E77=0,F77=0),0,IF(AND(Q$3>=G77,Q$3<H77),F77*MIN(12,E77-(Q$3-G77)*12)/E77,0)) | R15: =IF(OR(D77=0,E77=0,F77=0),0,IF(AND(R$3>=G77,R$3<H77),F77*MIN(12,E77-(R$3-G77)*12)/E77,0)) | S15: =IF(OR(D77=0,E77=0,F77=0),0,IF(AND(S$3>=G77,S$3<H77),F77*MIN(12,E77-(S$3-G77)*12)/E77,0)) | T15: =IF(OR(D77=0,E77=0,F77=0),0,IF(AND(T$3>=G77,T$3<H77),F77*MIN(12,E77-(T$3-G77)*12)/E77,0)) | U15: =IF(OR(D77=0,E77=0,F77=0),0,IF(AND(U$3>=G77,U$3<H77),F77*MIN(12,E77-(U$3-G77)*12)/E77,0)) | V15: =IF(OR(D77=0,E77=0,F77=0),0,IF(AND(V$3>=G77,V$3<H77),F77*MIN(12,E77-(V$3-G77)*12)/E77,0)) | W15: =IF(OR(D77=0,E77=0,F77=0),0,IF(AND(W$3>=G77,W$3<H77),F77*MIN(12,E77-(W$3-G77)*12)/E77,0)) | X15: =IF(OR(D77=0,E77=0,F77=0),0,IF(AND(X$3>=G77,X$3<H77),F77*MIN(12,E77-(X$3-G77)*12)/E77,0)) | Y15: =IF(OR(D77=0,E77=0,F77=0),0,IF(AND(Y$3>=G77,Y$3<H77),F77*MIN(12,E77-(Y$3-G77)*12)/E77,0)) | Z15: =IF(OR(D77=0,E77=0,F77=0),0,IF(AND(Z$3>=G77,Z$3<H77),F77*MIN(12,E77-(Z$3-G77)*12)/E77,0)) | AA15: =IF(OR(D77=0,E77=0,F77=0),0,IF(AND(AA$3>=G77,AA$3<H77),F77*MIN(12,E77-(AA$3-G77)*12)/E77,0)) | AB15: =IF(OR(D77=0,E77=0,F77=0),0,IF(AND(AB$3>=G77,AB$3<H77),F77*MIN(12,E77-(AB$3-G77)*12)/E77,0)) | AC15: =IF(OR(D77=0,E77=0,F77=0),0,IF(AND(AC$3>=G77,AC$3<H77),F77*MIN(12,E77-(AC$3-G77)*12)/E77,0)) | AD15: =IF(OR(D77=0,E77=0,F77=0),0,IF(AND(AD$3>=G77,AD$3<H77),F77*MIN(12,E77-(AD$3-G77)*12)/E77,0)) | AE15: =IF(OR(D77=0,E77=0,F77=0),0,IF(AND(AE$3>=G77,AE$3<H77),F77*MIN(12,E77-(AE$3-G77)*12)/E77,0)) | AF15: =IF(OR(D77=0,E77=0,F77=0),0,IF(AND(AF$3>=G77,AF$3<H77),F77*MIN(12,E77-(AF$3-G77)*12)/E77,0)) | AG15: =IF(OR(D77=0,E77=0,F77=0),0,IF(AND(AG$3>=G77,AG$3<H77),F77*MIN(12,E77-(AG$3-G77)*12)/E77,0)) | AH15: =IF(OR(D77=0,E77=0,F77=0),0,IF(AND(AH$3>=G77,AH$3<H77),F77*MIN(12,E77-(AH$3-G77)*12)/E77,0)) | AI15: =IF(OR(D77=0,E77=0,F77=0),0,IF(AND(AI$3>=G77,AI$3<H77),F77*MIN(12,E77-(AI$3-G77)*12)/E77,0)) | AJ15: =IF(OR(D77=0,E77=0,F77=0),0,IF(AND(AJ$3>=G77,AJ$3<H77),F77*MIN(12,E77-(AJ$3-G77)*12)/E77,0)) | AK15: =IF(OR(D77=0,E77=0,F77=0),0,IF(AND(AK$3>=G77,AK$3<H77),F77*MIN(12,E77-(AK$3-G77)*12)/E77,0)) | AL15: =IF(OR(D77=0,E77=0,F77=0),0,IF(AND(AL$3>=G77,AL$3<H77),F77*MIN(12,E77-(AL$3-G77)*12)/E77,0)) | AM15: =IF(OR(D77=0,E77=0,F77=0),0,IF(AND(AM$3>=G77,AM$3<H77),F77*MIN(12,E77-(AM$3-G77)*12)/E77,0)) | AN15: =IF(OR(D77=0,E77=0,F77=0),0,IF(AND(AN$3>=G77,AN$3<H77),F77*MIN(12,E77-(AN$3-G77)*12)/E77,0)) | AO15: =IF(OR(D77=0,E77=0,F77=0),0,IF(AND(AO$3>=G77,AO$3<H77),F77*MIN(12,E77-(AO$3-G77)*12)/E77,0)) | AP15: =IF(OR(D77=0,E77=0,F77=0),0,IF(AND(AP$3>=G77,AP$3<H77),F77*MIN(12,E77-(AP$3-G77)*12)/E77,0)) | AQ15: =IF(OR(D77=0,E77=0,F77=0),0,IF(AND(AQ$3>=G77,AQ$3<H77),F77*MIN(12,E77-(AQ$3-G77)*12)/E77,0)) | AR15: =IF(OR(D77=0,E77=0,F77=0),0,IF(AND(AR$3>=G77,AR$3<H77),F77*MIN(12,E77-(AR$3-G77)*12)/E77,0)) | AS15: =IF(OR(D77=0,E77=0,F77=0),0,IF(AND(AS$3>=G77,AS$3<H77),F77*MIN(12,E77-(AS$3-G77)*12)/E77,0)) | AT15: =IF(OR(D77=0,E77=0,F77=0),0,IF(AND(AT$3>=G77,AT$3<H77),F77*MIN(12,E77-(AT$3-G77)*12)/E77,0)) | AU15: =IF(OR(D77=0,E77=0,F77=0),0,IF(AND(AU$3>=G77,AU$3<H77),F77*MIN(12,E77-(AU$3-G77)*12)/E77,0)) | AV15: =IF(OR(D77=0,E77=0,F77=0),0,IF(AND(AV$3>=G77,AV$3<H77),F77*MIN(12,E77-(AV$3-G77)*12)/E77,0)) | AW15: =IF(OR(D77=0,E77=0,F77=0),0,IF(AND(AW$3>=G77,AW$3<H77),F77*MIN(12,E77-(AW$3-G77)*12)/E77,0)) | AX15: =IF(OR(D77=0,E77=0,F77=0),0,IF(AND(AX$3>=G77,AX$3<H77),F77*MIN(12,E77-(AX$3-G77)*12)/E77,0)) | AY15: =IF(OR(D77=0,E77=0,F77=0),0,IF(AND(AY$3>=G77,AY$3<H77),F77*MIN(12,E77-(AY$3-G77)*12)/E77,0)) | AZ15: =IF(OR(D77=0,E77=0,F77=0),0,IF(AND(AZ$3>=G77,AZ$3<H77),F77*MIN(12,E77-(AZ$3-G77)*12)/E77,0)) | BA15: =IF(OR(D77=0,E77=0,F77=0),0,IF(AND(BA$3>=G77,BA$3<H77),F77*MIN(12,E77-(BA$3-G77)*12)/E77,0)) | BB15: =IF(OR(D77=0,E77=0,F77=0),0,IF(AND(BB$3>=G77,BB$3<H77),F77*MIN(12,E77-(BB$3-G77)*12)/E77,0))
... A33: =A95 | B33: =B95 | C33: =C95 | D33: =SUM(E33:BB33) | E33: =IF(OR(D95=0,E95=0,F95=0),0,IF(AND(E$3>=G95,E$3<H95),F95*MIN(12,E95-(E$3-G95)*12)/E95,0)) | F33: =IF(OR(D95=0,E95=0,F95=0),0,IF(AND(F$3>=G95,F$3<H95),F95*MIN(12,E95-(F$3-G95)*12)/E95,0)) | G33: =IF(OR(D95=0,E95=0,F95=0),0,IF(AND(G$3>=G95,G$3<H95),F95*MIN(12,E95-(G$3-G95)*12)/E95,0)) | H33: =IF(OR(D95=0,E95=0,F95=0),0,IF(AND(H$3>=G95,H$3<H95),F95*MIN(12,E95-(H$3-G95)*12)/E95,0)) | I33: =IF(OR(D95=0,E95=0,F95=0),0,IF(AND(I$3>=G95,I$3<H95),F95*MIN(12,E95-(I$3-G95)*12)/E95,0)) | J33: =IF(OR(D95=0,E95=0,F95=0),0,IF(AND(J$3>=G95,J$3<H95),F95*MIN(12,E95-(J$3-G95)*12)/E95,0)) | K33: =IF(OR(D95=0,E95=0,F95=0),0,IF(AND(K$3>=G95,K$3<H95),F95*MIN(12,E95-(K$3-G95)*12)/E95,0)) | L33: =IF(OR(D95=0,E95=0,F95=0),0,IF(AND(L$3>=G95,L$3<H95),F95*MIN(12,E95-(L$3-G95)*12)/E95,0)) | M33: =IF(OR(D95=0,E95=0,F95=0),0,IF(AND(M$3>=G95,M$3<H95),F95*MIN(12,E95-(M$3-G95)*12)/E95,0)) | N33: =IF(OR(D95=0,E95=0,F95=0),0,IF(AND(N$3>=G95,N$3<H95),F95*MIN(12,E95-(N$3-G95)*12)/E95,0)) | O33: =IF(OR(D95=0,E95=0,F95=0),0,IF(AND(O$3>=G95,O$3<H95),F95*MIN(12,E95-(O$3-G95)*12)/E95,0)) | P33: =IF(OR(D95=0,E95=0,F95=0),0,IF(AND(P$3>=G95,P$3<H95),F95*MIN(12,E95-(P$3-G95)*12)/E95,0)) | Q33: =IF(OR(D95=0,E95=0,F95=0),0,IF(AND(Q$3>=G95,Q$3<H95),F95*MIN(12,E95-(Q$3-G95)*12)/E95,0)) | R33: =IF(OR(D95=0,E95=0,F95=0),0,IF(AND(R$3>=G95,R$3<H95),F95*MIN(12,E95-(R$3-G95)*12)/E95,0)) | S33: =IF(OR(D95=0,E95=0,F95=0),0,IF(AND(S$3>=G95,S$3<H95),F95*MIN(12,E95-(S$3-G95)*12)/E95,0)) | T33: =IF(OR(D95=0,E95=0,F95=0),0,IF(AND(T$3>=G95,T$3<H95),F95*MIN(12,E95-(T$3-G95)*12)/E95,0)) | U33: =IF(OR(D95=0,E95=0,F95=0),0,IF(AND(U$3>=G95,U$3<H95),F95*MIN(12,E95-(U$3-G95)*12)/E95,0)) | V33: =IF(OR(D95=0,E95=0,F95=0),0,IF(AND(V$3>=G95,V$3<H95),F95*MIN(12,E95-(V$3-G95)*12)/E95,0)) | W33: =IF(OR(D95=0,E95=0,F95=0),0,IF(AND(W$3>=G95,W$3<H95),F95*MIN(12,E95-(W$3-G95)*12)/E95,0)) | X33: =IF(OR(D95=0,E95=0,F95=0),0,IF(AND(X$3>=G95,X$3<H95),F95*MIN(12,E95-(X$3-G95)*12)/E95,0)) | Y33: =IF(OR(D95=0,E95=0,F95=0),0,IF(AND(Y$3>=G95,Y$3<H95),F95*MIN(12,E95-(Y$3-G95)*12)/E95,0)) | Z33: =IF(OR(D95=0,E95=0,F95=0),0,IF(AND(Z$3>=G95,Z$3<H95),F95*MIN(12,E95-(Z$3-G95)*12)/E95,0)) | AA33: =IF(OR(D95=0,E95=0,F95=0),0,IF(AND(AA$3>=G95,AA$3<H95),F95*MIN(12,E95-(AA$3-G95)*12)/E95,0)) | AB33: =IF(OR(D95=0,E95=0,F95=0),0,IF(AND(AB$3>=G95,AB$3<H95),F95*MIN(12,E95-(AB$3-G95)*12)/E95,0)) | AC33: =IF(OR(D95=0,E95=0,F95=0),0,IF(AND(AC$3>=G95,AC$3<H95),F95*MIN(12,E95-(AC$3-G95)*12)/E95,0)) | AD33: =IF(OR(D95=0,E95=0,F95=0),0,IF(AND(AD$3>=G95,AD$3<H95),F95*MIN(12,E95-(AD$3-G95)*12)/E95,0)) | AE33: =IF(OR(D95=0,E95=0,F95=0),0,IF(AND(AE$3>=G95,AE$3<H95),F95*MIN(12,E95-(AE$3-G95)*12)/E95,0)) | AF33: =IF(OR(D95=0,E95=0,F95=0),0,IF(AND(AF$3>=G95,AF$3<H95),F95*MIN(12,E95-(AF$3-G95)*12)/E95,0)) | AG33: =IF(OR(D95=0,E95=0,F95=0),0,IF(AND(AG$3>=G95,AG$3<H95),F95*MIN(12,E95-(AG$3-G95)*12)/E95,0)) | AH33: =IF(OR(D95=0,E95=0,F95=0),0,IF(AND(AH$3>=G95,AH$3<H95),F95*MIN(12,E95-(AH$3-G95)*12)/E95,0)) | AI33: =IF(OR(D95=0,E95=0,F95=0),0,IF(AND(AI$3>=G95,AI$3<H95),F95*MIN(12,E95-(AI$3-G95)*12)/E95,0)) | AJ33: =IF(OR(D95=0,E95=0,F95=0),0,IF(AND(AJ$3>=G95,AJ$3<H95),F95*MIN(12,E95-(AJ$3-G95)*12)/E95,0)) | AK33: =IF(OR(D95=0,E95=0,F95=0),0,IF(AND(AK$3>=G95,AK$3<H95),F95*MIN(12,E95-(AK$3-G95)*12)/E95,0)) | AL33: =IF(OR(D95=0,E95=0,F95=0),0,IF(AND(AL$3>=G95,AL$3<H95),F95*MIN(12,E95-(AL$3-G95)*12)/E95,0)) | AM33: =IF(OR(D95=0,E95=0,F95=0),0,IF(AND(AM$3>=G95,AM$3<H95),F95*MIN(12,E95-(AM$3-G95)*12)/E95,0)) | AN33: =IF(OR(D95=0,E95=0,F95=0),0,IF(AND(AN$3>=G95,AN$3<H95),F95*MIN(12,E95-(AN$3-G95)*12)/E95,0)) | AO33: =IF(OR(D95=0,E95=0,F95=0),0,IF(AND(AO$3>=G95,AO$3<H95),F95*MIN(12,E95-(AO$3-G95)*12)/E95,0)) | AP33: =IF(OR(D95=0,E95=0,F95=0),0,IF(AND(AP$3>=G95,AP$3<H95),F95*MIN(12,E95-(AP$3-G95)*12)/E95,0)) | AQ33: =IF(OR(D95=0,E95=0,F95=0),0,IF(AND(AQ$3>=G95,AQ$3<H95),F95*MIN(12,E95-(AQ$3-G95)*12)/E95,0)) | AR33: =IF(OR(D95=0,E95=0,F95=0),0,IF(AND(AR$3>=G95,AR$3<H95),F95*MIN(12,E95-(AR$3-G95)*12)/E95,0)) | AS33: =IF(OR(D95=0,E95=0,F95=0),0,IF(AND(AS$3>=G95,AS$3<H95),F95*MIN(12,E95-(AS$3-G95)*12)/E95,0)) | AT33: =IF(OR(D95=0,E95=0,F95=0),0,IF(AND(AT$3>=G95,AT$3<H95),F95*MIN(12,E95-(AT$3-G95)*12)/E95,0)) | AU33: =IF(OR(D95=0,E95=0,F95=0),0,IF(AND(AU$3>=G95,AU$3<H95),F95*MIN(12,E95-(AU$3-G95)*12)/E95,0)) | AV33: =IF(OR(D95=0,E95=0,F95=0),0,IF(AND(AV$3>=G95,AV$3<H95),F95*MIN(12,E95-(AV$3-G95)*12)/E95,0)) | AW33: =IF(OR(D95=0,E95=0,F95=0),0,IF(AND(AW$3>=G95,AW$3<H95),F95*MIN(12,E95-(AW$3-G95)*12)/E95,0)) | AX33: =IF(OR(D95=0,E95=0,F95=0),0,IF(AND(AX$3>=G95,AX$3<H95),F95*MIN(12,E95-(AX$3-G95)*12)/E95,0)) | AY33: =IF(OR(D95=0,E95=0,F95=0),0,IF(AND(AY$3>=G95,AY$3<H95),F95*MIN(12,E95-(AY$3-G95)*12)/E95,0)) | AZ33: =IF(OR(D95=0,E95=0,F95=0),0,IF(AND(AZ$3>=G95,AZ$3<H95),F95*MIN(12,E95-(AZ$3-G95)*12)/E95,0)) | BA33: =IF(OR(D95=0,E95=0,F95=0),0,IF(AND(BA$3>=G95,BA$3<H95),F95*MIN(12,E95-(BA$3-G95)*12)/E95,0)) | BB33: =IF(OR(D95=0,E95=0,F95=0),0,IF(AND(BB$3>=G95,BB$3<H95),F95*MIN(12,E95-(BB$3-G95)*12)/E95,0))
A35: CAPEX BY PHASE
B36: ZAN 1 | D36: =SUM(E36:BB36) | E36: =SUMPRODUCT(($C$4:$C$33="ZAN 1")*E$4:E$33) | F36: =SUMPRODUCT(($C$4:$C$33="ZAN 1")*F$4:F$33) | G36: =SUMPRODUCT(($C$4:$C$33="ZAN 1")*G$4:G$33) | H36: =SUMPRODUCT(($C$4:$C$33="ZAN 1")*H$4:H$33) | I36: =SUMPRODUCT(($C$4:$C$33="ZAN 1")*I$4:I$33) | J36: =SUMPRODUCT(($C$4:$C$33="ZAN 1")*J$4:J$33) | K36: =SUMPRODUCT(($C$4:$C$33="ZAN 1")*K$4:K$33) | L36: =SUMPRODUCT(($C$4:$C$33="ZAN 1")*L$4:L$33) | ... BB36: =SUMPRODUCT(($C$4:$C$33="ZAN 1")*BB$4:BB$33)
B37: ZAN 2 | D37: =SUM(E37:BB37) | E37: =SUMPRODUCT(($C$4:$C$33="ZAN 2")*E$4:E$33) | F37: =SUMPRODUCT(($C$4:$C$33="ZAN 2")*F$4:F$33) | G37: =SUMPRODUCT(($C$4:$C$33="ZAN 2")*G$4:G$33) | H37: =SUMPRODUCT(($C$4:$C$33="ZAN 2")*H$4:H$33) | I37: =SUMPRODUCT(($C$4:$C$33="ZAN 2")*I$4:I$33) | J37: =SUMPRODUCT(($C$4:$C$33="ZAN 2")*J$4:J$33) | K37: =SUMPRODUCT(($C$4:$C$33="ZAN 2")*K$4:K$33) | L37: =SUMPRODUCT(($C$4:$C$33="ZAN 2")*L$4:L$33) | ... BB37: =SUMPRODUCT(($C$4:$C$33="ZAN 2")*BB$4:BB$33)
B38: ZAN 3 | D38: =SUM(E38:BB38) | E38: =SUMPRODUCT(($C$4:$C$33="ZAN 3")*E$4:E$33) | F38: =SUMPRODUCT(($C$4:$C$33="ZAN 3")*F$4:F$33) | G38: =SUMPRODUCT(($C$4:$C$33="ZAN 3")*G$4:G$33) | H38: =SUMPRODUCT(($C$4:$C$33="ZAN 3")*H$4:H$33) | I38: =SUMPRODUCT(($C$4:$C$33="ZAN 3")*I$4:I$33) | J38: =SUMPRODUCT(($C$4:$C$33="ZAN 3")*J$4:J$33) | K38: =SUMPRODUCT(($C$4:$C$33="ZAN 3")*K$4:K$33) | L38: =SUMPRODUCT(($C$4:$C$33="ZAN 3")*L$4:L$33) | ... BB38: =SUMPRODUCT(($C$4:$C$33="ZAN 3")*BB$4:BB$33)
B39: ZAN 4 | D39: =SUM(E39:BB39) | E39: =SUMPRODUCT(($C$4:$C$33="ZAN 4")*E$4:E$33) | F39: =SUMPRODUCT(($C$4:$C$33="ZAN 4")*F$4:F$33) | G39: =SUMPRODUCT(($C$4:$C$33="ZAN 4")*G$4:G$33) | H39: =SUMPRODUCT(($C$4:$C$33="ZAN 4")*H$4:H$33) | I39: =SUMPRODUCT(($C$4:$C$33="ZAN 4")*I$4:I$33) | J39: =SUMPRODUCT(($C$4:$C$33="ZAN 4")*J$4:J$33) | K39: =SUMPRODUCT(($C$4:$C$33="ZAN 4")*K$4:K$33) | L39: =SUMPRODUCT(($C$4:$C$33="ZAN 4")*L$4:L$33) | ... BB39: =SUMPRODUCT(($C$4:$C$33="ZAN 4")*BB$4:BB$33)
B40: ZAN 5 | D40: =SUM(E40:BB40) | E40: =SUMPRODUCT(($C$4:$C$33="ZAN 5")*E$4:E$33) | F40: =SUMPRODUCT(($C$4:$C$33="ZAN 5")*F$4:F$33) | G40: =SUMPRODUCT(($C$4:$C$33="ZAN 5")*G$4:G$33) | H40: =SUMPRODUCT(($C$4:$C$33="ZAN 5")*H$4:H$33) | I40: =SUMPRODUCT(($C$4:$C$33="ZAN 5")*I$4:I$33) | J40: =SUMPRODUCT(($C$4:$C$33="ZAN 5")*J$4:J$33) | K40: =SUMPRODUCT(($C$4:$C$33="ZAN 5")*K$4:K$33) | L40: =SUMPRODUCT(($C$4:$C$33="ZAN 5")*L$4:L$33) | ... BB40: =SUMPRODUCT(($C$4:$C$33="ZAN 5")*BB$4:BB$33)
B41: ZAN 6 | D41: =SUM(E41:BB41) | E41: =SUMPRODUCT(($C$4:$C$33="ZAN 6")*E$4:E$33) | F41: =SUMPRODUCT(($C$4:$C$33="ZAN 6")*F$4:F$33) | G41: =SUMPRODUCT(($C$4:$C$33="ZAN 6")*G$4:G$33) | H41: =SUMPRODUCT(($C$4:$C$33="ZAN 6")*H$4:H$33) | I41: =SUMPRODUCT(($C$4:$C$33="ZAN 6")*I$4:I$33) | J41: =SUMPRODUCT(($C$4:$C$33="ZAN 6")*J$4:J$33) | K41: =SUMPRODUCT(($C$4:$C$33="ZAN 6")*K$4:K$33) | L41: =SUMPRODUCT(($C$4:$C$33="ZAN 6")*L$4:L$33) | ... BB41: =SUMPRODUCT(($C$4:$C$33="ZAN 6")*BB$4:BB$33)
B42: ZAN 7 | D42: =SUM(E42:BB42) | E42: =SUMPRODUCT(($C$4:$C$33="ZAN 7")*E$4:E$33) | F42: =SUMPRODUCT(($C$4:$C$33="ZAN 7")*F$4:F$33) | G42: =SUMPRODUCT(($C$4:$C$33="ZAN 7")*G$4:G$33) | H42: =SUMPRODUCT(($C$4:$C$33="ZAN 7")*H$4:H$33) | I42: =SUMPRODUCT(($C$4:$C$33="ZAN 7")*I$4:I$33) | J42: =SUMPRODUCT(($C$4:$C$33="ZAN 7")*J$4:J$33) | K42: =SUMPRODUCT(($C$4:$C$33="ZAN 7")*K$4:K$33) | L42: =SUMPRODUCT(($C$4:$C$33="ZAN 7")*L$4:L$33) | ... BB42: =SUMPRODUCT(($C$4:$C$33="ZAN 7")*BB$4:BB$33)
B43: ZAN 8 | D43: =SUM(E43:BB43) | E43: =SUMPRODUCT(($C$4:$C$33="ZAN 8")*E$4:E$33) | F43: =SUMPRODUCT(($C$4:$C$33="ZAN 8")*F$4:F$33) | G43: =SUMPRODUCT(($C$4:$C$33="ZAN 8")*G$4:G$33) | H43: =SUMPRODUCT(($C$4:$C$33="ZAN 8")*H$4:H$33) | I43: =SUMPRODUCT(($C$4:$C$33="ZAN 8")*I$4:I$33) | J43: =SUMPRODUCT(($C$4:$C$33="ZAN 8")*J$4:J$33) | K43: =SUMPRODUCT(($C$4:$C$33="ZAN 8")*K$4:K$33) | L43: =SUMPRODUCT(($C$4:$C$33="ZAN 8")*L$4:L$33) | ... BB43: =SUMPRODUCT(($C$4:$C$33="ZAN 8")*BB$4:BB$33)
B44: ZAN 9 | D44: =SUM(E44:BB44) | E44: =SUMPRODUCT(($C$4:$C$33="ZAN 9")*E$4:E$33) | F44: =SUMPRODUCT(($C$4:$C$33="ZAN 9")*F$4:F$33) | G44: =SUMPRODUCT(($C$4:$C$33="ZAN 9")*G$4:G$33) | H44: =SUMPRODUCT(($C$4:$C$33="ZAN 9")*H$4:H$33) | I44: =SUMPRODUCT(($C$4:$C$33="ZAN 9")*I$4:I$33) | J44: =SUMPRODUCT(($C$4:$C$33="ZAN 9")*J$4:J$33) | K44: =SUMPRODUCT(($C$4:$C$33="ZAN 9")*K$4:K$33) | L44: =SUMPRODUCT(($C$4:$C$33="ZAN 9")*L$4:L$33) | ... BB44: =SUMPRODUCT(($C$4:$C$33="ZAN 9")*BB$4:BB$33)
B45: ZAN 10 | D45: =SUM(E45:BB45) | E45: =SUMPRODUCT(($C$4:$C$33="ZAN 10")*E$4:E$33) | F45: =SUMPRODUCT(($C$4:$C$33="ZAN 10")*F$4:F$33) | G45: =SUMPRODUCT(($C$4:$C$33="ZAN 10")*G$4:G$33) | H45: =SUMPRODUCT(($C$4:$C$33="ZAN 10")*H$4:H$33) | I45: =SUMPRODUCT(($C$4:$C$33="ZAN 10")*I$4:I$33) | J45: =SUMPRODUCT(($C$4:$C$33="ZAN 10")*J$4:J$33) | K45: =SUMPRODUCT(($C$4:$C$33="ZAN 10")*K$4:K$33) | L45: =SUMPRODUCT(($C$4:$C$33="ZAN 10")*L$4:L$33) | ... BB45: =SUMPRODUCT(($C$4:$C$33="ZAN 10")*BB$4:BB$33)
B46: ZAN 11 | D46: =SUM(E46:BB46) | E46: =SUMPRODUCT(($C$4:$C$33="ZAN 11")*E$4:E$33) | F46: =SUMPRODUCT(($C$4:$C$33="ZAN 11")*F$4:F$33) | G46: =SUMPRODUCT(($C$4:$C$33="ZAN 11")*G$4:G$33) | H46: =SUMPRODUCT(($C$4:$C$33="ZAN 11")*H$4:H$33) | I46: =SUMPRODUCT(($C$4:$C$33="ZAN 11")*I$4:I$33) | J46: =SUMPRODUCT(($C$4:$C$33="ZAN 11")*J$4:J$33) | K46: =SUMPRODUCT(($C$4:$C$33="ZAN 11")*K$4:K$33) | L46: =SUMPRODUCT(($C$4:$C$33="ZAN 11")*L$4:L$33) | ... BB46: =SUMPRODUCT(($C$4:$C$33="ZAN 11")*BB$4:BB$33)
B47: ZAN 12 | D47: =SUM(E47:BB47) | E47: =SUMPRODUCT(($C$4:$C$33="ZAN 12")*E$4:E$33) | F47: =SUMPRODUCT(($C$4:$C$33="ZAN 12")*F$4:F$33) | G47: =SUMPRODUCT(($C$4:$C$33="ZAN 12")*G$4:G$33) | H47: =SUMPRODUCT(($C$4:$C$33="ZAN 12")*H$4:H$33) | I47: =SUMPRODUCT(($C$4:$C$33="ZAN 12")*I$4:I$33) | J47: =SUMPRODUCT(($C$4:$C$33="ZAN 12")*J$4:J$33) | K47: =SUMPRODUCT(($C$4:$C$33="ZAN 12")*K$4:K$33) | L47: =SUMPRODUCT(($C$4:$C$33="ZAN 12")*L$4:L$33) | ... BB47: =SUMPRODUCT(($C$4:$C$33="ZAN 12")*BB$4:BB$33)
B48: ZAN 13 | D48: =SUM(E48:BB48) | E48: =SUMPRODUCT(($C$4:$C$33="ZAN 13")*E$4:E$33) | F48: =SUMPRODUCT(($C$4:$C$33="ZAN 13")*F$4:F$33) | G48: =SUMPRODUCT(($C$4:$C$33="ZAN 13")*G$4:G$33) | H48: =SUMPRODUCT(($C$4:$C$33="ZAN 13")*H$4:H$33) | I48: =SUMPRODUCT(($C$4:$C$33="ZAN 13")*I$4:I$33) | J48: =SUMPRODUCT(($C$4:$C$33="ZAN 13")*J$4:J$33) | K48: =SUMPRODUCT(($C$4:$C$33="ZAN 13")*K$4:K$33) | L48: =SUMPRODUCT(($C$4:$C$33="ZAN 13")*L$4:L$33) | ... BB48: =SUMPRODUCT(($C$4:$C$33="ZAN 13")*BB$4:BB$33)
B49: ZAN 14 | D49: =SUM(E49:BB49) | E49: =SUMPRODUCT(($C$4:$C$33="ZAN 14")*E$4:E$33) | F49: =SUMPRODUCT(($C$4:$C$33="ZAN 14")*F$4:F$33) | G49: =SUMPRODUCT(($C$4:$C$33="ZAN 14")*G$4:G$33) | H49: =SUMPRODUCT(($C$4:$C$33="ZAN 14")*H$4:H$33) | I49: =SUMPRODUCT(($C$4:$C$33="ZAN 14")*I$4:I$33) | J49: =SUMPRODUCT(($C$4:$C$33="ZAN 14")*J$4:J$33) | K49: =SUMPRODUCT(($C$4:$C$33="ZAN 14")*K$4:K$33) | L49: =SUMPRODUCT(($C$4:$C$33="ZAN 14")*L$4:L$33) | ... BB49: =SUMPRODUCT(($C$4:$C$33="ZAN 14")*BB$4:BB$33)
B50: ZAN 15 | D50: =SUM(E50:BB50) | E50: =SUMPRODUCT(($C$4:$C$33="ZAN 15")*E$4:E$33) | F50: =SUMPRODUCT(($C$4:$C$33="ZAN 15")*F$4:F$33) | G50: =SUMPRODUCT(($C$4:$C$33="ZAN 15")*G$4:G$33) | H50: =SUMPRODUCT(($C$4:$C$33="ZAN 15")*H$4:H$33) | I50: =SUMPRODUCT(($C$4:$C$33="ZAN 15")*I$4:I$33) | J50: =SUMPRODUCT(($C$4:$C$33="ZAN 15")*J$4:J$33) | K50: =SUMPRODUCT(($C$4:$C$33="ZAN 15")*K$4:K$33) | L50: =SUMPRODUCT(($C$4:$C$33="ZAN 15")*L$4:L$33) | ... BB50: =SUMPRODUCT(($C$4:$C$33="ZAN 15")*BB$4:BB$33)
B52: TOTAL CAPEX | D52: =SUM(D4:D33) | E52: =SUM(E36:E50) | F52: =SUM(F36:F50) | G52: =SUM(G36:G50) | H52: =SUM(H36:H50) | I52: =SUM(I36:I50) | J52: =SUM(J36:J50) | K52: =SUM(K36:K50) | L52: =SUM(L36:L50) | ... BB52: =SUM(BB36:BB50)
A54: LAND RENT SCHEDULE
B55: Annual Land Rent | D55: =SUM(E55:BB55) | E55: =IF(E$3-$C63+1<=$K$63,0,$E$63*(1+$I$63)^INT((E$3-$C63+1-$K$63-1)/$G$63)) | F55: =IF(F$3-$C63+1<=$K$63,0,$E$63*(1+$I$63)^INT((F$3-$C63+1-$K$63-1)/$G$63)) | G55: =IF(G$3-$C63+1<=$K$63,0,$E$63*(1+$I$63)^INT((G$3-$C63+1-$K$63-1)/$G$63)) | H55: =IF(H$3-$C63+1<=$K$63,0,$E$63*(1+$I$63)^INT((H$3-$C63+1-$K$63-1)/$G$63)) | I55: =IF(I$3-$C63+1<=$K$63,0,$E$63*(1+$I$63)^INT((I$3-$C63+1-$K$63-1)/$G$63)) | J55: =IF(J$3-$C63+1<=$K$63,0,$E$63*(1+$I$63)^INT((J$3-$C63+1-$K$63-1)/$G$63)) | K55: =IF(K$3-$C63+1<=$K$63,0,$E$63*(1+$I$63)^INT((K$3-$C63+1-$K$63-1)/$G$63)) | L55: =IF(L$3-$C63+1<=$K$63,0,$E$63*(1+$I$63)^INT((L$3-$C63+1-$K$63-1)/$G$63)) | ... BB55: =IF(BB$3-$C63+1<=$K$63,0,$E$63*(1+$I$63)^INT((BB$3-$C63+1-$K$63-1)/$G$63))
B56: ZAN 1 | D56: =SUM(E56:BB56) | E56: =E55*$C64 | F56: =F55*$C64 | G56: =G55*$C64 | H56: =H55*$C64 | I56: =I55*$C64 | J56: =J55*$C64 | K56: =K55*$C64 | L56: =L55*$C64 | ... BB56: =BB55*$C64
B57: ZAN 2 | D57: =SUM(E57:BB57) | E57: =E55*$D64 | F57: =F55*$D64 | G57: =G55*$D64 | H57: =H55*$D64 | I57: =I55*$D64 | J57: =J55*$D64 | K57: =K55*$D64 | L57: =L55*$D64 | ... BB57: =BB55*$D64
B58: ZAN 3 | D58: =SUM(E58:BB58) | E58: =E55*$E64 | F58: =F55*$E64 | G58: =G55*$E64 | H58: =H55*$E64 | I58: =I55*$E64 | J58: =J55*$E64 | K58: =K55*$E64 | L58: =L55*$E64 | ... BB58: =BB55*$E64
A62: IMPORT البيانات المستوردة (يمكن طيها ▼)
A63: Inputs: | B63: StartYear | C63: =Inputs!C7 | D63: LandRent | E63: =Inputs!C18 | F63: EveryN | G63: =Inputs!C19 | H63: Esc% | I63: =Inputs!C20 | J63: Grace | K63: =Inputs!C21
B64: PhaseAlloc | C64: =Inputs!E45 | D64: =Inputs!E46 | E64: =Inputs!E47
A65: # | B65: Asset | C65: Phase | D65: GFA | E65: Dur | F65: CAPEX | G65: StartYr | H65: EndYr
A66: =1 | B66: =Program!C4 | C66: =Program!A4 | D66: =Program!H4 | E66: =Program!S4 | F66: =Program!T4 | G66: =Program!U4 | H66: =Program!V4
A67: =2 | B67: =Program!C5 | C67: =Program!A5 | D67: =Program!H5 | E67: =Program!S5 | F67: =Program!T5 | G67: =Program!U5 | H67: =Program!V5
A68: =3 | B68: =Program!C6 | C68: =Program!A6 | D68: =Program!H6 | E68: =Program!S6 | F68: =Program!T6 | G68: =Program!U6 | H68: =Program!V6
A69: =4 | B69: =Program!C7 | C69: =Program!A7 | D69: =Program!H7 | E69: =Program!S7 | F69: =Program!T7 | G69: =Program!U7 | H69: =Program!V7
A70: =5 | B70: =Program!C8 | C70: =Program!A8 | D70: =Program!H8 | E70: =Program!S8 | F70: =Program!T8 | G70: =Program!U8 | H70: =Program!V8
A71: =6 | B71: =Program!C9 | C71: =Program!A9 | D71: =Program!H9 | E71: =Program!S9 | F71: =Program!T9 | G71: =Program!U9 | H71: =Program!V9
A72: =7 | B72: =Program!C10 | C72: =Program!A10 | D72: =Program!H10 | E72: =Program!S10 | F72: =Program!T10 | G72: =Program!U10 | H72: =Program!V10
A73: =8 | B73: =Program!C11 | C73: =Program!A11 | D73: =Program!H11 | E73: =Program!S11 | F73: =Program!T11 | G73: =Program!U11 | H73: =Program!V11
A74: =9 | B74: =Program!C12 | C74: =Program!A12 | D74: =Program!H12 | E74: =Program!S12 | F74: =Program!T12 | G74: =Program!U12 | H74: =Program!V12
A75: =10 | B75: =Program!C13 | C75: =Program!A13 | D75: =Program!H13 | E75: =Program!S13 | F75: =Program!T13 | G75: =Program!U13 | H75: =Program!V13
A76: =11 | B76: =Program!C14 | C76: =Program!A14 | D76: =Program!H14 | E76: =Program!S14 | F76: =Program!T14 | G76: =Program!U14 | H76: =Program!V14
A77: =12 | B77: =Program!C15 | C77: =Program!A15 | D77: =Program!H15 | E77: =Program!S15 | F77: =Program!T15 | G77: =Program!U15 | H77: =Program!V15
A78: =13 | B78: =Program!C16 | C78: =Program!A16 | D78: =Program!H16 | E78: =Program!S16 | F78: =Program!T16 | G78: =Program!U16 | H78: =Program!V16
A79: =14 | B79: =Program!C17 | C79: =Program!A17 | D79: =Program!H17 | E79: =Program!S17 | F79: =Program!T17 | G79: =Program!U17 | H79: =Program!V17
A80: =15 | B80: =Program!C18 | C80: =Program!A18 | D80: =Program!H18 | E80: =Program!S18 | F80: =Program!T18 | G80: =Program!U18 | H80: =Program!V18
A81: =16 | B81: =Program!C19 | C81: =Program!A19 | D81: =Program!H19 | E81: =Program!S19 | F81: =Program!T19 | G81: =Program!U19 | H81: =Program!V19
A82: =17 | B82: =Program!C20 | C82: =Program!A20 | D82: =Program!H20 | E82: =Program!S20 | F82: =Program!T20 | G82: =Program!U20 | H82: =Program!V20
A83: =18 | B83: =Program!C21 | C83: =Program!A21 | D83: =Program!H21 | E83: =Program!S21 | F83: =Program!T21 | G83: =Program!U21 | H83: =Program!V21
A84: =19 | B84: =Program!C22 | C84: =Program!A22 | D84: =Program!H22 | E84: =Program!S22 | F84: =Program!T22 | G84: =Program!U22 | H84: =Program!V22
A85: =20 | B85: =Program!C23 | C85: =Program!A23 | D85: =Program!H23 | E85: =Program!S23 | F85: =Program!T23 | G85: =Program!U23 | H85: =Program!V23
A86: =21 | B86: =Program!C24 | C86: =Program!A24 | D86: =Program!H24 | E86: =Program!S24 | F86: =Program!T24 | G86: =Program!U24 | H86: =Program!V24
A87: =22 | B87: =Program!C25 | C87: =Program!A25 | D87: =Program!H25 | E87: =Program!S25 | F87: =Program!T25 | G87: =Program!U25 | H87: =Program!V25
A88: =23 | B88: =Program!C26 | C88: =Program!A26 | D88: =Program!H26 | E88: =Program!S26 | F88: =Program!T26 | G88: =Program!U26 | H88: =Program!V26
A89: =24 | B89: =Program!C27 | C89: =Program!A27 | D89: =Program!H27 | E89: =Program!S27 | F89: =Program!T27 | G89: =Program!U27 | H89: =Program!V27
A90: =25 | B90: =Program!C28 | C90: =Program!A28 | D90: =Program!H28 | E90: =Program!S28 | F90: =Program!T28 | G90: =Program!U28 | H90: =Program!V28
A91: =26 | B91: =Program!C29 | C91: =Program!A29 | D91: =Program!H29 | E91: =Program!S29 | F91: =Program!T29 | G91: =Program!U29 | H91: =Program!V29
A92: =27 | B92: =Program!C30 | C92: =Program!A30 | D92: =Program!H30 | E92: =Program!S30 | F92: =Program!T30 | G92: =Program!U30 | H92: =Program!V30
A93: =28 | B93: =Program!C31 | C93: =Program!A31 | D93: =Program!H31 | E93: =Program!S31 | F93: =Program!T31 | G93: =Program!U31 | H93: =Program!V31
A94: =29 | B94: =Program!C32 | C94: =Program!A32 | D94: =Program!H32 | E94: =Program!S32 | F94: =Program!T32 | G94: =Program!U32 | H94: =Program!V32
A95: =30 | B95: =Program!C33 | C95: =Program!A33 | D95: =Program!H33 | E95: =Program!S33 | F95: =Program!T33 | G95: =Program!U33 | H95: =Program!V33

Sheet Revenue
A1: REVENUE SCHEDULE جدول الإيرادات
A3: # | B3: Asset | C3: Phase | D3: Total | E3: =$C93+0 | F3: =$C93+1 | G3: =$C93+2 | H3: =$C93+3 | I3: =$C93+4 | J3: =$C93+5 | K3: =$C93+6 | L3: =$C93+7 | M3: =$C93+8 | N3: =$C93+9 | O3: =$C93+10 | P3: =$C93+11 | Q3: =$C93+12 | R3: =$C93+13 | S3: =$C93+14 | T3: =$C93+15 | U3: =$C93+16 | V3: =$C93+17 | W3: =$C93+18 | X3: =$C93+19 | Y3: =$C93+20 | Z3: =$C93+21 | AA3: =$C93+22 | AB3: =$C93+23 | AC3: =$C93+24 | AD3: =$C93+25 | AE3: =$C93+26 | AF3: =$C93+27 | AG3: =$C93+28 | AH3: =$C93+29 | AI3: =$C93+30 | AJ3: =$C93+31 | AK3: =$C93+32 | AL3: =$C93+33 | AM3: =$C93+34 | AN3: =$C93+35 | AO3: =$C93+36 | AP3: =$C93+37 | AQ3: =$C93+38 | AR3: =$C93+39 | AS3: =$C93+40 | AT3: =$C93+41 | AU3: =$C93+42 | AV3: =$C93+43 | AW3: =$C93+44 | AX3: =$C93+45 | AY3: =$C93+46 | AZ3: =$C93+47 | BA3: =$C93+48 | BB3: =$C93+49
A4: =A95 | B4: =B95 | C4: =C95 | D4: =SUM(E4:BB4) | E4: =IF(OR(E95=0,E$3<D95),0,E95*IF(G95=0,H95,MIN(H95,H95*(E$3-D95+1)/MAX(1,G95)))*(1+F95)^(E$3-D95)*$E93) | F4: =IF(OR(E95=0,F$3<D95),0,E95*IF(G95=0,H95,MIN(H95,H95*(F$3-D95+1)/MAX(1,G95)))*(1+F95)^(F$3-D95)*$E93) | G4: =IF(OR(E95=0,G$3<D95),0,E95*IF(G95=0,H95,MIN(H95,H95*(G$3-D95+1)/MAX(1,G95)))*(1+F95)^(G$3-D95)*$E93) | H4: =IF(OR(E95=0,H$3<D95),0,E95*IF(G95=0,H95,MIN(H95,H95*(H$3-D95+1)/MAX(1,G95)))*(1+F95)^(H$3-D95)*$E93) | I4: =IF(OR(E95=0,I$3<D95),0,E95*IF(G95=0,H95,MIN(H95,H95*(I$3-D95+1)/MAX(1,G95)))*(1+F95)^(I$3-D95)*$E93) | J4: =IF(OR(E95=0,J$3<D95),0,E95*IF(G95=0,H95,MIN(H95,H95*(J$3-D95+1)/MAX(1,G95)))*(1+F95)^(J$3-D95)*$E93) | K4: =IF(OR(E95=0,K$3<D95),0,E95*IF(G95=0,H95,MIN(H95,H95*(K$3-D95+1)/MAX(1,G95)))*(1+F95)^(K$3-D95)*$E93) | L4: =IF(OR(E95=0,L$3<D95),0,E95*IF(G95=0,H95,MIN(H95,H95*(L$3-D95+1)/MAX(1,G95)))*(1+F95)^(L$3-D95)*$E93) | M4: =IF(OR(E95=0,M$3<D95),0,E95*IF(G95=0,H95,MIN(H95,H95*(M$3-D95+1)/MAX(1,G95)))*(1+F95)^(M$3-D95)*$E93) | N4: =IF(OR(E95=0,N$3<D95),0,E95*IF(G95=0,H95,MIN(H95,H95*(N$3-D95+1)/MAX(1,G95)))*(1+F95)^(N$3-D95)*$E93) | O4: =IF(OR(E95=0,O$3<D95),0,E95*IF(G95=0,H95,MIN(H95,H95*(O$3-D95+1)/MAX(1,G95)))*(1+F95)^(O$3-D95)*$E93) | P4: =IF(OR(E95=0,P$3<D95),0,E95*IF(G95=0,H95,MIN(H95,H95*(P$3-D95+1)/MAX(1,G95)))*(1+F95)^(P$3-D95)*$E93) | Q4: =IF(OR(E95=0,Q$3<D95),0,E95*IF(G95=0,H95,MIN(H95,H95*(Q$3-D95+1)/MAX(1,G95)))*(1+F95)^(Q$3-D95)*$E93) | R4: =IF(OR(E95=0,R$3<D95),0,E95*IF(G95=0,H95,MIN(H95,H95*(R$3-D95+1)/MAX(1,G95)))*(1+F95)^(R$3-D95)*$E93) | S4: =IF(OR(E95=0,S$3<D95),0,E95*IF(G95=0,H95,MIN(H95,H95*(S$3-D95+1)/MAX(1,G95)))*(1+F95)^(S$3-D95)*$E93) | T4: =IF(OR(E95=0,T$3<D95),0,E95*IF(G95=0,H95,MIN(H95,H95*(T$3-D95+1)/MAX(1,G95)))*(1+F95)^(T$3-D95)*$E93) | U4: =IF(OR(E95=0,U$3<D95),0,E95*IF(G95=0,H95,MIN(H95,H95*(U$3-D95+1)/MAX(1,G95)))*(1+F95)^(U$3-D95)*$E93) | V4: =IF(OR(E95=0,V$3<D95),0,E95*IF(G95=0,H95,MIN(H95,H95*(V$3-D95+1)/MAX(1,G95)))*(1+F95)^(V$3-D95)*$E93) | W4: =IF(OR(E95=0,W$3<D95),0,E95*IF(G95=0,H95,MIN(H95,H95*(W$3-D95+1)/MAX(1,G95)))*(1+F95)^(W$3-D95)*$E93) | X4: =IF(OR(E95=0,X$3<D95),0,E95*IF(G95=0,H95,MIN(H95,H95*(X$3-D95+1)/MAX(1,G95)))*(1+F95)^(X$3-D95)*$E93) | Y4: =IF(OR(E95=0,Y$3<D95),0,E95*IF(G95=0,H95,MIN(H95,H95*(Y$3-D95+1)/MAX(1,G95)))*(1+F95)^(Y$3-D95)*$E93) | Z4: =IF(OR(E95=0,Z$3<D95),0,E95*IF(G95=0,H95,MIN(H95,H95*(Z$3-D95+1)/MAX(1,G95)))*(1+F95)^(Z$3-D95)*$E93) | AA4: =IF(OR(E95=0,AA$3<D95),0,E95*IF(G95=0,H95,MIN(H95,H95*(AA$3-D95+1)/MAX(1,G95)))*(1+F95)^(AA$3-D95)*$E93) | AB4: =IF(OR(E95=0,AB$3<D95),0,E95*IF(G95=0,H95,MIN(H95,H95*(AB$3-D95+1)/MAX(1,G95)))*(1+F95)^(AB$3-D95)*$E93) | AC4: =IF(OR(E95=0,AC$3<D95),0,E95*IF(G95=0,H95,MIN(H95,H95*(AC$3-D95+1)/MAX(1,G95)))*(1+F95)^(AC$3-D95)*$E93) | AD4: =IF(OR(E95=0,AD$3<D95),0,E95*IF(G95=0,H95,MIN(H95,H95*(AD$3-D95+1)/MAX(1,G95)))*(1+F95)^(AD$3-D95)*$E93) | AE4: =IF(OR(E95=0,AE$3<D95),0,E95*IF(G95=0,H95,MIN(H95,H95*(AE$3-D95+1)/MAX(1,G95)))*(1+F95)^(AE$3-D95)*$E93) | AF4: =IF(OR(E95=0,AF$3<D95),0,E95*IF(G95=0,H95,MIN(H95,H95*(AF$3-D95+1)/MAX(1,G95)))*(1+F95)^(AF$3-D95)*$E93) | AG4: =IF(OR(E95=0,AG$3<D95),0,E95*IF(G95=0,H95,MIN(H95,H95*(AG$3-D95+1)/MAX(1,G95)))*(1+F95)^(AG$3-D95)*$E93) | AH4: =IF(OR(E95=0,AH$3<D95),0,E95*IF(G95=0,H95,MIN(H95,H95*(AH$3-D95+1)/MAX(1,G95)))*(1+F95)^(AH$3-D95)*$E93) | AI4: =IF(OR(E95=0,AI$3<D95),0,E95*IF(G95=0,H95,MIN(H95,H95*(AI$3-D95+1)/MAX(1,G95)))*(1+F95)^(AI$3-D95)*$E93) | AJ4: =IF(OR(E95=0,AJ$3<D95),0,E95*IF(G95=0,H95,MIN(H95,H95*(AJ$3-D95+1)/MAX(1,G95)))*(1+F95)^(AJ$3-D95)*$E93) | AK4: =IF(OR(E95=0,AK$3<D95),0,E95*IF(G95=0,H95,MIN(H95,H95*(AK$3-D95+1)/MAX(1,G95)))*(1+F95)^(AK$3-D95)*$E93) | AL4: =IF(OR(E95=0,AL$3<D95),0,E95*IF(G95=0,H95,MIN(H95,H95*(AL$3-D95+1)/MAX(1,G95)))*(1+F95)^(AL$3-D95)*$E93) | AM4: =IF(OR(E95=0,AM$3<D95),0,E95*IF(G95=0,H95,MIN(H95,H95*(AM$3-D95+1)/MAX(1,G95)))*(1+F95)^(AM$3-D95)*$E93) | AN4: =IF(OR(E95=0,AN$3<D95),0,E95*IF(G95=0,H95,MIN(H95,H95*(AN$3-D95+1)/MAX(1,G95)))*(1+F95)^(AN$3-D95)*$E93) | AO4: =IF(OR(E95=0,AO$3<D95),0,E95*IF(G95=0,H95,MIN(H95,H95*(AO$3-D95+1)/MAX(1,G95)))*(1+F95)^(AO$3-D95)*$E93) | AP4: =IF(OR(E95=0,AP$3<D95),0,E95*IF(G95=0,H95,MIN(H95,H95*(AP$3-D95+1)/MAX(1,G95)))*(1+F95)^(AP$3-D95)*$E93) | AQ4: =IF(OR(E95=0,AQ$3<D95),0,E95*IF(G95=0,H95,MIN(H95,H95*(AQ$3-D95+1)/MAX(1,G95)))*(1+F95)^(AQ$3-D95)*$E93) | AR4: =IF(OR(E95=0,AR$3<D95),0,E95*IF(G95=0,H95,MIN(H95,H95*(AR$3-D95+1)/MAX(1,G95)))*(1+F95)^(AR$3-D95)*$E93) | AS4: =IF(OR(E95=0,AS$3<D95),0,E95*IF(G95=0,H95,MIN(H95,H95*(AS$3-D95+1)/MAX(1,G95)))*(1+F95)^(AS$3-D95)*$E93) | AT4: =IF(OR(E95=0,AT$3<D95),0,E95*IF(G95=0,H95,MIN(H95,H95*(AT$3-D95+1)/MAX(1,G95)))*(1+F95)^(AT$3-D95)*$E93) | AU4: =IF(OR(E95=0,AU$3<D95),0,E95*IF(G95=0,H95,MIN(H95,H95*(AU$3-D95+1)/MAX(1,G95)))*(1+F95)^(AU$3-D95)*$E93) | AV4: =IF(OR(E95=0,AV$3<D95),0,E95*IF(G95=0,H95,MIN(H95,H95*(AV$3-D95+1)/MAX(1,G95)))*(1+F95)^(AV$3-D95)*$E93) | AW4: =IF(OR(E95=0,AW$3<D95),0,E95*IF(G95=0,H95,MIN(H95,H95*(AW$3-D95+1)/MAX(1,G95)))*(1+F95)^(AW$3-D95)*$E93) | AX4: =IF(OR(E95=0,AX$3<D95),0,E95*IF(G95=0,H95,MIN(H95,H95*(AX$3-D95+1)/MAX(1,G95)))*(1+F95)^(AX$3-D95)*$E93) | AY4: =IF(OR(E95=0,AY$3<D95),0,E95*IF(G95=0,H95,MIN(H95,H95*(AY$3-D95+1)/MAX(1,G95)))*(1+F95)^(AY$3-D95)*$E93) | AZ4: =IF(OR(E95=0,AZ$3<D95),0,E95*IF(G95=0,H95,MIN(H95,H95*(AZ$3-D95+1)/MAX(1,G95)))*(1+F95)^(AZ$3-D95)*$E93) | BA4: =IF(OR(E95=0,BA$3<D95),0,E95*IF(G95=0,H95,MIN(H95,H95*(BA$3-D95+1)/MAX(1,G95)))*(1+F95)^(BA$3-D95)*$E93) | BB4: =IF(OR(E95=0,BB$3<D95),0,E95*IF(G95=0,H95,MIN(H95,H95*(BB$3-D95+1)/MAX(1,G95)))*(1+F95)^(BB$3-D95)*$E93)
A5: =A96 | B5: =B96 | C5: =C96 | D5: =SUM(E5:BB5) | E5: =IF(OR(E96=0,E$3<D96),0,E96*IF(G96=0,H96,MIN(H96,H96*(E$3-D96+1)/MAX(1,G96)))*(1+F96)^(E$3-D96)*$E93) | F5: =IF(OR(E96=0,F$3<D96),0,E96*IF(G96=0,H96,MIN(H96,H96*(F$3-D96+1)/MAX(1,G96)))*(1+F96)^(F$3-D96)*$E93) | G5: =IF(OR(E96=0,G$3<D96),0,E96*IF(G96=0,H96,MIN(H96,H96*(G$3-D96+1)/MAX(1,G96)))*(1+F96)^(G$3-D96)*$E93) | H5: =IF(OR(E96=0,H$3<D96),0,E96*IF(G96=0,H96,MIN(H96,H96*(H$3-D96+1)/MAX(1,G96)))*(1+F96)^(H$3-D96)*$E93) | I5: =IF(OR(E96=0,I$3<D96),0,E96*IF(G96=0,H96,MIN(H96,H96*(I$3-D96+1)/MAX(1,G96)))*(1+F96)^(I$3-D96)*$E93) | J5: =IF(OR(E96=0,J$3<D96),0,E96*IF(G96=0,H96,MIN(H96,H96*(J$3-D96+1)/MAX(1,G96)))*(1+F96)^(J$3-D96)*$E93) | K5: =IF(OR(E96=0,K$3<D96),0,E96*IF(G96=0,H96,MIN(H96,H96*(K$3-D96+1)/MAX(1,G96)))*(1+F96)^(K$3-D96)*$E93) | L5: =IF(OR(E96=0,L$3<D96),0,E96*IF(G96=0,H96,MIN(H96,H96*(L$3-D96+1)/MAX(1,G96)))*(1+F96)^(L$3-D96)*$E93) | M5: =IF(OR(E96=0,M$3<D96),0,E96*IF(G96=0,H96,MIN(H96,H96*(M$3-D96+1)/MAX(1,G96)))*(1+F96)^(M$3-D96)*$E93) | N5: =IF(OR(E96=0,N$3<D96),0,E96*IF(G96=0,H96,MIN(H96,H96*(N$3-D96+1)/MAX(1,G96)))*(1+F96)^(N$3-D96)*$E93) | O5: =IF(OR(E96=0,O$3<D96),0,E96*IF(G96=0,H96,MIN(H96,H96*(O$3-D96+1)/MAX(1,G96)))*(1+F96)^(O$3-D96)*$E93) | P5: =IF(OR(E96=0,P$3<D96),0,E96*IF(G96=0,H96,MIN(H96,H96*(P$3-D96+1)/MAX(1,G96)))*(1+F96)^(P$3-D96)*$E93) | Q5: =IF(OR(E96=0,Q$3<D96),0,E96*IF(G96=0,H96,MIN(H96,H96*(Q$3-D96+1)/MAX(1,G96)))*(1+F96)^(Q$3-D96)*$E93) | R5: =IF(OR(E96=0,R$3<D96),0,E96*IF(G96=0,H96,MIN(H96,H96*(R$3-D96+1)/MAX(1,G96)))*(1+F96)^(R$3-D96)*$E93) | S5: =IF(OR(E96=0,S$3<D96),0,E96*IF(G96=0,H96,MIN(H96,H96*(S$3-D96+1)/MAX(1,G96)))*(1+F96)^(S$3-D96)*$E93) | T5: =IF(OR(E96=0,T$3<D96),0,E96*IF(G96=0,H96,MIN(H96,H96*(T$3-D96+1)/MAX(1,G96)))*(1+F96)^(T$3-D96)*$E93) | U5: =IF(OR(E96=0,U$3<D96),0,E96*IF(G96=0,H96,MIN(H96,H96*(U$3-D96+1)/MAX(1,G96)))*(1+F96)^(U$3-D96)*$E93) | V5: =IF(OR(E96=0,V$3<D96),0,E96*IF(G96=0,H96,MIN(H96,H96*(V$3-D96+1)/MAX(1,G96)))*(1+F96)^(V$3-D96)*$E93) | W5: =IF(OR(E96=0,W$3<D96),0,E96*IF(G96=0,H96,MIN(H96,H96*(W$3-D96+1)/MAX(1,G96)))*(1+F96)^(W$3-D96)*$E93) | X5: =IF(OR(E96=0,X$3<D96),0,E96*IF(G96=0,H96,MIN(H96,H96*(X$3-D96+1)/MAX(1,G96)))*(1+F96)^(X$3-D96)*$E93) | Y5: =IF(OR(E96=0,Y$3<D96),0,E96*IF(G96=0,H96,MIN(H96,H96*(Y$3-D96+1)/MAX(1,G96)))*(1+F96)^(Y$3-D96)*$E93) | Z5: =IF(OR(E96=0,Z$3<D96),0,E96*IF(G96=0,H96,MIN(H96,H96*(Z$3-D96+1)/MAX(1,G96)))*(1+F96)^(Z$3-D96)*$E93) | AA5: =IF(OR(E96=0,AA$3<D96),0,E96*IF(G96=0,H96,MIN(H96,H96*(AA$3-D96+1)/MAX(1,G96)))*(1+F96)^(AA$3-D96)*$E93) | AB5: =IF(OR(E96=0,AB$3<D96),0,E96*IF(G96=0,H96,MIN(H96,H96*(AB$3-D96+1)/MAX(1,G96)))*(1+F96)^(AB$3-D96)*$E93) | AC5: =IF(OR(E96=0,AC$3<D96),0,E96*IF(G96=0,H96,MIN(H96,H96*(AC$3-D96+1)/MAX(1,G96)))*(1+F96)^(AC$3-D96)*$E93) | AD5: =IF(OR(E96=0,AD$3<D96),0,E96*IF(G96=0,H96,MIN(H96,H96*(AD$3-D96+1)/MAX(1,G96)))*(1+F96)^(AD$3-D96)*$E93) | AE5: =IF(OR(E96=0,AE$3<D96),0,E96*IF(G96=0,H96,MIN(H96,H96*(AE$3-D96+1)/MAX(1,G96)))*(1+F96)^(AE$3-D96)*$E93) | AF5: =IF(OR(E96=0,AF$3<D96),0,E96*IF(G96=0,H96,MIN(H96,H96*(AF$3-D96+1)/MAX(1,G96)))*(1+F96)^(AF$3-D96)*$E93) | AG5: =IF(OR(E96=0,AG$3<D96),0,E96*IF(G96=0,H96,MIN(H96,H96*(AG$3-D96+1)/MAX(1,G96)))*(1+F96)^(AG$3-D96)*$E93) | AH5: =IF(OR(E96=0,AH$3<D96),0,E96*IF(G96=0,H96,MIN(H96,H96*(AH$3-D96+1)/MAX(1,G96)))*(1+F96)^(AH$3-D96)*$E93) | AI5: =IF(OR(E96=0,AI$3<D96),0,E96*IF(G96=0,H96,MIN(H96,H96*(AI$3-D96+1)/MAX(1,G96)))*(1+F96)^(AI$3-D96)*$E93) | AJ5: =IF(OR(E96=0,AJ$3<D96),0,E96*IF(G96=0,H96,MIN(H96,H96*(AJ$3-D96+1)/MAX(1,G96)))*(1+F96)^(AJ$3-D96)*$E93) | AK5: =IF(OR(E96=0,AK$3<D96),0,E96*IF(G96=0,H96,MIN(H96,H96*(AK$3-D96+1)/MAX(1,G96)))*(1+F96)^(AK$3-D96)*$E93) | AL5: =IF(OR(E96=0,AL$3<D96),0,E96*IF(G96=0,H96,MIN(H96,H96*(AL$3-D96+1)/MAX(1,G96)))*(1+F96)^(AL$3-D96)*$E93) | AM5: =IF(OR(E96=0,AM$3<D96),0,E96*IF(G96=0,H96,MIN(H96,H96*(AM$3-D96+1)/MAX(1,G96)))*(1+F96)^(AM$3-D96)*$E93) | AN5: =IF(OR(E96=0,AN$3<D96),0,E96*IF(G96=0,H96,MIN(H96,H96*(AN$3-D96+1)/MAX(1,G96)))*(1+F96)^(AN$3-D96)*$E93) | AO5: =IF(OR(E96=0,AO$3<D96),0,E96*IF(G96=0,H96,MIN(H96,H96*(AO$3-D96+1)/MAX(1,G96)))*(1+F96)^(AO$3-D96)*$E93) | AP5: =IF(OR(E96=0,AP$3<D96),0,E96*IF(G96=0,H96,MIN(H96,H96*(AP$3-D96+1)/MAX(1,G96)))*(1+F96)^(AP$3-D96)*$E93) | AQ5: =IF(OR(E96=0,AQ$3<D96),0,E96*IF(G96=0,H96,MIN(H96,H96*(AQ$3-D96+1)/MAX(1,G96)))*(1+F96)^(AQ$3-D96)*$E93) | AR5: =IF(OR(E96=0,AR$3<D96),0,E96*IF(G96=0,H96,MIN(H96,H96*(AR$3-D96+1)/MAX(1,G96)))*(1+F96)^(AR$3-D96)*$E93) | AS5: =IF(OR(E96=0,AS$3<D96),0,E96*IF(G96=0,H96,MIN(H96,H96*(AS$3-D96+1)/MAX(1,G96)))*(1+F96)^(AS$3-D96)*$E93) | AT5: =IF(OR(E96=0,AT$3<D96),0,E96*IF(G96=0,H96,MIN(H96,H96*(AT$3-D96+1)/MAX(1,G96)))*(1+F96)^(AT$3-D96)*$E93) | AU5: =IF(OR(E96=0,AU$3<D96),0,E96*IF(G96=0,H96,MIN(H96,H96*(AU$3-D96+1)/MAX(1,G96)))*(1+F96)^(AU$3-D96)*$E93) | AV5: =IF(OR(E96=0,AV$3<D96),0,E96*IF(G96=0,H96,MIN(H96,H96*(AV$3-D96+1)/MAX(1,G96)))*(1+F96)^(AV$3-D96)*$E93) | AW5: =IF(OR(E96=0,AW$3<D96),0,E96*IF(G96=0,H96,MIN(H96,H96*(AW$3-D96+1)/MAX(1,G96)))*(1+F96)^(AW$3-D96)*$E93) | AX5: =IF(OR(E96=0,AX$3<D96),0,E96*IF(G96=0,H96,MIN(H96,H96*(AX$3-D96+1)/MAX(1,G96)))*(1+F96)^(AX$3-D96)*$E93) | AY5: =IF(OR(E96=0,AY$3<D96),0,E96*IF(G96=0,H96,MIN(H96,H96*(AY$3-D96+1)/MAX(1,G96)))*(1+F96)^(AY$3-D96)*$E93) | AZ5: =IF(OR(E96=0,AZ$3<D96),0,E96*IF(G96=0,H96,MIN(H96,H96*(AZ$3-D96+1)/MAX(1,G96)))*(1+F96)^(AZ$3-D96)*$E93) | BA5: =IF(OR(E96=0,BA$3<D96),0,E96*IF(G96=0,H96,MIN(H96,H96*(BA$3-D96+1)/MAX(1,G96)))*(1+F96)^(BA$3-D96)*$E93) | BB5: =IF(OR(E96=0,BB$3<D96),0,E96*IF(G96=0,H96,MIN(H96,H96*(BB$3-D96+1)/MAX(1,G96)))*(1+F96)^(BB$3-D96)*$E93)
A6: =A97 | B6: =B97 | C6: =C97 | D6: =SUM(E6:BB6) | E6: =IF(OR(E97=0,E$3<D97),0,E97*IF(G97=0,H97,MIN(H97,H97*(E$3-D97+1)/MAX(1,G97)))*(1+F97)^(E$3-D97)*$E93) | F6: =IF(OR(E97=0,F$3<D97),0,E97*IF(G97=0,H97,MIN(H97,H97*(F$3-D97+1)/MAX(1,G97)))*(1+F97)^(F$3-D97)*$E93) | G6: =IF(OR(E97=0,G$3<D97),0,E97*IF(G97=0,H97,MIN(H97,H97*(G$3-D97+1)/MAX(1,G97)))*(1+F97)^(G$3-D97)*$E93) | H6: =IF(OR(E97=0,H$3<D97),0,E97*IF(G97=0,H97,MIN(H97,H97*(H$3-D97+1)/MAX(1,G97)))*(1+F97)^(H$3-D97)*$E93) | I6: =IF(OR(E97=0,I$3<D97),0,E97*IF(G97=0,H97,MIN(H97,H97*(I$3-D97+1)/MAX(1,G97)))*(1+F97)^(I$3-D97)*$E93) | J6: =IF(OR(E97=0,J$3<D97),0,E97*IF(G97=0,H97,MIN(H97,H97*(J$3-D97+1)/MAX(1,G97)))*(1+F97)^(J$3-D97)*$E93) | K6: =IF(OR(E97=0,K$3<D97),0,E97*IF(G97=0,H97,MIN(H97,H97*(K$3-D97+1)/MAX(1,G97)))*(1+F97)^(K$3-D97)*$E93) | L6: =IF(OR(E97=0,L$3<D97),0,E97*IF(G97=0,H97,MIN(H97,H97*(L$3-D97+1)/MAX(1,G97)))*(1+F97)^(L$3-D97)*$E93) | M6: =IF(OR(E97=0,M$3<D97),0,E97*IF(G97=0,H97,MIN(H97,H97*(M$3-D97+1)/MAX(1,G97)))*(1+F97)^(M$3-D97)*$E93) | N6: =IF(OR(E97=0,N$3<D97),0,E97*IF(G97=0,H97,MIN(H97,H97*(N$3-D97+1)/MAX(1,G97)))*(1+F97)^(N$3-D97)*$E93) | O6: =IF(OR(E97=0,O$3<D97),0,E97*IF(G97=0,H97,MIN(H97,H97*(O$3-D97+1)/MAX(1,G97)))*(1+F97)^(O$3-D97)*$E93) | P6: =IF(OR(E97=0,P$3<D97),0,E97*IF(G97=0,H97,MIN(H97,H97*(P$3-D97+1)/MAX(1,G97)))*(1+F97)^(P$3-D97)*$E93) | Q6: =IF(OR(E97=0,Q$3<D97),0,E97*IF(G97=0,H97,MIN(H97,H97*(Q$3-D97+1)/MAX(1,G97)))*(1+F97)^(Q$3-D97)*$E93) | R6: =IF(OR(E97=0,R$3<D97),0,E97*IF(G97=0,H97,MIN(H97,H97*(R$3-D97+1)/MAX(1,G97)))*(1+F97)^(R$3-D97)*$E93) | S6: =IF(OR(E97=0,S$3<D97),0,E97*IF(G97=0,H97,MIN(H97,H97*(S$3-D97+1)/MAX(1,G97)))*(1+F97)^(S$3-D97)*$E93) | T6: =IF(OR(E97=0,T$3<D97),0,E97*IF(G97=0,H97,MIN(H97,H97*(T$3-D97+1)/MAX(1,G97)))*(1+F97)^(T$3-D97)*$E93) | U6: =IF(OR(E97=0,U$3<D97),0,E97*IF(G97=0,H97,MIN(H97,H97*(U$3-D97+1)/MAX(1,G97)))*(1+F97)^(U$3-D97)*$E93) | V6: =IF(OR(E97=0,V$3<D97),0,E97*IF(G97=0,H97,MIN(H97,H97*(V$3-D97+1)/MAX(1,G97)))*(1+F97)^(V$3-D97)*$E93) | W6: =IF(OR(E97=0,W$3<D97),0,E97*IF(G97=0,H97,MIN(H97,H97*(W$3-D97+1)/MAX(1,G97)))*(1+F97)^(W$3-D97)*$E93) | X6: =IF(OR(E97=0,X$3<D97),0,E97*IF(G97=0,H97,MIN(H97,H97*(X$3-D97+1)/MAX(1,G97)))*(1+F97)^(X$3-D97)*$E93) | Y6: =IF(OR(E97=0,Y$3<D97),0,E97*IF(G97=0,H97,MIN(H97,H97*(Y$3-D97+1)/MAX(1,G97)))*(1+F97)^(Y$3-D97)*$E93) | Z6: =IF(OR(E97=0,Z$3<D97),0,E97*IF(G97=0,H97,MIN(H97,H97*(Z$3-D97+1)/MAX(1,G97)))*(1+F97)^(Z$3-D97)*$E93) | AA6: =IF(OR(E97=0,AA$3<D97),0,E97*IF(G97=0,H97,MIN(H97,H97*(AA$3-D97+1)/MAX(1,G97)))*(1+F97)^(AA$3-D97)*$E93) | AB6: =IF(OR(E97=0,AB$3<D97),0,E97*IF(G97=0,H97,MIN(H97,H97*(AB$3-D97+1)/MAX(1,G97)))*(1+F97)^(AB$3-D97)*$E93) | AC6: =IF(OR(E97=0,AC$3<D97),0,E97*IF(G97=0,H97,MIN(H97,H97*(AC$3-D97+1)/MAX(1,G97)))*(1+F97)^(AC$3-D97)*$E93) | AD6: =IF(OR(E97=0,AD$3<D97),0,E97*IF(G97=0,H97,MIN(H97,H97*(AD$3-D97+1)/MAX(1,G97)))*(1+F97)^(AD$3-D97)*$E93) | AE6: =IF(OR(E97=0,AE$3<D97),0,E97*IF(G97=0,H97,MIN(H97,H97*(AE$3-D97+1)/MAX(1,G97)))*(1+F97)^(AE$3-D97)*$E93) | AF6: =IF(OR(E97=0,AF$3<D97),0,E97*IF(G97=0,H97,MIN(H97,H97*(AF$3-D97+1)/MAX(1,G97)))*(1+F97)^(AF$3-D97)*$E93) | AG6: =IF(OR(E97=0,AG$3<D97),0,E97*IF(G97=0,H97,MIN(H97,H97*(AG$3-D97+1)/MAX(1,G97)))*(1+F97)^(AG$3-D97)*$E93) | AH6: =IF(OR(E97=0,AH$3<D97),0,E97*IF(G97=0,H97,MIN(H97,H97*(AH$3-D97+1)/MAX(1,G97)))*(1+F97)^(AH$3-D97)*$E93) | AI6: =IF(OR(E97=0,AI$3<D97),0,E97*IF(G97=0,H97,MIN(H97,H97*(AI$3-D97+1)/MAX(1,G97)))*(1+F97)^(AI$3-D97)*$E93) | AJ6: =IF(OR(E97=0,AJ$3<D97),0,E97*IF(G97=0,H97,MIN(H97,H97*(AJ$3-D97+1)/MAX(1,G97)))*(1+F97)^(AJ$3-D97)*$E93) | AK6: =IF(OR(E97=0,AK$3<D97),0,E97*IF(G97=0,H97,MIN(H97,H97*(AK$3-D97+1)/MAX(1,G97)))*(1+F97)^(AK$3-D97)*$E93) | AL6: =IF(OR(E97=0,AL$3<D97),0,E97*IF(G97=0,H97,MIN(H97,H97*(AL$3-D97+1)/MAX(1,G97)))*(1+F97)^(AL$3-D97)*$E93) | AM6: =IF(OR(E97=0,AM$3<D97),0,E97*IF(G97=0,H97,MIN(H97,H97*(AM$3-D97+1)/MAX(1,G97)))*(1+F97)^(AM$3-D97)*$E93) | AN6: =IF(OR(E97=0,AN$3<D97),0,E97*IF(G97=0,H97,MIN(H97,H97*(AN$3-D97+1)/MAX(1,G97)))*(1+F97)^(AN$3-D97)*$E93) | AO6: =IF(OR(E97=0,AO$3<D97),0,E97*IF(G97=0,H97,MIN(H97,H97*(AO$3-D97+1)/MAX(1,G97)))*(1+F97)^(AO$3-D97)*$E93) | AP6: =IF(OR(E97=0,AP$3<D97),0,E97*IF(G97=0,H97,MIN(H97,H97*(AP$3-D97+1)/MAX(1,G97)))*(1+F97)^(AP$3-D97)*$E93) | AQ6: =IF(OR(E97=0,AQ$3<D97),0,E97*IF(G97=0,H97,MIN(H97,H97*(AQ$3-D97+1)/MAX(1,G97)))*(1+F97)^(AQ$3-D97)*$E93) | AR6: =IF(OR(E97=0,AR$3<D97),0,E97*IF(G97=0,H97,MIN(H97,H97*(AR$3-D97+1)/MAX(1,G97)))*(1+F97)^(AR$3-D97)*$E93) | AS6: =IF(OR(E97=0,AS$3<D97),0,E97*IF(G97=0,H97,MIN(H97,H97*(AS$3-D97+1)/MAX(1,G97)))*(1+F97)^(AS$3-D97)*$E93) | AT6: =IF(OR(E97=0,AT$3<D97),0,E97*IF(G97=0,H97,MIN(H97,H97*(AT$3-D97+1)/MAX(1,G97)))*(1+F97)^(AT$3-D97)*$E93) | AU6: =IF(OR(E97=0,AU$3<D97),0,E97*IF(G97=0,H97,MIN(H97,H97*(AU$3-D97+1)/MAX(1,G97)))*(1+F97)^(AU$3-D97)*$E93) | AV6: =IF(OR(E97=0,AV$3<D97),0,E97*IF(G97=0,H97,MIN(H97,H97*(AV$3-D97+1)/MAX(1,G97)))*(1+F97)^(AV$3-D97)*$E93) | AW6: =IF(OR(E97=0,AW$3<D97),0,E97*IF(G97=0,H97,MIN(H97,H97*(AW$3-D97+1)/MAX(1,G97)))*(1+F97)^(AW$3-D97)*$E93) | AX6: =IF(OR(E97=0,AX$3<D97),0,E97*IF(G97=0,H97,MIN(H97,H97*(AX$3-D97+1)/MAX(1,G97)))*(1+F97)^(AX$3-D97)*$E93) | AY6: =IF(OR(E97=0,AY$3<D97),0,E97*IF(G97=0,H97,MIN(H97,H97*(AY$3-D97+1)/MAX(1,G97)))*(1+F97)^(AY$3-D97)*$E93) | AZ6: =IF(OR(E97=0,AZ$3<D97),0,E97*IF(G97=0,H97,MIN(H97,H97*(AZ$3-D97+1)/MAX(1,G97)))*(1+F97)^(AZ$3-D97)*$E93) | BA6: =IF(OR(E97=0,BA$3<D97),0,E97*IF(G97=0,H97,MIN(H97,H97*(BA$3-D97+1)/MAX(1,G97)))*(1+F97)^(BA$3-D97)*$E93) | BB6: =IF(OR(E97=0,BB$3<D97),0,E97*IF(G97=0,H97,MIN(H97,H97*(BB$3-D97+1)/MAX(1,G97)))*(1+F97)^(BB$3-D97)*$E93)
A7: =A98 | B7: =B98 | C7: =C98 | D7: =SUM(E7:BB7) | E7: =IF(OR(E98=0,E$3<D98),0,E98*IF(G98=0,H98,MIN(H98,H98*(E$3-D98+1)/MAX(1,G98)))*(1+F98)^(E$3-D98)*$E93) | F7: =IF(OR(E98=0,F$3<D98),0,E98*IF(G98=0,H98,MIN(H98,H98*(F$3-D98+1)/MAX(1,G98)))*(1+F98)^(F$3-D98)*$E93) | G7: =IF(OR(E98=0,G$3<D98),0,E98*IF(G98=0,H98,MIN(H98,H98*(G$3-D98+1)/MAX(1,G98)))*(1+F98)^(G$3-D98)*$E93) | H7: =IF(OR(E98=0,H$3<D98),0,E98*IF(G98=0,H98,MIN(H98,H98*(H$3-D98+1)/MAX(1,G98)))*(1+F98)^(H$3-D98)*$E93) | I7: =IF(OR(E98=0,I$3<D98),0,E98*IF(G98=0,H98,MIN(H98,H98*(I$3-D98+1)/MAX(1,G98)))*(1+F98)^(I$3-D98)*$E93) | J7: =IF(OR(E98=0,J$3<D98),0,E98*IF(G98=0,H98,MIN(H98,H98*(J$3-D98+1)/MAX(1,G98)))*(1+F98)^(J$3-D98)*$E93) | K7: =IF(OR(E98=0,K$3<D98),0,E98*IF(G98=0,H98,MIN(H98,H98*(K$3-D98+1)/MAX(1,G98)))*(1+F98)^(K$3-D98)*$E93) | L7: =IF(OR(E98=0,L$3<D98),0,E98*IF(G98=0,H98,MIN(H98,H98*(L$3-D98+1)/MAX(1,G98)))*(1+F98)^(L$3-D98)*$E93) | M7: =IF(OR(E98=0,M$3<D98),0,E98*IF(G98=0,H98,MIN(H98,H98*(M$3-D98+1)/MAX(1,G98)))*(1+F98)^(M$3-D98)*$E93) | N7: =IF(OR(E98=0,N$3<D98),0,E98*IF(G98=0,H98,MIN(H98,H98*(N$3-D98+1)/MAX(1,G98)))*(1+F98)^(N$3-D98)*$E93) | O7: =IF(OR(E98=0,O$3<D98),0,E98*IF(G98=0,H98,MIN(H98,H98*(O$3-D98+1)/MAX(1,G98)))*(1+F98)^(O$3-D98)*$E93) | P7: =IF(OR(E98=0,P$3<D98),0,E98*IF(G98=0,H98,MIN(H98,H98*(P$3-D98+1)/MAX(1,G98)))*(1+F98)^(P$3-D98)*$E93) | Q7: =IF(OR(E98=0,Q$3<D98),0,E98*IF(G98=0,H98,MIN(H98,H98*(Q$3-D98+1)/MAX(1,G98)))*(1+F98)^(Q$3-D98)*$E93) | R7: =IF(OR(E98=0,R$3<D98),0,E98*IF(G98=0,H98,MIN(H98,H98*(R$3-D98+1)/MAX(1,G98)))*(1+F98)^(R$3-D98)*$E93) | S7: =IF(OR(E98=0,S$3<D98),0,E98*IF(G98=0,H98,MIN(H98,H98*(S$3-D98+1)/MAX(1,G98)))*(1+F98)^(S$3-D98)*$E93) | T7: =IF(OR(E98=0,T$3<D98),0,E98*IF(G98=0,H98,MIN(H98,H98*(T$3-D98+1)/MAX(1,G98)))*(1+F98)^(T$3-D98)*$E93) | U7: =IF(OR(E98=0,U$3<D98),0,E98*IF(G98=0,H98,MIN(H98,H98*(U$3-D98+1)/MAX(1,G98)))*(1+F98)^(U$3-D98)*$E93) | V7: =IF(OR(E98=0,V$3<D98),0,E98*IF(G98=0,H98,MIN(H98,H98*(V$3-D98+1)/MAX(1,G98)))*(1+F98)^(V$3-D98)*$E93) | W7: =IF(OR(E98=0,W$3<D98),0,E98*IF(G98=0,H98,MIN(H98,H98*(W$3-D98+1)/MAX(1,G98)))*(1+F98)^(W$3-D98)*$E93) | X7: =IF(OR(E98=0,X$3<D98),0,E98*IF(G98=0,H98,MIN(H98,H98*(X$3-D98+1)/MAX(1,G98)))*(1+F98)^(X$3-D98)*$E93) | Y7: =IF(OR(E98=0,Y$3<D98),0,E98*IF(G98=0,H98,MIN(H98,H98*(Y$3-D98+1)/MAX(1,G98)))*(1+F98)^(Y$3-D98)*$E93) | Z7: =IF(OR(E98=0,Z$3<D98),0,E98*IF(G98=0,H98,MIN(H98,H98*(Z$3-D98+1)/MAX(1,G98)))*(1+F98)^(Z$3-D98)*$E93) | AA7: =IF(OR(E98=0,AA$3<D98),0,E98*IF(G98=0,H98,MIN(H98,H98*(AA$3-D98+1)/MAX(1,G98)))*(1+F98)^(AA$3-D98)*$E93) | AB7: =IF(OR(E98=0,AB$3<D98),0,E98*IF(G98=0,H98,MIN(H98,H98*(AB$3-D98+1)/MAX(1,G98)))*(1+F98)^(AB$3-D98)*$E93) | AC7: =IF(OR(E98=0,AC$3<D98),0,E98*IF(G98=0,H98,MIN(H98,H98*(AC$3-D98+1)/MAX(1,G98)))*(1+F98)^(AC$3-D98)*$E93) | AD7: =IF(OR(E98=0,AD$3<D98),0,E98*IF(G98=0,H98,MIN(H98,H98*(AD$3-D98+1)/MAX(1,G98)))*(1+F98)^(AD$3-D98)*$E93) | AE7: =IF(OR(E98=0,AE$3<D98),0,E98*IF(G98=0,H98,MIN(H98,H98*(AE$3-D98+1)/MAX(1,G98)))*(1+F98)^(AE$3-D98)*$E93) | AF7: =IF(OR(E98=0,AF$3<D98),0,E98*IF(G98=0,H98,MIN(H98,H98*(AF$3-D98+1)/MAX(1,G98)))*(1+F98)^(AF$3-D98)*$E93) | AG7: =IF(OR(E98=0,AG$3<D98),0,E98*IF(G98=0,H98,MIN(H98,H98*(AG$3-D98+1)/MAX(1,G98)))*(1+F98)^(AG$3-D98)*$E93) | AH7: =IF(OR(E98=0,AH$3<D98),0,E98*IF(G98=0,H98,MIN(H98,H98*(AH$3-D98+1)/MAX(1,G98)))*(1+F98)^(AH$3-D98)*$E93) | AI7: =IF(OR(E98=0,AI$3<D98),0,E98*IF(G98=0,H98,MIN(H98,H98*(AI$3-D98+1)/MAX(1,G98)))*(1+F98)^(AI$3-D98)*$E93) | AJ7: =IF(OR(E98=0,AJ$3<D98),0,E98*IF(G98=0,H98,MIN(H98,H98*(AJ$3-D98+1)/MAX(1,G98)))*(1+F98)^(AJ$3-D98)*$E93) | AK7: =IF(OR(E98=0,AK$3<D98),0,E98*IF(G98=0,H98,MIN(H98,H98*(AK$3-D98+1)/MAX(1,G98)))*(1+F98)^(AK$3-D98)*$E93) | AL7: =IF(OR(E98=0,AL$3<D98),0,E98*IF(G98=0,H98,MIN(H98,H98*(AL$3-D98+1)/MAX(1,G98)))*(1+F98)^(AL$3-D98)*$E93) | AM7: =IF(OR(E98=0,AM$3<D98),0,E98*IF(G98=0,H98,MIN(H98,H98*(AM$3-D98+1)/MAX(1,G98)))*(1+F98)^(AM$3-D98)*$E93) | AN7: =IF(OR(E98=0,AN$3<D98),0,E98*IF(G98=0,H98,MIN(H98,H98*(AN$3-D98+1)/MAX(1,G98)))*(1+F98)^(AN$3-D98)*$E93) | AO7: =IF(OR(E98=0,AO$3<D98),0,E98*IF(G98=0,H98,MIN(H98,H98*(AO$3-D98+1)/MAX(1,G98)))*(1+F98)^(AO$3-D98)*$E93) | AP7: =IF(OR(E98=0,AP$3<D98),0,E98*IF(G98=0,H98,MIN(H98,H98*(AP$3-D98+1)/MAX(1,G98)))*(1+F98)^(AP$3-D98)*$E93) | AQ7: =IF(OR(E98=0,AQ$3<D98),0,E98*IF(G98=0,H98,MIN(H98,H98*(AQ$3-D98+1)/MAX(1,G98)))*(1+F98)^(AQ$3-D98)*$E93) | AR7: =IF(OR(E98=0,AR$3<D98),0,E98*IF(G98=0,H98,MIN(H98,H98*(AR$3-D98+1)/MAX(1,G98)))*(1+F98)^(AR$3-D98)*$E93) | AS7: =IF(OR(E98=0,AS$3<D98),0,E98*IF(G98=0,H98,MIN(H98,H98*(AS$3-D98+1)/MAX(1,G98)))*(1+F98)^(AS$3-D98)*$E93) | AT7: =IF(OR(E98=0,AT$3<D98),0,E98*IF(G98=0,H98,MIN(H98,H98*(AT$3-D98+1)/MAX(1,G98)))*(1+F98)^(AT$3-D98)*$E93) | AU7: =IF(OR(E98=0,AU$3<D98),0,E98*IF(G98=0,H98,MIN(H98,H98*(AU$3-D98+1)/MAX(1,G98)))*(1+F98)^(AU$3-D98)*$E93) | AV7: =IF(OR(E98=0,AV$3<D98),0,E98*IF(G98=0,H98,MIN(H98,H98*(AV$3-D98+1)/MAX(1,G98)))*(1+F98)^(AV$3-D98)*$E93) | AW7: =IF(OR(E98=0,AW$3<D98),0,E98*IF(G98=0,H98,MIN(H98,H98*(AW$3-D98+1)/MAX(1,G98)))*(1+F98)^(AW$3-D98)*$E93) | AX7: =IF(OR(E98=0,AX$3<D98),0,E98*IF(G98=0,H98,MIN(H98,H98*(AX$3-D98+1)/MAX(1,G98)))*(1+F98)^(AX$3-D98)*$E93) | AY7: =IF(OR(E98=0,AY$3<D98),0,E98*IF(G98=0,H98,MIN(H98,H98*(AY$3-D98+1)/MAX(1,G98)))*(1+F98)^(AY$3-D98)*$E93) | AZ7: =IF(OR(E98=0,AZ$3<D98),0,E98*IF(G98=0,H98,MIN(H98,H98*(AZ$3-D98+1)/MAX(1,G98)))*(1+F98)^(AZ$3-D98)*$E93) | BA7: =IF(OR(E98=0,BA$3<D98),0,E98*IF(G98=0,H98,MIN(H98,H98*(BA$3-D98+1)/MAX(1,G98)))*(1+F98)^(BA$3-D98)*$E93) | BB7: =IF(OR(E98=0,BB$3<D98),0,E98*IF(G98=0,H98,MIN(H98,H98*(BB$3-D98+1)/MAX(1,G98)))*(1+F98)^(BB$3-D98)*$E93)
A8: =A99 | B8: =B99 | C8: =C99 | D8: =SUM(E8:BB8) | E8: =IF(OR(E99=0,E$3<D99),0,E99*IF(G99=0,H99,MIN(H99,H99*(E$3-D99+1)/MAX(1,G99)))*(1+F99)^(E$3-D99)*$E93) | F8: =IF(OR(E99=0,F$3<D99),0,E99*IF(G99=0,H99,MIN(H99,H99*(F$3-D99+1)/MAX(1,G99)))*(1+F99)^(F$3-D99)*$E93) | G8: =IF(OR(E99=0,G$3<D99),0,E99*IF(G99=0,H99,MIN(H99,H99*(G$3-D99+1)/MAX(1,G99)))*(1+F99)^(G$3-D99)*$E93) | H8: =IF(OR(E99=0,H$3<D99),0,E99*IF(G99=0,H99,MIN(H99,H99*(H$3-D99+1)/MAX(1,G99)))*(1+F99)^(H$3-D99)*$E93) | I8: =IF(OR(E99=0,I$3<D99),0,E99*IF(G99=0,H99,MIN(H99,H99*(I$3-D99+1)/MAX(1,G99)))*(1+F99)^(I$3-D99)*$E93) | J8: =IF(OR(E99=0,J$3<D99),0,E99*IF(G99=0,H99,MIN(H99,H99*(J$3-D99+1)/MAX(1,G99)))*(1+F99)^(J$3-D99)*$E93) | K8: =IF(OR(E99=0,K$3<D99),0,E99*IF(G99=0,H99,MIN(H99,H99*(K$3-D99+1)/MAX(1,G99)))*(1+F99)^(K$3-D99)*$E93) | L8: =IF(OR(E99=0,L$3<D99),0,E99*IF(G99=0,H99,MIN(H99,H99*(L$3-D99+1)/MAX(1,G99)))*(1+F99)^(L$3-D99)*$E93) | M8: =IF(OR(E99=0,M$3<D99),0,E99*IF(G99=0,H99,MIN(H99,H99*(M$3-D99+1)/MAX(1,G99)))*(1+F99)^(M$3-D99)*$E93) | N8: =IF(OR(E99=0,N$3<D99),0,E99*IF(G99=0,H99,MIN(H99,H99*(N$3-D99+1)/MAX(1,G99)))*(1+F99)^(N$3-D99)*$E93) | O8: =IF(OR(E99=0,O$3<D99),0,E99*IF(G99=0,H99,MIN(H99,H99*(O$3-D99+1)/MAX(1,G99)))*(1+F99)^(O$3-D99)*$E93) | P8: =IF(OR(E99=0,P$3<D99),0,E99*IF(G99=0,H99,MIN(H99,H99*(P$3-D99+1)/MAX(1,G99)))*(1+F99)^(P$3-D99)*$E93) | Q8: =IF(OR(E99=0,Q$3<D99),0,E99*IF(G99=0,H99,MIN(H99,H99*(Q$3-D99+1)/MAX(1,G99)))*(1+F99)^(Q$3-D99)*$E93) | R8: =IF(OR(E99=0,R$3<D99),0,E99*IF(G99=0,H99,MIN(H99,H99*(R$3-D99+1)/MAX(1,G99)))*(1+F99)^(R$3-D99)*$E93) | S8: =IF(OR(E99=0,S$3<D99),0,E99*IF(G99=0,H99,MIN(H99,H99*(S$3-D99+1)/MAX(1,G99)))*(1+F99)^(S$3-D99)*$E93) | T8: =IF(OR(E99=0,T$3<D99),0,E99*IF(G99=0,H99,MIN(H99,H99*(T$3-D99+1)/MAX(1,G99)))*(1+F99)^(T$3-D99)*$E93) | U8: =IF(OR(E99=0,U$3<D99),0,E99*IF(G99=0,H99,MIN(H99,H99*(U$3-D99+1)/MAX(1,G99)))*(1+F99)^(U$3-D99)*$E93) | V8: =IF(OR(E99=0,V$3<D99),0,E99*IF(G99=0,H99,MIN(H99,H99*(V$3-D99+1)/MAX(1,G99)))*(1+F99)^(V$3-D99)*$E93) | W8: =IF(OR(E99=0,W$3<D99),0,E99*IF(G99=0,H99,MIN(H99,H99*(W$3-D99+1)/MAX(1,G99)))*(1+F99)^(W$3-D99)*$E93) | X8: =IF(OR(E99=0,X$3<D99),0,E99*IF(G99=0,H99,MIN(H99,H99*(X$3-D99+1)/MAX(1,G99)))*(1+F99)^(X$3-D99)*$E93) | Y8: =IF(OR(E99=0,Y$3<D99),0,E99*IF(G99=0,H99,MIN(H99,H99*(Y$3-D99+1)/MAX(1,G99)))*(1+F99)^(Y$3-D99)*$E93) | Z8: =IF(OR(E99=0,Z$3<D99),0,E99*IF(G99=0,H99,MIN(H99,H99*(Z$3-D99+1)/MAX(1,G99)))*(1+F99)^(Z$3-D99)*$E93) | AA8: =IF(OR(E99=0,AA$3<D99),0,E99*IF(G99=0,H99,MIN(H99,H99*(AA$3-D99+1)/MAX(1,G99)))*(1+F99)^(AA$3-D99)*$E93) | AB8: =IF(OR(E99=0,AB$3<D99),0,E99*IF(G99=0,H99,MIN(H99,H99*(AB$3-D99+1)/MAX(1,G99)))*(1+F99)^(AB$3-D99)*$E93) | AC8: =IF(OR(E99=0,AC$3<D99),0,E99*IF(G99=0,H99,MIN(H99,H99*(AC$3-D99+1)/MAX(1,G99)))*(1+F99)^(AC$3-D99)*$E93) | AD8: =IF(OR(E99=0,AD$3<D99),0,E99*IF(G99=0,H99,MIN(H99,H99*(AD$3-D99+1)/MAX(1,G99)))*(1+F99)^(AD$3-D99)*$E93) | AE8: =IF(OR(E99=0,AE$3<D99),0,E99*IF(G99=0,H99,MIN(H99,H99*(AE$3-D99+1)/MAX(1,G99)))*(1+F99)^(AE$3-D99)*$E93) | AF8: =IF(OR(E99=0,AF$3<D99),0,E99*IF(G99=0,H99,MIN(H99,H99*(AF$3-D99+1)/MAX(1,G99)))*(1+F99)^(AF$3-D99)*$E93) | AG8: =IF(OR(E99=0,AG$3<D99),0,E99*IF(G99=0,H99,MIN(H99,H99*(AG$3-D99+1)/MAX(1,G99)))*(1+F99)^(AG$3-D99)*$E93) | AH8: =IF(OR(E99=0,AH$3<D99),0,E99*IF(G99=0,H99,MIN(H99,H99*(AH$3-D99+1)/MAX(1,G99)))*(1+F99)^(AH$3-D99)*$E93) | AI8: =IF(OR(E99=0,AI$3<D99),0,E99*IF(G99=0,H99,MIN(H99,H99*(AI$3-D99+1)/MAX(1,G99)))*(1+F99)^(AI$3-D99)*$E93) | AJ8: =IF(OR(E99=0,AJ$3<D99),0,E99*IF(G99=0,H99,MIN(H99,H99*(AJ$3-D99+1)/MAX(1,G99)))*(1+F99)^(AJ$3-D99)*$E93) | AK8: =IF(OR(E99=0,AK$3<D99),0,E99*IF(G99=0,H99,MIN(H99,H99*(AK$3-D99+1)/MAX(1,G99)))*(1+F99)^(AK$3-D99)*$E93) | AL8: =IF(OR(E99=0,AL$3<D99),0,E99*IF(G99=0,H99,MIN(H99,H99*(AL$3-D99+1)/MAX(1,G99)))*(1+F99)^(AL$3-D99)*$E93) | AM8: =IF(OR(E99=0,AM$3<D99),0,E99*IF(G99=0,H99,MIN(H99,H99*(AM$3-D99+1)/MAX(1,G99)))*(1+F99)^(AM$3-D99)*$E93) | AN8: =IF(OR(E99=0,AN$3<D99),0,E99*IF(G99=0,H99,MIN(H99,H99*(AN$3-D99+1)/MAX(1,G99)))*(1+F99)^(AN$3-D99)*$E93) | AO8: =IF(OR(E99=0,AO$3<D99),0,E99*IF(G99=0,H99,MIN(H99,H99*(AO$3-D99+1)/MAX(1,G99)))*(1+F99)^(AO$3-D99)*$E93) | AP8: =IF(OR(E99=0,AP$3<D99),0,E99*IF(G99=0,H99,MIN(H99,H99*(AP$3-D99+1)/MAX(1,G99)))*(1+F99)^(AP$3-D99)*$E93) | AQ8: =IF(OR(E99=0,AQ$3<D99),0,E99*IF(G99=0,H99,MIN(H99,H99*(AQ$3-D99+1)/MAX(1,G99)))*(1+F99)^(AQ$3-D99)*$E93) | AR8: =IF(OR(E99=0,AR$3<D99),0,E99*IF(G99=0,H99,MIN(H99,H99*(AR$3-D99+1)/MAX(1,G99)))*(1+F99)^(AR$3-D99)*$E93) | AS8: =IF(OR(E99=0,AS$3<D99),0,E99*IF(G99=0,H99,MIN(H99,H99*(AS$3-D99+1)/MAX(1,G99)))*(1+F99)^(AS$3-D99)*$E93) | AT8: =IF(OR(E99=0,AT$3<D99),0,E99*IF(G99=0,H99,MIN(H99,H99*(AT$3-D99+1)/MAX(1,G99)))*(1+F99)^(AT$3-D99)*$E93) | AU8: =IF(OR(E99=0,AU$3<D99),0,E99*IF(G99=0,H99,MIN(H99,H99*(AU$3-D99+1)/MAX(1,G99)))*(1+F99)^(AU$3-D99)*$E93) | AV8: =IF(OR(E99=0,AV$3<D99),0,E99*IF(G99=0,H99,MIN(H99,H99*(AV$3-D99+1)/MAX(1,G99)))*(1+F99)^(AV$3-D99)*$E93) | AW8: =IF(OR(E99=0,AW$3<D99),0,E99*IF(G99=0,H99,MIN(H99,H99*(AW$3-D99+1)/MAX(1,G99)))*(1+F99)^(AW$3-D99)*$E93) | AX8: =IF(OR(E99=0,AX$3<D99),0,E99*IF(G99=0,H99,MIN(H99,H99*(AX$3-D99+1)/MAX(1,G99)))*(1+F99)^(AX$3-D99)*$E93) | AY8: =IF(OR(E99=0,AY$3<D99),0,E99*IF(G99=0,H99,MIN(H99,H99*(AY$3-D99+1)/MAX(1,G99)))*(1+F99)^(AY$3-D99)*$E93) | AZ8: =IF(OR(E99=0,AZ$3<D99),0,E99*IF(G99=0,H99,MIN(H99,H99*(AZ$3-D99+1)/MAX(1,G99)))*(1+F99)^(AZ$3-D99)*$E93) | BA8: =IF(OR(E99=0,BA$3<D99),0,E99*IF(G99=0,H99,MIN(H99,H99*(BA$3-D99+1)/MAX(1,G99)))*(1+F99)^(BA$3-D99)*$E93) | BB8: =IF(OR(E99=0,BB$3<D99),0,E99*IF(G99=0,H99,MIN(H99,H99*(BB$3-D99+1)/MAX(1,G99)))*(1+F99)^(BB$3-D99)*$E93)
A9: =A100 | B9: =B100 | C9: =C100 | D9: =SUM(E9:BB9) | E9: =IF(OR(E100=0,E$3<D100),0,E100*IF(G100=0,H100,MIN(H100,H100*(E$3-D100+1)/MAX(1,G100)))*(1+F100)^(E$3-D100)*$E93) | F9: =IF(OR(E100=0,F$3<D100),0,E100*IF(G100=0,H100,MIN(H100,H100*(F$3-D100+1)/MAX(1,G100)))*(1+F100)^(F$3-D100)*$E93) | G9: =IF(OR(E100=0,G$3<D100),0,E100*IF(G100=0,H100,MIN(H100,H100*(G$3-D100+1)/MAX(1,G100)))*(1+F100)^(G$3-D100)*$E93) | H9: =IF(OR(E100=0,H$3<D100),0,E100*IF(G100=0,H100,MIN(H100,H100*(H$3-D100+1)/MAX(1,G100)))*(1+F100)^(H$3-D100)*$E93) | I9: =IF(OR(E100=0,I$3<D100),0,E100*IF(G100=0,H100,MIN(H100,H100*(I$3-D100+1)/MAX(1,G100)))*(1+F100)^(I$3-D100)*$E93) | J9: =IF(OR(E100=0,J$3<D100),0,E100*IF(G100=0,H100,MIN(H100,H100*(J$3-D100+1)/MAX(1,G100)))*(1+F100)^(J$3-D100)*$E93) | K9: =IF(OR(E100=0,K$3<D100),0,E100*IF(G100=0,H100,MIN(H100,H100*(K$3-D100+1)/MAX(1,G100)))*(1+F100)^(K$3-D100)*$E93) | L9: =IF(OR(E100=0,L$3<D100),0,E100*IF(G100=0,H100,MIN(H100,H100*(L$3-D100+1)/MAX(1,G100)))*(1+F100)^(L$3-D100)*$E93) | M9: =IF(OR(E100=0,M$3<D100),0,E100*IF(G100=0,H100,MIN(H100,H100*(M$3-D100+1)/MAX(1,G100)))*(1+F100)^(M$3-D100)*$E93) | N9: =IF(OR(E100=0,N$3<D100),0,E100*IF(G100=0,H100,MIN(H100,H100*(N$3-D100+1)/MAX(1,G100)))*(1+F100)^(N$3-D100)*$E93) | O9: =IF(OR(E100=0,O$3<D100),0,E100*IF(G100=0,H100,MIN(H100,H100*(O$3-D100+1)/MAX(1,G100)))*(1+F100)^(O$3-D100)*$E93) | P9: =IF(OR(E100=0,P$3<D100),0,E100*IF(G100=0,H100,MIN(H100,H100*(P$3-D100+1)/MAX(1,G100)))*(1+F100)^(P$3-D100)*$E93) | Q9: =IF(OR(E100=0,Q$3<D100),0,E100*IF(G100=0,H100,MIN(H100,H100*(Q$3-D100+1)/MAX(1,G100)))*(1+F100)^(Q$3-D100)*$E93) | R9: =IF(OR(E100=0,R$3<D100),0,E100*IF(G100=0,H100,MIN(H100,H100*(R$3-D100+1)/MAX(1,G100)))*(1+F100)^(R$3-D100)*$E93) | S9: =IF(OR(E100=0,S$3<D100),0,E100*IF(G100=0,H100,MIN(H100,H100*(S$3-D100+1)/MAX(1,G100)))*(1+F100)^(S$3-D100)*$E93) | T9: =IF(OR(E100=0,T$3<D100),0,E100*IF(G100=0,H100,MIN(H100,H100*(T$3-D100+1)/MAX(1,G100)))*(1+F100)^(T$3-D100)*$E93) | U9: =IF(OR(E100=0,U$3<D100),0,E100*IF(G100=0,H100,MIN(H100,H100*(U$3-D100+1)/MAX(1,G100)))*(1+F100)^(U$3-D100)*$E93) | V9: =IF(OR(E100=0,V$3<D100),0,E100*IF(G100=0,H100,MIN(H100,H100*(V$3-D100+1)/MAX(1,G100)))*(1+F100)^(V$3-D100)*$E93) | W9: =IF(OR(E100=0,W$3<D100),0,E100*IF(G100=0,H100,MIN(H100,H100*(W$3-D100+1)/MAX(1,G100)))*(1+F100)^(W$3-D100)*$E93) | X9: =IF(OR(E100=0,X$3<D100),0,E100*IF(G100=0,H100,MIN(H100,H100*(X$3-D100+1)/MAX(1,G100)))*(1+F100)^(X$3-D100)*$E93) | Y9: =IF(OR(E100=0,Y$3<D100),0,E100*IF(G100=0,H100,MIN(H100,H100*(Y$3-D100+1)/MAX(1,G100)))*(1+F100)^(Y$3-D100)*$E93) | Z9: =IF(OR(E100=0,Z$3<D100),0,E100*IF(G100=0,H100,MIN(H100,H100*(Z$3-D100+1)/MAX(1,G100)))*(1+F100)^(Z$3-D100)*$E93) | AA9: =IF(OR(E100=0,AA$3<D100),0,E100*IF(G100=0,H100,MIN(H100,H100*(AA$3-D100+1)/MAX(1,G100)))*(1+F100)^(AA$3-D100)*$E93) | AB9: =IF(OR(E100=0,AB$3<D100),0,E100*IF(G100=0,H100,MIN(H100,H100*(AB$3-D100+1)/MAX(1,G100)))*(1+F100)^(AB$3-D100)*$E93) | AC9: =IF(OR(E100=0,AC$3<D100),0,E100*IF(G100=0,H100,MIN(H100,H100*(AC$3-D100+1)/MAX(1,G100)))*(1+F100)^(AC$3-D100)*$E93) | AD9: =IF(OR(E100=0,AD$3<D100),0,E100*IF(G100=0,H100,MIN(H100,H100*(AD$3-D100+1)/MAX(1,G100)))*(1+F100)^(AD$3-D100)*$E93) | AE9: =IF(OR(E100=0,AE$3<D100),0,E100*IF(G100=0,H100,MIN(H100,H100*(AE$3-D100+1)/MAX(1,G100)))*(1+F100)^(AE$3-D100)*$E93) | AF9: =IF(OR(E100=0,AF$3<D100),0,E100*IF(G100=0,H100,MIN(H100,H100*(AF$3-D100+1)/MAX(1,G100)))*(1+F100)^(AF$3-D100)*$E93) | AG9: =IF(OR(E100=0,AG$3<D100),0,E100*IF(G100=0,H100,MIN(H100,H100*(AG$3-D100+1)/MAX(1,G100)))*(1+F100)^(AG$3-D100)*$E93) | AH9: =IF(OR(E100=0,AH$3<D100),0,E100*IF(G100=0,H100,MIN(H100,H100*(AH$3-D100+1)/MAX(1,G100)))*(1+F100)^(AH$3-D100)*$E93) | AI9: =IF(OR(E100=0,AI$3<D100),0,E100*IF(G100=0,H100,MIN(H100,H100*(AI$3-D100+1)/MAX(1,G100)))*(1+F100)^(AI$3-D100)*$E93) | AJ9: =IF(OR(E100=0,AJ$3<D100),0,E100*IF(G100=0,H100,MIN(H100,H100*(AJ$3-D100+1)/MAX(1,G100)))*(1+F100)^(AJ$3-D100)*$E93) | AK9: =IF(OR(E100=0,AK$3<D100),0,E100*IF(G100=0,H100,MIN(H100,H100*(AK$3-D100+1)/MAX(1,G100)))*(1+F100)^(AK$3-D100)*$E93) | AL9: =IF(OR(E100=0,AL$3<D100),0,E100*IF(G100=0,H100,MIN(H100,H100*(AL$3-D100+1)/MAX(1,G100)))*(1+F100)^(AL$3-D100)*$E93) | AM9: =IF(OR(E100=0,AM$3<D100),0,E100*IF(G100=0,H100,MIN(H100,H100*(AM$3-D100+1)/MAX(1,G100)))*(1+F100)^(AM$3-D100)*$E93) | AN9: =IF(OR(E100=0,AN$3<D100),0,E100*IF(G100=0,H100,MIN(H100,H100*(AN$3-D100+1)/MAX(1,G100)))*(1+F100)^(AN$3-D100)*$E93) | AO9: =IF(OR(E100=0,AO$3<D100),0,E100*IF(G100=0,H100,MIN(H100,H100*(AO$3-D100+1)/MAX(1,G100)))*(1+F100)^(AO$3-D100)*$E93) | AP9: =IF(OR(E100=0,AP$3<D100),0,E100*IF(G100=0,H100,MIN(H100,H100*(AP$3-D100+1)/MAX(1,G100)))*(1+F100)^(AP$3-D100)*$E93) | AQ9: =IF(OR(E100=0,AQ$3<D100),0,E100*IF(G100=0,H100,MIN(H100,H100*(AQ$3-D100+1)/MAX(1,G100)))*(1+F100)^(AQ$3-D100)*$E93) | AR9: =IF(OR(E100=0,AR$3<D100),0,E100*IF(G100=0,H100,MIN(H100,H100*(AR$3-D100+1)/MAX(1,G100)))*(1+F100)^(AR$3-D100)*$E93) | AS9: =IF(OR(E100=0,AS$3<D100),0,E100*IF(G100=0,H100,MIN(H100,H100*(AS$3-D100+1)/MAX(1,G100)))*(1+F100)^(AS$3-D100)*$E93) | AT9: =IF(OR(E100=0,AT$3<D100),0,E100*IF(G100=0,H100,MIN(H100,H100*(AT$3-D100+1)/MAX(1,G100)))*(1+F100)^(AT$3-D100)*$E93) | AU9: =IF(OR(E100=0,AU$3<D100),0,E100*IF(G100=0,H100,MIN(H100,H100*(AU$3-D100+1)/MAX(1,G100)))*(1+F100)^(AU$3-D100)*$E93) | AV9: =IF(OR(E100=0,AV$3<D100),0,E100*IF(G100=0,H100,MIN(H100,H100*(AV$3-D100+1)/MAX(1,G100)))*(1+F100)^(AV$3-D100)*$E93) | AW9: =IF(OR(E100=0,AW$3<D100),0,E100*IF(G100=0,H100,MIN(H100,H100*(AW$3-D100+1)/MAX(1,G100)))*(1+F100)^(AW$3-D100)*$E93) | AX9: =IF(OR(E100=0,AX$3<D100),0,E100*IF(G100=0,H100,MIN(H100,H100*(AX$3-D100+1)/MAX(1,G100)))*(1+F100)^(AX$3-D100)*$E93) | AY9: =IF(OR(E100=0,AY$3<D100),0,E100*IF(G100=0,H100,MIN(H100,H100*(AY$3-D100+1)/MAX(1,G100)))*(1+F100)^(AY$3-D100)*$E93) | AZ9: =IF(OR(E100=0,AZ$3<D100),0,E100*IF(G100=0,H100,MIN(H100,H100*(AZ$3-D100+1)/MAX(1,G100)))*(1+F100)^(AZ$3-D100)*$E93) | BA9: =IF(OR(E100=0,BA$3<D100),0,E100*IF(G100=0,H100,MIN(H100,H100*(BA$3-D100+1)/MAX(1,G100)))*(1+F100)^(BA$3-D100)*$E93) | BB9: =IF(OR(E100=0,BB$3<D100),0,E100*IF(G100=0,H100,MIN(H100,H100*(BB$3-D100+1)/MAX(1,G100)))*(1+F100)^(BB$3-D100)*$E93)
A10: =A101 | B10: =B101 | C10: =C101 | D10: =SUM(E10:BB10) | E10: =IF(OR(E101=0,E$3<D101),0,E101*IF(G101=0,H101,MIN(H101,H101*(E$3-D101+1)/MAX(1,G101)))*(1+F101)^(E$3-D101)*$E93) | F10: =IF(OR(E101=0,F$3<D101),0,E101*IF(G101=0,H101,MIN(H101,H101*(F$3-D101+1)/MAX(1,G101)))*(1+F101)^(F$3-D101)*$E93) | G10: =IF(OR(E101=0,G$3<D101),0,E101*IF(G101=0,H101,MIN(H101,H101*(G$3-D101+1)/MAX(1,G101)))*(1+F101)^(G$3-D101)*$E93) | H10: =IF(OR(E101=0,H$3<D101),0,E101*IF(G101=0,H101,MIN(H101,H101*(H$3-D101+1)/MAX(1,G101)))*(1+F101)^(H$3-D101)*$E93) | I10: =IF(OR(E101=0,I$3<D101),0,E101*IF(G101=0,H101,MIN(H101,H101*(I$3-D101+1)/MAX(1,G101)))*(1+F101)^(I$3-D101)*$E93) | J10: =IF(OR(E101=0,J$3<D101),0,E101*IF(G101=0,H101,MIN(H101,H101*(J$3-D101+1)/MAX(1,G101)))*(1+F101)^(J$3-D101)*$E93) | K10: =IF(OR(E101=0,K$3<D101),0,E101*IF(G101=0,H101,MIN(H101,H101*(K$3-D101+1)/MAX(1,G101)))*(1+F101)^(K$3-D101)*$E93) | L10: =IF(OR(E101=0,L$3<D101),0,E101*IF(G101=0,H101,MIN(H101,H101*(L$3-D101+1)/MAX(1,G101)))*(1+F101)^(L$3-D101)*$E93) | M10: =IF(OR(E101=0,M$3<D101),0,E101*IF(G101=0,H101,MIN(H101,H101*(M$3-D101+1)/MAX(1,G101)))*(1+F101)^(M$3-D101)*$E93) | N10: =IF(OR(E101=0,N$3<D101),0,E101*IF(G101=0,H101,MIN(H101,H101*(N$3-D101+1)/MAX(1,G101)))*(1+F101)^(N$3-D101)*$E93) | O10: =IF(OR(E101=0,O$3<D101),0,E101*IF(G101=0,H101,MIN(H101,H101*(O$3-D101+1)/MAX(1,G101)))*(1+F101)^(O$3-D101)*$E93) | P10: =IF(OR(E101=0,P$3<D101),0,E101*IF(G101=0,H101,MIN(H101,H101*(P$3-D101+1)/MAX(1,G101)))*(1+F101)^(P$3-D101)*$E93) | Q10: =IF(OR(E101=0,Q$3<D101),0,E101*IF(G101=0,H101,MIN(H101,H101*(Q$3-D101+1)/MAX(1,G101)))*(1+F101)^(Q$3-D101)*$E93) | R10: =IF(OR(E101=0,R$3<D101),0,E101*IF(G101=0,H101,MIN(H101,H101*(R$3-D101+1)/MAX(1,G101)))*(1+F101)^(R$3-D101)*$E93) | S10: =IF(OR(E101=0,S$3<D101),0,E101*IF(G101=0,H101,MIN(H101,H101*(S$3-D101+1)/MAX(1,G101)))*(1+F101)^(S$3-D101)*$E93) | T10: =IF(OR(E101=0,T$3<D101),0,E101*IF(G101=0,H101,MIN(H101,H101*(T$3-D101+1)/MAX(1,G101)))*(1+F101)^(T$3-D101)*$E93) | U10: =IF(OR(E101=0,U$3<D101),0,E101*IF(G101=0,H101,MIN(H101,H101*(U$3-D101+1)/MAX(1,G101)))*(1+F101)^(U$3-D101)*$E93) | V10: =IF(OR(E101=0,V$3<D101),0,E101*IF(G101=0,H101,MIN(H101,H101*(V$3-D101+1)/MAX(1,G101)))*(1+F101)^(V$3-D101)*$E93) | W10: =IF(OR(E101=0,W$3<D101),0,E101*IF(G101=0,H101,MIN(H101,H101*(W$3-D101+1)/MAX(1,G101)))*(1+F101)^(W$3-D101)*$E93) | X10: =IF(OR(E101=0,X$3<D101),0,E101*IF(G101=0,H101,MIN(H101,H101*(X$3-D101+1)/MAX(1,G101)))*(1+F101)^(X$3-D101)*$E93) | Y10: =IF(OR(E101=0,Y$3<D101),0,E101*IF(G101=0,H101,MIN(H101,H101*(Y$3-D101+1)/MAX(1,G101)))*(1+F101)^(Y$3-D101)*$E93) | Z10: =IF(OR(E101=0,Z$3<D101),0,E101*IF(G101=0,H101,MIN(H101,H101*(Z$3-D101+1)/MAX(1,G101)))*(1+F101)^(Z$3-D101)*$E93) | AA10: =IF(OR(E101=0,AA$3<D101),0,E101*IF(G101=0,H101,MIN(H101,H101*(AA$3-D101+1)/MAX(1,G101)))*(1+F101)^(AA$3-D101)*$E93) | AB10: =IF(OR(E101=0,AB$3<D101),0,E101*IF(G101=0,H101,MIN(H101,H101*(AB$3-D101+1)/MAX(1,G101)))*(1+F101)^(AB$3-D101)*$E93) | AC10: =IF(OR(E101=0,AC$3<D101),0,E101*IF(G101=0,H101,MIN(H101,H101*(AC$3-D101+1)/MAX(1,G101)))*(1+F101)^(AC$3-D101)*$E93) | AD10: =IF(OR(E101=0,AD$3<D101),0,E101*IF(G101=0,H101,MIN(H101,H101*(AD$3-D101+1)/MAX(1,G101)))*(1+F101)^(AD$3-D101)*$E93) | AE10: =IF(OR(E101=0,AE$3<D101),0,E101*IF(G101=0,H101,MIN(H101,H101*(AE$3-D101+1)/MAX(1,G101)))*(1+F101)^(AE$3-D101)*$E93) | AF10: =IF(OR(E101=0,AF$3<D101),0,E101*IF(G101=0,H101,MIN(H101,H101*(AF$3-D101+1)/MAX(1,G101)))*(1+F101)^(AF$3-D101)*$E93) | AG10: =IF(OR(E101=0,AG$3<D101),0,E101*IF(G101=0,H101,MIN(H101,H101*(AG$3-D101+1)/MAX(1,G101)))*(1+F101)^(AG$3-D101)*$E93) | AH10: =IF(OR(E101=0,AH$3<D101),0,E101*IF(G101=0,H101,MIN(H101,H101*(AH$3-D101+1)/MAX(1,G101)))*(1+F101)^(AH$3-D101)*$E93) | AI10: =IF(OR(E101=0,AI$3<D101),0,E101*IF(G101=0,H101,MIN(H101,H101*(AI$3-D101+1)/MAX(1,G101)))*(1+F101)^(AI$3-D101)*$E93) | AJ10: =IF(OR(E101=0,AJ$3<D101),0,E101*IF(G101=0,H101,MIN(H101,H101*(AJ$3-D101+1)/MAX(1,G101)))*(1+F101)^(AJ$3-D101)*$E93) | AK10: =IF(OR(E101=0,AK$3<D101),0,E101*IF(G101=0,H101,MIN(H101,H101*(AK$3-D101+1)/MAX(1,G101)))*(1+F101)^(AK$3-D101)*$E93) | AL10: =IF(OR(E101=0,AL$3<D101),0,E101*IF(G101=0,H101,MIN(H101,H101*(AL$3-D101+1)/MAX(1,G101)))*(1+F101)^(AL$3-D101)*$E93) | AM10: =IF(OR(E101=0,AM$3<D101),0,E101*IF(G101=0,H101,MIN(H101,H101*(AM$3-D101+1)/MAX(1,G101)))*(1+F101)^(AM$3-D101)*$E93) | AN10: =IF(OR(E101=0,AN$3<D101),0,E101*IF(G101=0,H101,MIN(H101,H101*(AN$3-D101+1)/MAX(1,G101)))*(1+F101)^(AN$3-D101)*$E93) | AO10: =IF(OR(E101=0,AO$3<D101),0,E101*IF(G101=0,H101,MIN(H101,H101*(AO$3-D101+1)/MAX(1,G101)))*(1+F101)^(AO$3-D101)*$E93) | AP10: =IF(OR(E101=0,AP$3<D101),0,E101*IF(G101=0,H101,MIN(H101,H101*(AP$3-D101+1)/MAX(1,G101)))*(1+F101)^(AP$3-D101)*$E93) | AQ10: =IF(OR(E101=0,AQ$3<D101),0,E101*IF(G101=0,H101,MIN(H101,H101*(AQ$3-D101+1)/MAX(1,G101)))*(1+F101)^(AQ$3-D101)*$E93) | AR10: =IF(OR(E101=0,AR$3<D101),0,E101*IF(G101=0,H101,MIN(H101,H101*(AR$3-D101+1)/MAX(1,G101)))*(1+F101)^(AR$3-D101)*$E93) | AS10: =IF(OR(E101=0,AS$3<D101),0,E101*IF(G101=0,H101,MIN(H101,H101*(AS$3-D101+1)/MAX(1,G101)))*(1+F101)^(AS$3-D101)*$E93) | AT10: =IF(OR(E101=0,AT$3<D101),0,E101*IF(G101=0,H101,MIN(H101,H101*(AT$3-D101+1)/MAX(1,G101)))*(1+F101)^(AT$3-D101)*$E93) | AU10: =IF(OR(E101=0,AU$3<D101),0,E101*IF(G101=0,H101,MIN(H101,H101*(AU$3-D101+1)/MAX(1,G101)))*(1+F101)^(AU$3-D101)*$E93) | AV10: =IF(OR(E101=0,AV$3<D101),0,E101*IF(G101=0,H101,MIN(H101,H101*(AV$3-D101+1)/MAX(1,G101)))*(1+F101)^(AV$3-D101)*$E93) | AW10: =IF(OR(E101=0,AW$3<D101),0,E101*IF(G101=0,H101,MIN(H101,H101*(AW$3-D101+1)/MAX(1,G101)))*(1+F101)^(AW$3-D101)*$E93) | AX10: =IF(OR(E101=0,AX$3<D101),0,E101*IF(G101=0,H101,MIN(H101,H101*(AX$3-D101+1)/MAX(1,G101)))*(1+F101)^(AX$3-D101)*$E93) | AY10: =IF(OR(E101=0,AY$3<D101),0,E101*IF(G101=0,H101,MIN(H101,H101*(AY$3-D101+1)/MAX(1,G101)))*(1+F101)^(AY$3-D101)*$E93) | AZ10: =IF(OR(E101=0,AZ$3<D101),0,E101*IF(G101=0,H101,MIN(H101,H101*(AZ$3-D101+1)/MAX(1,G101)))*(1+F101)^(AZ$3-D101)*$E93) | BA10: =IF(OR(E101=0,BA$3<D101),0,E101*IF(G101=0,H101,MIN(H101,H101*(BA$3-D101+1)/MAX(1,G101)))*(1+F101)^(BA$3-D101)*$E93) | BB10: =IF(OR(E101=0,BB$3<D101),0,E101*IF(G101=0,H101,MIN(H101,H101*(BB$3-D101+1)/MAX(1,G101)))*(1+F101)^(BB$3-D101)*$E93)
A11: =A102 | B11: =B102 | C11: =C102 | D11: =SUM(E11:BB11) | E11: =IF(OR(E102=0,E$3<D102),0,E102*IF(G102=0,H102,MIN(H102,H102*(E$3-D102+1)/MAX(1,G102)))*(1+F102)^(E$3-D102)*$E93) | F11: =IF(OR(E102=0,F$3<D102),0,E102*IF(G102=0,H102,MIN(H102,H102*(F$3-D102+1)/MAX(1,G102)))*(1+F102)^(F$3-D102)*$E93) | G11: =IF(OR(E102=0,G$3<D102),0,E102*IF(G102=0,H102,MIN(H102,H102*(G$3-D102+1)/MAX(1,G102)))*(1+F102)^(G$3-D102)*$E93) | H11: =IF(OR(E102=0,H$3<D102),0,E102*IF(G102=0,H102,MIN(H102,H102*(H$3-D102+1)/MAX(1,G102)))*(1+F102)^(H$3-D102)*$E93) | I11: =IF(OR(E102=0,I$3<D102),0,E102*IF(G102=0,H102,MIN(H102,H102*(I$3-D102+1)/MAX(1,G102)))*(1+F102)^(I$3-D102)*$E93) | J11: =IF(OR(E102=0,J$3<D102),0,E102*IF(G102=0,H102,MIN(H102,H102*(J$3-D102+1)/MAX(1,G102)))*(1+F102)^(J$3-D102)*$E93) | K11: =IF(OR(E102=0,K$3<D102),0,E102*IF(G102=0,H102,MIN(H102,H102*(K$3-D102+1)/MAX(1,G102)))*(1+F102)^(K$3-D102)*$E93) | L11: =IF(OR(E102=0,L$3<D102),0,E102*IF(G102=0,H102,MIN(H102,H102*(L$3-D102+1)/MAX(1,G102)))*(1+F102)^(L$3-D102)*$E93) | M11: =IF(OR(E102=0,M$3<D102),0,E102*IF(G102=0,H102,MIN(H102,H102*(M$3-D102+1)/MAX(1,G102)))*(1+F102)^(M$3-D102)*$E93) | N11: =IF(OR(E102=0,N$3<D102),0,E102*IF(G102=0,H102,MIN(H102,H102*(N$3-D102+1)/MAX(1,G102)))*(1+F102)^(N$3-D102)*$E93) | O11: =IF(OR(E102=0,O$3<D102),0,E102*IF(G102=0,H102,MIN(H102,H102*(O$3-D102+1)/MAX(1,G102)))*(1+F102)^(O$3-D102)*$E93) | P11: =IF(OR(E102=0,P$3<D102),0,E102*IF(G102=0,H102,MIN(H102,H102*(P$3-D102+1)/MAX(1,G102)))*(1+F102)^(P$3-D102)*$E93) | Q11: =IF(OR(E102=0,Q$3<D102),0,E102*IF(G102=0,H102,MIN(H102,H102*(Q$3-D102+1)/MAX(1,G102)))*(1+F102)^(Q$3-D102)*$E93) | R11: =IF(OR(E102=0,R$3<D102),0,E102*IF(G102=0,H102,MIN(H102,H102*(R$3-D102+1)/MAX(1,G102)))*(1+F102)^(R$3-D102)*$E93) | S11: =IF(OR(E102=0,S$3<D102),0,E102*IF(G102=0,H102,MIN(H102,H102*(S$3-D102+1)/MAX(1,G102)))*(1+F102)^(S$3-D102)*$E93) | T11: =IF(OR(E102=0,T$3<D102),0,E102*IF(G102=0,H102,MIN(H102,H102*(T$3-D102+1)/MAX(1,G102)))*(1+F102)^(T$3-D102)*$E93) | U11: =IF(OR(E102=0,U$3<D102),0,E102*IF(G102=0,H102,MIN(H102,H102*(U$3-D102+1)/MAX(1,G102)))*(1+F102)^(U$3-D102)*$E93) | V11: =IF(OR(E102=0,V$3<D102),0,E102*IF(G102=0,H102,MIN(H102,H102*(V$3-D102+1)/MAX(1,G102)))*(1+F102)^(V$3-D102)*$E93) | W11: =IF(OR(E102=0,W$3<D102),0,E102*IF(G102=0,H102,MIN(H102,H102*(W$3-D102+1)/MAX(1,G102)))*(1+F102)^(W$3-D102)*$E93) | X11: =IF(OR(E102=0,X$3<D102),0,E102*IF(G102=0,H102,MIN(H102,H102*(X$3-D102+1)/MAX(1,G102)))*(1+F102)^(X$3-D102)*$E93) | Y11: =IF(OR(E102=0,Y$3<D102),0,E102*IF(G102=0,H102,MIN(H102,H102*(Y$3-D102+1)/MAX(1,G102)))*(1+F102)^(Y$3-D102)*$E93) | Z11: =IF(OR(E102=0,Z$3<D102),0,E102*IF(G102=0,H102,MIN(H102,H102*(Z$3-D102+1)/MAX(1,G102)))*(1+F102)^(Z$3-D102)*$E93) | AA11: =IF(OR(E102=0,AA$3<D102),0,E102*IF(G102=0,H102,MIN(H102,H102*(AA$3-D102+1)/MAX(1,G102)))*(1+F102)^(AA$3-D102)*$E93) | AB11: =IF(OR(E102=0,AB$3<D102),0,E102*IF(G102=0,H102,MIN(H102,H102*(AB$3-D102+1)/MAX(1,G102)))*(1+F102)^(AB$3-D102)*$E93) | AC11: =IF(OR(E102=0,AC$3<D102),0,E102*IF(G102=0,H102,MIN(H102,H102*(AC$3-D102+1)/MAX(1,G102)))*(1+F102)^(AC$3-D102)*$E93) | AD11: =IF(OR(E102=0,AD$3<D102),0,E102*IF(G102=0,H102,MIN(H102,H102*(AD$3-D102+1)/MAX(1,G102)))*(1+F102)^(AD$3-D102)*$E93) | AE11: =IF(OR(E102=0,AE$3<D102),0,E102*IF(G102=0,H102,MIN(H102,H102*(AE$3-D102+1)/MAX(1,G102)))*(1+F102)^(AE$3-D102)*$E93) | AF11: =IF(OR(E102=0,AF$3<D102),0,E102*IF(G102=0,H102,MIN(H102,H102*(AF$3-D102+1)/MAX(1,G102)))*(1+F102)^(AF$3-D102)*$E93) | AG11: =IF(OR(E102=0,AG$3<D102),0,E102*IF(G102=0,H102,MIN(H102,H102*(AG$3-D102+1)/MAX(1,G102)))*(1+F102)^(AG$3-D102)*$E93) | AH11: =IF(OR(E102=0,AH$3<D102),0,E102*IF(G102=0,H102,MIN(H102,H102*(AH$3-D102+1)/MAX(1,G102)))*(1+F102)^(AH$3-D102)*$E93) | AI11: =IF(OR(E102=0,AI$3<D102),0,E102*IF(G102=0,H102,MIN(H102,H102*(AI$3-D102+1)/MAX(1,G102)))*(1+F102)^(AI$3-D102)*$E93) | AJ11: =IF(OR(E102=0,AJ$3<D102),0,E102*IF(G102=0,H102,MIN(H102,H102*(AJ$3-D102+1)/MAX(1,G102)))*(1+F102)^(AJ$3-D102)*$E93) | AK11: =IF(OR(E102=0,AK$3<D102),0,E102*IF(G102=0,H102,MIN(H102,H102*(AK$3-D102+1)/MAX(1,G102)))*(1+F102)^(AK$3-D102)*$E93) | AL11: =IF(OR(E102=0,AL$3<D102),0,E102*IF(G102=0,H102,MIN(H102,H102*(AL$3-D102+1)/MAX(1,G102)))*(1+F102)^(AL$3-D102)*$E93) | AM11: =IF(OR(E102=0,AM$3<D102),0,E102*IF(G102=0,H102,MIN(H102,H102*(AM$3-D102+1)/MAX(1,G102)))*(1+F102)^(AM$3-D102)*$E93) | AN11: =IF(OR(E102=0,AN$3<D102),0,E102*IF(G102=0,H102,MIN(H102,H102*(AN$3-D102+1)/MAX(1,G102)))*(1+F102)^(AN$3-D102)*$E93) | AO11: =IF(OR(E102=0,AO$3<D102),0,E102*IF(G102=0,H102,MIN(H102,H102*(AO$3-D102+1)/MAX(1,G102)))*(1+F102)^(AO$3-D102)*$E93) | AP11: =IF(OR(E102=0,AP$3<D102),0,E102*IF(G102=0,H102,MIN(H102,H102*(AP$3-D102+1)/MAX(1,G102)))*(1+F102)^(AP$3-D102)*$E93) | AQ11: =IF(OR(E102=0,AQ$3<D102),0,E102*IF(G102=0,H102,MIN(H102,H102*(AQ$3-D102+1)/MAX(1,G102)))*(1+F102)^(AQ$3-D102)*$E93) | AR11: =IF(OR(E102=0,AR$3<D102),0,E102*IF(G102=0,H102,MIN(H102,H102*(AR$3-D102+1)/MAX(1,G102)))*(1+F102)^(AR$3-D102)*$E93) | AS11: =IF(OR(E102=0,AS$3<D102),0,E102*IF(G102=0,H102,MIN(H102,H102*(AS$3-D102+1)/MAX(1,G102)))*(1+F102)^(AS$3-D102)*$E93) | AT11: =IF(OR(E102=0,AT$3<D102),0,E102*IF(G102=0,H102,MIN(H102,H102*(AT$3-D102+1)/MAX(1,G102)))*(1+F102)^(AT$3-D102)*$E93) | AU11: =IF(OR(E102=0,AU$3<D102),0,E102*IF(G102=0,H102,MIN(H102,H102*(AU$3-D102+1)/MAX(1,G102)))*(1+F102)^(AU$3-D102)*$E93) | AV11: =IF(OR(E102=0,AV$3<D102),0,E102*IF(G102=0,H102,MIN(H102,H102*(AV$3-D102+1)/MAX(1,G102)))*(1+F102)^(AV$3-D102)*$E93) | AW11: =IF(OR(E102=0,AW$3<D102),0,E102*IF(G102=0,H102,MIN(H102,H102*(AW$3-D102+1)/MAX(1,G102)))*(1+F102)^(AW$3-D102)*$E93) | AX11: =IF(OR(E102=0,AX$3<D102),0,E102*IF(G102=0,H102,MIN(H102,H102*(AX$3-D102+1)/MAX(1,G102)))*(1+F102)^(AX$3-D102)*$E93) | AY11: =IF(OR(E102=0,AY$3<D102),0,E102*IF(G102=0,H102,MIN(H102,H102*(AY$3-D102+1)/MAX(1,G102)))*(1+F102)^(AY$3-D102)*$E93) | AZ11: =IF(OR(E102=0,AZ$3<D102),0,E102*IF(G102=0,H102,MIN(H102,H102*(AZ$3-D102+1)/MAX(1,G102)))*(1+F102)^(AZ$3-D102)*$E93) | BA11: =IF(OR(E102=0,BA$3<D102),0,E102*IF(G102=0,H102,MIN(H102,H102*(BA$3-D102+1)/MAX(1,G102)))*(1+F102)^(BA$3-D102)*$E93) | BB11: =IF(OR(E102=0,BB$3<D102),0,E102*IF(G102=0,H102,MIN(H102,H102*(BB$3-D102+1)/MAX(1,G102)))*(1+F102)^(BB$3-D102)*$E93)
A12: =A103 | B12: =B103 | C12: =C103 | D12: =SUM(E12:BB12) | E12: =IF(OR(E103=0,E$3<D103),0,E103*IF(G103=0,H103,MIN(H103,H103*(E$3-D103+1)/MAX(1,G103)))*(1+F103)^(E$3-D103)*$E93) | F12: =IF(OR(E103=0,F$3<D103),0,E103*IF(G103=0,H103,MIN(H103,H103*(F$3-D103+1)/MAX(1,G103)))*(1+F103)^(F$3-D103)*$E93) | G12: =IF(OR(E103=0,G$3<D103),0,E103*IF(G103=0,H103,MIN(H103,H103*(G$3-D103+1)/MAX(1,G103)))*(1+F103)^(G$3-D103)*$E93) | H12: =IF(OR(E103=0,H$3<D103),0,E103*IF(G103=0,H103,MIN(H103,H103*(H$3-D103+1)/MAX(1,G103)))*(1+F103)^(H$3-D103)*$E93) | I12: =IF(OR(E103=0,I$3<D103),0,E103*IF(G103=0,H103,MIN(H103,H103*(I$3-D103+1)/MAX(1,G103)))*(1+F103)^(I$3-D103)*$E93) | J12: =IF(OR(E103=0,J$3<D103),0,E103*IF(G103=0,H103,MIN(H103,H103*(J$3-D103+1)/MAX(1,G103)))*(1+F103)^(J$3-D103)*$E93) | K12: =IF(OR(E103=0,K$3<D103),0,E103*IF(G103=0,H103,MIN(H103,H103*(K$3-D103+1)/MAX(1,G103)))*(1+F103)^(K$3-D103)*$E93) | L12: =IF(OR(E103=0,L$3<D103),0,E103*IF(G103=0,H103,MIN(H103,H103*(L$3-D103+1)/MAX(1,G103)))*(1+F103)^(L$3-D103)*$E93) | M12: =IF(OR(E103=0,M$3<D103),0,E103*IF(G103=0,H103,MIN(H103,H103*(M$3-D103+1)/MAX(1,G103)))*(1+F103)^(M$3-D103)*$E93) | N12: =IF(OR(E103=0,N$3<D103),0,E103*IF(G103=0,H103,MIN(H103,H103*(N$3-D103+1)/MAX(1,G103)))*(1+F103)^(N$3-D103)*$E93) | O12: =IF(OR(E103=0,O$3<D103),0,E103*IF(G103=0,H103,MIN(H103,H103*(O$3-D103+1)/MAX(1,G103)))*(1+F103)^(O$3-D103)*$E93) | P12: =IF(OR(E103=0,P$3<D103),0,E103*IF(G103=0,H103,MIN(H103,H103*(P$3-D103+1)/MAX(1,G103)))*(1+F103)^(P$3-D103)*$E93) | Q12: =IF(OR(E103=0,Q$3<D103),0,E103*IF(G103=0,H103,MIN(H103,H103*(Q$3-D103+1)/MAX(1,G103)))*(1+F103)^(Q$3-D103)*$E93) | R12: =IF(OR(E103=0,R$3<D103),0,E103*IF(G103=0,H103,MIN(H103,H103*(R$3-D103+1)/MAX(1,G103)))*(1+F103)^(R$3-D103)*$E93) | S12: =IF(OR(E103=0,S$3<D103),0,E103*IF(G103=0,H103,MIN(H103,H103*(S$3-D103+1)/MAX(1,G103)))*(1+F103)^(S$3-D103)*$E93) | T12: =IF(OR(E103=0,T$3<D103),0,E103*IF(G103=0,H103,MIN(H103,H103*(T$3-D103+1)/MAX(1,G103)))*(1+F103)^(T$3-D103)*$E93) | U12: =IF(OR(E103=0,U$3<D103),0,E103*IF(G103=0,H103,MIN(H103,H103*(U$3-D103+1)/MAX(1,G103)))*(1+F103)^(U$3-D103)*$E93) | V12: =IF(OR(E103=0,V$3<D103),0,E103*IF(G103=0,H103,MIN(H103,H103*(V$3-D103+1)/MAX(1,G103)))*(1+F103)^(V$3-D103)*$E93) | W12: =IF(OR(E103=0,W$3<D103),0,E103*IF(G103=0,H103,MIN(H103,H103*(W$3-D103+1)/MAX(1,G103)))*(1+F103)^(W$3-D103)*$E93) | X12: =IF(OR(E103=0,X$3<D103),0,E103*IF(G103=0,H103,MIN(H103,H103*(X$3-D103+1)/MAX(1,G103)))*(1+F103)^(X$3-D103)*$E93) | Y12: =IF(OR(E103=0,Y$3<D103),0,E103*IF(G103=0,H103,MIN(H103,H103*(Y$3-D103+1)/MAX(1,G103)))*(1+F103)^(Y$3-D103)*$E93) | Z12: =IF(OR(E103=0,Z$3<D103),0,E103*IF(G103=0,H103,MIN(H103,H103*(Z$3-D103+1)/MAX(1,G103)))*(1+F103)^(Z$3-D103)*$E93) | AA12: =IF(OR(E103=0,AA$3<D103),0,E103*IF(G103=0,H103,MIN(H103,H103*(AA$3-D103+1)/MAX(1,G103)))*(1+F103)^(AA$3-D103)*$E93) | AB12: =IF(OR(E103=0,AB$3<D103),0,E103*IF(G103=0,H103,MIN(H103,H103*(AB$3-D103+1)/MAX(1,G103)))*(1+F103)^(AB$3-D103)*$E93) | AC12: =IF(OR(E103=0,AC$3<D103),0,E103*IF(G103=0,H103,MIN(H103,H103*(AC$3-D103+1)/MAX(1,G103)))*(1+F103)^(AC$3-D103)*$E93) | AD12: =IF(OR(E103=0,AD$3<D103),0,E103*IF(G103=0,H103,MIN(H103,H103*(AD$3-D103+1)/MAX(1,G103)))*(1+F103)^(AD$3-D103)*$E93) | AE12: =IF(OR(E103=0,AE$3<D103),0,E103*IF(G103=0,H103,MIN(H103,H103*(AE$3-D103+1)/MAX(1,G103)))*(1+F103)^(AE$3-D103)*$E93) | AF12: =IF(OR(E103=0,AF$3<D103),0,E103*IF(G103=0,H103,MIN(H103,H103*(AF$3-D103+1)/MAX(1,G103)))*(1+F103)^(AF$3-D103)*$E93) | AG12: =IF(OR(E103=0,AG$3<D103),0,E103*IF(G103=0,H103,MIN(H103,H103*(AG$3-D103+1)/MAX(1,G103)))*(1+F103)^(AG$3-D103)*$E93) | AH12: =IF(OR(E103=0,AH$3<D103),0,E103*IF(G103=0,H103,MIN(H103,H103*(AH$3-D103+1)/MAX(1,G103)))*(1+F103)^(AH$3-D103)*$E93) | AI12: =IF(OR(E103=0,AI$3<D103),0,E103*IF(G103=0,H103,MIN(H103,H103*(AI$3-D103+1)/MAX(1,G103)))*(1+F103)^(AI$3-D103)*$E93) | AJ12: =IF(OR(E103=0,AJ$3<D103),0,E103*IF(G103=0,H103,MIN(H103,H103*(AJ$3-D103+1)/MAX(1,G103)))*(1+F103)^(AJ$3-D103)*$E93) | AK12: =IF(OR(E103=0,AK$3<D103),0,E103*IF(G103=0,H103,MIN(H103,H103*(AK$3-D103+1)/MAX(1,G103)))*(1+F103)^(AK$3-D103)*$E93) | AL12: =IF(OR(E103=0,AL$3<D103),0,E103*IF(G103=0,H103,MIN(H103,H103*(AL$3-D103+1)/MAX(1,G103)))*(1+F103)^(AL$3-D103)*$E93) | AM12: =IF(OR(E103=0,AM$3<D103),0,E103*IF(G103=0,H103,MIN(H103,H103*(AM$3-D103+1)/MAX(1,G103)))*(1+F103)^(AM$3-D103)*$E93) | AN12: =IF(OR(E103=0,AN$3<D103),0,E103*IF(G103=0,H103,MIN(H103,H103*(AN$3-D103+1)/MAX(1,G103)))*(1+F103)^(AN$3-D103)*$E93) | AO12: =IF(OR(E103=0,AO$3<D103),0,E103*IF(G103=0,H103,MIN(H103,H103*(AO$3-D103+1)/MAX(1,G103)))*(1+F103)^(AO$3-D103)*$E93) | AP12: =IF(OR(E103=0,AP$3<D103),0,E103*IF(G103=0,H103,MIN(H103,H103*(AP$3-D103+1)/MAX(1,G103)))*(1+F103)^(AP$3-D103)*$E93) | AQ12: =IF(OR(E103=0,AQ$3<D103),0,E103*IF(G103=0,H103,MIN(H103,H103*(AQ$3-D103+1)/MAX(1,G103)))*(1+F103)^(AQ$3-D103)*$E93) | AR12: =IF(OR(E103=0,AR$3<D103),0,E103*IF(G103=0,H103,MIN(H103,H103*(AR$3-D103+1)/MAX(1,G103)))*(1+F103)^(AR$3-D103)*$E93) | AS12: =IF(OR(E103=0,AS$3<D103),0,E103*IF(G103=0,H103,MIN(H103,H103*(AS$3-D103+1)/MAX(1,G103)))*(1+F103)^(AS$3-D103)*$E93) | AT12: =IF(OR(E103=0,AT$3<D103),0,E103*IF(G103=0,H103,MIN(H103,H103*(AT$3-D103+1)/MAX(1,G103)))*(1+F103)^(AT$3-D103)*$E93) | AU12: =IF(OR(E103=0,AU$3<D103),0,E103*IF(G103=0,H103,MIN(H103,H103*(AU$3-D103+1)/MAX(1,G103)))*(1+F103)^(AU$3-D103)*$E93) | AV12: =IF(OR(E103=0,AV$3<D103),0,E103*IF(G103=0,H103,MIN(H103,H103*(AV$3-D103+1)/MAX(1,G103)))*(1+F103)^(AV$3-D103)*$E93) | AW12: =IF(OR(E103=0,AW$3<D103),0,E103*IF(G103=0,H103,MIN(H103,H103*(AW$3-D103+1)/MAX(1,G103)))*(1+F103)^(AW$3-D103)*$E93) | AX12: =IF(OR(E103=0,AX$3<D103),0,E103*IF(G103=0,H103,MIN(H103,H103*(AX$3-D103+1)/MAX(1,G103)))*(1+F103)^(AX$3-D103)*$E93) | AY12: =IF(OR(E103=0,AY$3<D103),0,E103*IF(G103=0,H103,MIN(H103,H103*(AY$3-D103+1)/MAX(1,G103)))*(1+F103)^(AY$3-D103)*$E93) | AZ12: =IF(OR(E103=0,AZ$3<D103),0,E103*IF(G103=0,H103,MIN(H103,H103*(AZ$3-D103+1)/MAX(1,G103)))*(1+F103)^(AZ$3-D103)*$E93) | BA12: =IF(OR(E103=0,BA$3<D103),0,E103*IF(G103=0,H103,MIN(H103,H103*(BA$3-D103+1)/MAX(1,G103)))*(1+F103)^(BA$3-D103)*$E93) | BB12: =IF(OR(E103=0,BB$3<D103),0,E103*IF(G103=0,H103,MIN(H103,H103*(BB$3-D103+1)/MAX(1,G103)))*(1+F103)^(BB$3-D103)*$E93)
A13: =A104 | B13: =B104 | C13: =C104 | D13: =SUM(E13:BB13) | E13: =IF(OR(E104=0,E$3<D104),0,E104*IF(G104=0,H104,MIN(H104,H104*(E$3-D104+1)/MAX(1,G104)))*(1+F104)^(E$3-D104)*$E93) | F13: =IF(OR(E104=0,F$3<D104),0,E104*IF(G104=0,H104,MIN(H104,H104*(F$3-D104+1)/MAX(1,G104)))*(1+F104)^(F$3-D104)*$E93) | G13: =IF(OR(E104=0,G$3<D104),0,E104*IF(G104=0,H104,MIN(H104,H104*(G$3-D104+1)/MAX(1,G104)))*(1+F104)^(G$3-D104)*$E93) | H13: =IF(OR(E104=0,H$3<D104),0,E104*IF(G104=0,H104,MIN(H104,H104*(H$3-D104+1)/MAX(1,G104)))*(1+F104)^(H$3-D104)*$E93) | I13: =IF(OR(E104=0,I$3<D104),0,E104*IF(G104=0,H104,MIN(H104,H104*(I$3-D104+1)/MAX(1,G104)))*(1+F104)^(I$3-D104)*$E93) | J13: =IF(OR(E104=0,J$3<D104),0,E104*IF(G104=0,H104,MIN(H104,H104*(J$3-D104+1)/MAX(1,G104)))*(1+F104)^(J$3-D104)*$E93) | K13: =IF(OR(E104=0,K$3<D104),0,E104*IF(G104=0,H104,MIN(H104,H104*(K$3-D104+1)/MAX(1,G104)))*(1+F104)^(K$3-D104)*$E93) | L13: =IF(OR(E104=0,L$3<D104),0,E104*IF(G104=0,H104,MIN(H104,H104*(L$3-D104+1)/MAX(1,G104)))*(1+F104)^(L$3-D104)*$E93) | M13: =IF(OR(E104=0,M$3<D104),0,E104*IF(G104=0,H104,MIN(H104,H104*(M$3-D104+1)/MAX(1,G104)))*(1+F104)^(M$3-D104)*$E93) | N13: =IF(OR(E104=0,N$3<D104),0,E104*IF(G104=0,H104,MIN(H104,H104*(N$3-D104+1)/MAX(1,G104)))*(1+F104)^(N$3-D104)*$E93) | O13: =IF(OR(E104=0,O$3<D104),0,E104*IF(G104=0,H104,MIN(H104,H104*(O$3-D104+1)/MAX(1,G104)))*(1+F104)^(O$3-D104)*$E93) | P13: =IF(OR(E104=0,P$3<D104),0,E104*IF(G104=0,H104,MIN(H104,H104*(P$3-D104+1)/MAX(1,G104)))*(1+F104)^(P$3-D104)*$E93) | Q13: =IF(OR(E104=0,Q$3<D104),0,E104*IF(G104=0,H104,MIN(H104,H104*(Q$3-D104+1)/MAX(1,G104)))*(1+F104)^(Q$3-D104)*$E93) | R13: =IF(OR(E104=0,R$3<D104),0,E104*IF(G104=0,H104,MIN(H104,H104*(R$3-D104+1)/MAX(1,G104)))*(1+F104)^(R$3-D104)*$E93) | S13: =IF(OR(E104=0,S$3<D104),0,E104*IF(G104=0,H104,MIN(H104,H104*(S$3-D104+1)/MAX(1,G104)))*(1+F104)^(S$3-D104)*$E93) | T13: =IF(OR(E104=0,T$3<D104),0,E104*IF(G104=0,H104,MIN(H104,H104*(T$3-D104+1)/MAX(1,G104)))*(1+F104)^(T$3-D104)*$E93) | U13: =IF(OR(E104=0,U$3<D104),0,E104*IF(G104=0,H104,MIN(H104,H104*(U$3-D104+1)/MAX(1,G104)))*(1+F104)^(U$3-D104)*$E93) | V13: =IF(OR(E104=0,V$3<D104),0,E104*IF(G104=0,H104,MIN(H104,H104*(V$3-D104+1)/MAX(1,G104)))*(1+F104)^(V$3-D104)*$E93) | W13: =IF(OR(E104=0,W$3<D104),0,E104*IF(G104=0,H104,MIN(H104,H104*(W$3-D104+1)/MAX(1,G104)))*(1+F104)^(W$3-D104)*$E93) | X13: =IF(OR(E104=0,X$3<D104),0,E104*IF(G104=0,H104,MIN(H104,H104*(X$3-D104+1)/MAX(1,G104)))*(1+F104)^(X$3-D104)*$E93) | Y13: =IF(OR(E104=0,Y$3<D104),0,E104*IF(G104=0,H104,MIN(H104,H104*(Y$3-D104+1)/MAX(1,G104)))*(1+F104)^(Y$3-D104)*$E93) | Z13: =IF(OR(E104=0,Z$3<D104),0,E104*IF(G104=0,H104,MIN(H104,H104*(Z$3-D104+1)/MAX(1,G104)))*(1+F104)^(Z$3-D104)*$E93) | AA13: =IF(OR(E104=0,AA$3<D104),0,E104*IF(G104=0,H104,MIN(H104,H104*(AA$3-D104+1)/MAX(1,G104)))*(1+F104)^(AA$3-D104)*$E93) | AB13: =IF(OR(E104=0,AB$3<D104),0,E104*IF(G104=0,H104,MIN(H104,H104*(AB$3-D104+1)/MAX(1,G104)))*(1+F104)^(AB$3-D104)*$E93) | AC13: =IF(OR(E104=0,AC$3<D104),0,E104*IF(G104=0,H104,MIN(H104,H104*(AC$3-D104+1)/MAX(1,G104)))*(1+F104)^(AC$3-D104)*$E93) | AD13: =IF(OR(E104=0,AD$3<D104),0,E104*IF(G104=0,H104,MIN(H104,H104*(AD$3-D104+1)/MAX(1,G104)))*(1+F104)^(AD$3-D104)*$E93) | AE13: =IF(OR(E104=0,AE$3<D104),0,E104*IF(G104=0,H104,MIN(H104,H104*(AE$3-D104+1)/MAX(1,G104)))*(1+F104)^(AE$3-D104)*$E93) | AF13: =IF(OR(E104=0,AF$3<D104),0,E104*IF(G104=0,H104,MIN(H104,H104*(AF$3-D104+1)/MAX(1,G104)))*(1+F104)^(AF$3-D104)*$E93) | AG13: =IF(OR(E104=0,AG$3<D104),0,E104*IF(G104=0,H104,MIN(H104,H104*(AG$3-D104+1)/MAX(1,G104)))*(1+F104)^(AG$3-D104)*$E93) | AH13: =IF(OR(E104=0,AH$3<D104),0,E104*IF(G104=0,H104,MIN(H104,H104*(AH$3-D104+1)/MAX(1,G104)))*(1+F104)^(AH$3-D104)*$E93) | AI13: =IF(OR(E104=0,AI$3<D104),0,E104*IF(G104=0,H104,MIN(H104,H104*(AI$3-D104+1)/MAX(1,G104)))*(1+F104)^(AI$3-D104)*$E93) | AJ13: =IF(OR(E104=0,AJ$3<D104),0,E104*IF(G104=0,H104,MIN(H104,H104*(AJ$3-D104+1)/MAX(1,G104)))*(1+F104)^(AJ$3-D104)*$E93) | AK13: =IF(OR(E104=0,AK$3<D104),0,E104*IF(G104=0,H104,MIN(H104,H104*(AK$3-D104+1)/MAX(1,G104)))*(1+F104)^(AK$3-D104)*$E93) | AL13: =IF(OR(E104=0,AL$3<D104),0,E104*IF(G104=0,H104,MIN(H104,H104*(AL$3-D104+1)/MAX(1,G104)))*(1+F104)^(AL$3-D104)*$E93) | AM13: =IF(OR(E104=0,AM$3<D104),0,E104*IF(G104=0,H104,MIN(H104,H104*(AM$3-D104+1)/MAX(1,G104)))*(1+F104)^(AM$3-D104)*$E93) | AN13: =IF(OR(E104=0,AN$3<D104),0,E104*IF(G104=0,H104,MIN(H104,H104*(AN$3-D104+1)/MAX(1,G104)))*(1+F104)^(AN$3-D104)*$E93) | AO13: =IF(OR(E104=0,AO$3<D104),0,E104*IF(G104=0,H104,MIN(H104,H104*(AO$3-D104+1)/MAX(1,G104)))*(1+F104)^(AO$3-D104)*$E93) | AP13: =IF(OR(E104=0,AP$3<D104),0,E104*IF(G104=0,H104,MIN(H104,H104*(AP$3-D104+1)/MAX(1,G104)))*(1+F104)^(AP$3-D104)*$E93) | AQ13: =IF(OR(E104=0,AQ$3<D104),0,E104*IF(G104=0,H104,MIN(H104,H104*(AQ$3-D104+1)/MAX(1,G104)))*(1+F104)^(AQ$3-D104)*$E93) | AR13: =IF(OR(E104=0,AR$3<D104),0,E104*IF(G104=0,H104,MIN(H104,H104*(AR$3-D104+1)/MAX(1,G104)))*(1+F104)^(AR$3-D104)*$E93) | AS13: =IF(OR(E104=0,AS$3<D104),0,E104*IF(G104=0,H104,MIN(H104,H104*(AS$3-D104+1)/MAX(1,G104)))*(1+F104)^(AS$3-D104)*$E93) | AT13: =IF(OR(E104=0,AT$3<D104),0,E104*IF(G104=0,H104,MIN(H104,H104*(AT$3-D104+1)/MAX(1,G104)))*(1+F104)^(AT$3-D104)*$E93) | AU13: =IF(OR(E104=0,AU$3<D104),0,E104*IF(G104=0,H104,MIN(H104,H104*(AU$3-D104+1)/MAX(1,G104)))*(1+F104)^(AU$3-D104)*$E93) | AV13: =IF(OR(E104=0,AV$3<D104),0,E104*IF(G104=0,H104,MIN(H104,H104*(AV$3-D104+1)/MAX(1,G104)))*(1+F104)^(AV$3-D104)*$E93) | AW13: =IF(OR(E104=0,AW$3<D104),0,E104*IF(G104=0,H104,MIN(H104,H104*(AW$3-D104+1)/MAX(1,G104)))*(1+F104)^(AW$3-D104)*$E93) | AX13: =IF(OR(E104=0,AX$3<D104),0,E104*IF(G104=0,H104,MIN(H104,H104*(AX$3-D104+1)/MAX(1,G104)))*(1+F104)^(AX$3-D104)*$E93) | AY13: =IF(OR(E104=0,AY$3<D104),0,E104*IF(G104=0,H104,MIN(H104,H104*(AY$3-D104+1)/MAX(1,G104)))*(1+F104)^(AY$3-D104)*$E93) | AZ13: =IF(OR(E104=0,AZ$3<D104),0,E104*IF(G104=0,H104,MIN(H104,H104*(AZ$3-D104+1)/MAX(1,G104)))*(1+F104)^(AZ$3-D104)*$E93) | BA13: =IF(OR(E104=0,BA$3<D104),0,E104*IF(G104=0,H104,MIN(H104,H104*(BA$3-D104+1)/MAX(1,G104)))*(1+F104)^(BA$3-D104)*$E93) | BB13: =IF(OR(E104=0,BB$3<D104),0,E104*IF(G104=0,H104,MIN(H104,H104*(BB$3-D104+1)/MAX(1,G104)))*(1+F104)^(BB$3-D104)*$E93)
A14: =A105 | B14: =B105 | C14: =C105 | D14: =SUM(E14:BB14) | E14: =IF(OR(E105=0,E$3<D105),0,E105*IF(G105=0,H105,MIN(H105,H105*(E$3-D105+1)/MAX(1,G105)))*(1+F105)^(E$3-D105)*$E93) | F14: =IF(OR(E105=0,F$3<D105),0,E105*IF(G105=0,H105,MIN(H105,H105*(F$3-D105+1)/MAX(1,G105)))*(1+F105)^(F$3-D105)*$E93) | G14: =IF(OR(E105=0,G$3<D105),0,E105*IF(G105=0,H105,MIN(H105,H105*(G$3-D105+1)/MAX(1,G105)))*(1+F105)^(G$3-D105)*$E93) | H14: =IF(OR(E105=0,H$3<D105),0,E105*IF(G105=0,H105,MIN(H105,H105*(H$3-D105+1)/MAX(1,G105)))*(1+F105)^(H$3-D105)*$E93) | I14: =IF(OR(E105=0,I$3<D105),0,E105*IF(G105=0,H105,MIN(H105,H105*(I$3-D105+1)/MAX(1,G105)))*(1+F105)^(I$3-D105)*$E93) | J14: =IF(OR(E105=0,J$3<D105),0,E105*IF(G105=0,H105,MIN(H105,H105*(J$3-D105+1)/MAX(1,G105)))*(1+F105)^(J$3-D105)*$E93) | K14: =IF(OR(E105=0,K$3<D105),0,E105*IF(G105=0,H105,MIN(H105,H105*(K$3-D105+1)/MAX(1,G105)))*(1+F105)^(K$3-D105)*$E93) | L14: =IF(OR(E105=0,L$3<D105),0,E105*IF(G105=0,H105,MIN(H105,H105*(L$3-D105+1)/MAX(1,G105)))*(1+F105)^(L$3-D105)*$E93) | M14: =IF(OR(E105=0,M$3<D105),0,E105*IF(G105=0,H105,MIN(H105,H105*(M$3-D105+1)/MAX(1,G105)))*(1+F105)^(M$3-D105)*$E93) | N14: =IF(OR(E105=0,N$3<D105),0,E105*IF(G105=0,H105,MIN(H105,H105*(N$3-D105+1)/MAX(1,G105)))*(1+F105)^(N$3-D105)*$E93) | O14: =IF(OR(E105=0,O$3<D105),0,E105*IF(G105=0,H105,MIN(H105,H105*(O$3-D105+1)/MAX(1,G105)))*(1+F105)^(O$3-D105)*$E93) | P14: =IF(OR(E105=0,P$3<D105),0,E105*IF(G105=0,H105,MIN(H105,H105*(P$3-D105+1)/MAX(1,G105)))*(1+F105)^(P$3-D105)*$E93) | Q14: =IF(OR(E105=0,Q$3<D105),0,E105*IF(G105=0,H105,MIN(H105,H105*(Q$3-D105+1)/MAX(1,G105)))*(1+F105)^(Q$3-D105)*$E93) | R14: =IF(OR(E105=0,R$3<D105),0,E105*IF(G105=0,H105,MIN(H105,H105*(R$3-D105+1)/MAX(1,G105)))*(1+F105)^(R$3-D105)*$E93) | S14: =IF(OR(E105=0,S$3<D105),0,E105*IF(G105=0,H105,MIN(H105,H105*(S$3-D105+1)/MAX(1,G105)))*(1+F105)^(S$3-D105)*$E93) | T14: =IF(OR(E105=0,T$3<D105),0,E105*IF(G105=0,H105,MIN(H105,H105*(T$3-D105+1)/MAX(1,G105)))*(1+F105)^(T$3-D105)*$E93) | U14: =IF(OR(E105=0,U$3<D105),0,E105*IF(G105=0,H105,MIN(H105,H105*(U$3-D105+1)/MAX(1,G105)))*(1+F105)^(U$3-D105)*$E93) | V14: =IF(OR(E105=0,V$3<D105),0,E105*IF(G105=0,H105,MIN(H105,H105*(V$3-D105+1)/MAX(1,G105)))*(1+F105)^(V$3-D105)*$E93) | W14: =IF(OR(E105=0,W$3<D105),0,E105*IF(G105=0,H105,MIN(H105,H105*(W$3-D105+1)/MAX(1,G105)))*(1+F105)^(W$3-D105)*$E93) | X14: =IF(OR(E105=0,X$3<D105),0,E105*IF(G105=0,H105,MIN(H105,H105*(X$3-D105+1)/MAX(1,G105)))*(1+F105)^(X$3-D105)*$E93) | Y14: =IF(OR(E105=0,Y$3<D105),0,E105*IF(G105=0,H105,MIN(H105,H105*(Y$3-D105+1)/MAX(1,G105)))*(1+F105)^(Y$3-D105)*$E93) | Z14: =IF(OR(E105=0,Z$3<D105),0,E105*IF(G105=0,H105,MIN(H105,H105*(Z$3-D105+1)/MAX(1,G105)))*(1+F105)^(Z$3-D105)*$E93) | AA14: =IF(OR(E105=0,AA$3<D105),0,E105*IF(G105=0,H105,MIN(H105,H105*(AA$3-D105+1)/MAX(1,G105)))*(1+F105)^(AA$3-D105)*$E93) | AB14: =IF(OR(E105=0,AB$3<D105),0,E105*IF(G105=0,H105,MIN(H105,H105*(AB$3-D105+1)/MAX(1,G105)))*(1+F105)^(AB$3-D105)*$E93) | AC14: =IF(OR(E105=0,AC$3<D105),0,E105*IF(G105=0,H105,MIN(H105,H105*(AC$3-D105+1)/MAX(1,G105)))*(1+F105)^(AC$3-D105)*$E93) | AD14: =IF(OR(E105=0,AD$3<D105),0,E105*IF(G105=0,H105,MIN(H105,H105*(AD$3-D105+1)/MAX(1,G105)))*(1+F105)^(AD$3-D105)*$E93) | AE14: =IF(OR(E105=0,AE$3<D105),0,E105*IF(G105=0,H105,MIN(H105,H105*(AE$3-D105+1)/MAX(1,G105)))*(1+F105)^(AE$3-D105)*$E93) | AF14: =IF(OR(E105=0,AF$3<D105),0,E105*IF(G105=0,H105,MIN(H105,H105*(AF$3-D105+1)/MAX(1,G105)))*(1+F105)^(AF$3-D105)*$E93) | AG14: =IF(OR(E105=0,AG$3<D105),0,E105*IF(G105=0,H105,MIN(H105,H105*(AG$3-D105+1)/MAX(1,G105)))*(1+F105)^(AG$3-D105)*$E93) | AH14: =IF(OR(E105=0,AH$3<D105),0,E105*IF(G105=0,H105,MIN(H105,H105*(AH$3-D105+1)/MAX(1,G105)))*(1+F105)^(AH$3-D105)*$E93) | AI14: =IF(OR(E105=0,AI$3<D105),0,E105*IF(G105=0,H105,MIN(H105,H105*(AI$3-D105+1)/MAX(1,G105)))*(1+F105)^(AI$3-D105)*$E93) | AJ14: =IF(OR(E105=0,AJ$3<D105),0,E105*IF(G105=0,H105,MIN(H105,H105*(AJ$3-D105+1)/MAX(1,G105)))*(1+F105)^(AJ$3-D105)*$E93) | AK14: =IF(OR(E105=0,AK$3<D105),0,E105*IF(G105=0,H105,MIN(H105,H105*(AK$3-D105+1)/MAX(1,G105)))*(1+F105)^(AK$3-D105)*$E93) | AL14: =IF(OR(E105=0,AL$3<D105),0,E105*IF(G105=0,H105,MIN(H105,H105*(AL$3-D105+1)/MAX(1,G105)))*(1+F105)^(AL$3-D105)*$E93) | AM14: =IF(OR(E105=0,AM$3<D105),0,E105*IF(G105=0,H105,MIN(H105,H105*(AM$3-D105+1)/MAX(1,G105)))*(1+F105)^(AM$3-D105)*$E93) | AN14: =IF(OR(E105=0,AN$3<D105),0,E105*IF(G105=0,H105,MIN(H105,H105*(AN$3-D105+1)/MAX(1,G105)))*(1+F105)^(AN$3-D105)*$E93) | AO14: =IF(OR(E105=0,AO$3<D105),0,E105*IF(G105=0,H105,MIN(H105,H105*(AO$3-D105+1)/MAX(1,G105)))*(1+F105)^(AO$3-D105)*$E93) | AP14: =IF(OR(E105=0,AP$3<D105),0,E105*IF(G105=0,H105,MIN(H105,H105*(AP$3-D105+1)/MAX(1,G105)))*(1+F105)^(AP$3-D105)*$E93) | AQ14: =IF(OR(E105=0,AQ$3<D105),0,E105*IF(G105=0,H105,MIN(H105,H105*(AQ$3-D105+1)/MAX(1,G105)))*(1+F105)^(AQ$3-D105)*$E93) | AR14: =IF(OR(E105=0,AR$3<D105),0,E105*IF(G105=0,H105,MIN(H105,H105*(AR$3-D105+1)/MAX(1,G105)))*(1+F105)^(AR$3-D105)*$E93) | AS14: =IF(OR(E105=0,AS$3<D105),0,E105*IF(G105=0,H105,MIN(H105,H105*(AS$3-D105+1)/MAX(1,G105)))*(1+F105)^(AS$3-D105)*$E93) | AT14: =IF(OR(E105=0,AT$3<D105),0,E105*IF(G105=0,H105,MIN(H105,H105*(AT$3-D105+1)/MAX(1,G105)))*(1+F105)^(AT$3-D105)*$E93) | AU14: =IF(OR(E105=0,AU$3<D105),0,E105*IF(G105=0,H105,MIN(H105,H105*(AU$3-D105+1)/MAX(1,G105)))*(1+F105)^(AU$3-D105)*$E93) | AV14: =IF(OR(E105=0,AV$3<D105),0,E105*IF(G105=0,H105,MIN(H105,H105*(AV$3-D105+1)/MAX(1,G105)))*(1+F105)^(AV$3-D105)*$E93) | AW14: =IF(OR(E105=0,AW$3<D105),0,E105*IF(G105=0,H105,MIN(H105,H105*(AW$3-D105+1)/MAX(1,G105)))*(1+F105)^(AW$3-D105)*$E93) | AX14: =IF(OR(E105=0,AX$3<D105),0,E105*IF(G105=0,H105,MIN(H105,H105*(AX$3-D105+1)/MAX(1,G105)))*(1+F105)^(AX$3-D105)*$E93) | AY14: =IF(OR(E105=0,AY$3<D105),0,E105*IF(G105=0,H105,MIN(H105,H105*(AY$3-D105+1)/MAX(1,G105)))*(1+F105)^(AY$3-D105)*$E93) | AZ14: =IF(OR(E105=0,AZ$3<D105),0,E105*IF(G105=0,H105,MIN(H105,H105*(AZ$3-D105+1)/MAX(1,G105)))*(1+F105)^(AZ$3-D105)*$E93) | BA14: =IF(OR(E105=0,BA$3<D105),0,E105*IF(G105=0,H105,MIN(H105,H105*(BA$3-D105+1)/MAX(1,G105)))*(1+F105)^(BA$3-D105)*$E93) | BB14: =IF(OR(E105=0,BB$3<D105),0,E105*IF(G105=0,H105,MIN(H105,H105*(BB$3-D105+1)/MAX(1,G105)))*(1+F105)^(BB$3-D105)*$E93)
A15: =A106 | B15: =B106 | C15: =C106 | D15: =SUM(E15:BB15) | E15: =IF(OR(E106=0,E$3<D106),0,E106*IF(G106=0,H106,MIN(H106,H106*(E$3-D106+1)/MAX(1,G106)))*(1+F106)^(E$3-D106)*$E93) | F15: =IF(OR(E106=0,F$3<D106),0,E106*IF(G106=0,H106,MIN(H106,H106*(F$3-D106+1)/MAX(1,G106)))*(1+F106)^(F$3-D106)*$E93) | G15: =IF(OR(E106=0,G$3<D106),0,E106*IF(G106=0,H106,MIN(H106,H106*(G$3-D106+1)/MAX(1,G106)))*(1+F106)^(G$3-D106)*$E93) | H15: =IF(OR(E106=0,H$3<D106),0,E106*IF(G106=0,H106,MIN(H106,H106*(H$3-D106+1)/MAX(1,G106)))*(1+F106)^(H$3-D106)*$E93) | I15: =IF(OR(E106=0,I$3<D106),0,E106*IF(G106=0,H106,MIN(H106,H106*(I$3-D106+1)/MAX(1,G106)))*(1+F106)^(I$3-D106)*$E93) | J15: =IF(OR(E106=0,J$3<D106),0,E106*IF(G106=0,H106,MIN(H106,H106*(J$3-D106+1)/MAX(1,G106)))*(1+F106)^(J$3-D106)*$E93) | K15: =IF(OR(E106=0,K$3<D106),0,E106*IF(G106=0,H106,MIN(H106,H106*(K$3-D106+1)/MAX(1,G106)))*(1+F106)^(K$3-D106)*$E93) | L15: =IF(OR(E106=0,L$3<D106),0,E106*IF(G106=0,H106,MIN(H106,H106*(L$3-D106+1)/MAX(1,G106)))*(1+F106)^(L$3-D106)*$E93) | M15: =IF(OR(E106=0,M$3<D106),0,E106*IF(G106=0,H106,MIN(H106,H106*(M$3-D106+1)/MAX(1,G106)))*(1+F106)^(M$3-D106)*$E93) | N15: =IF(OR(E106=0,N$3<D106),0,E106*IF(G106=0,H106,MIN(H106,H106*(N$3-D106+1)/MAX(1,G106)))*(1+F106)^(N$3-D106)*$E93) | O15: =IF(OR(E106=0,O$3<D106),0,E106*IF(G106=0,H106,MIN(H106,H106*(O$3-D106+1)/MAX(1,G106)))*(1+F106)^(O$3-D106)*$E93) | P15: =IF(OR(E106=0,P$3<D106),0,E106*IF(G106=0,H106,MIN(H106,H106*(P$3-D106+1)/MAX(1,G106)))*(1+F106)^(P$3-D106)*$E93) | Q15: =IF(OR(E106=0,Q$3<D106),0,E106*IF(G106=0,H106,MIN(H106,H106*(Q$3-D106+1)/MAX(1,G106)))*(1+F106)^(Q$3-D106)*$E93) | R15: =IF(OR(E106=0,R$3<D106),0,E106*IF(G106=0,H106,MIN(H106,H106*(R$3-D106+1)/MAX(1,G106)))*(1+F106)^(R$3-D106)*$E93) | S15: =IF(OR(E106=0,S$3<D106),0,E106*IF(G106=0,H106,MIN(H106,H106*(S$3-D106+1)/MAX(1,G106)))*(1+F106)^(S$3-D106)*$E93) | T15: =IF(OR(E106=0,T$3<D106),0,E106*IF(G106=0,H106,MIN(H106,H106*(T$3-D106+1)/MAX(1,G106)))*(1+F106)^(T$3-D106)*$E93) | U15: =IF(OR(E106=0,U$3<D106),0,E106*IF(G106=0,H106,MIN(H106,H106*(U$3-D106+1)/MAX(1,G106)))*(1+F106)^(U$3-D106)*$E93) | V15: =IF(OR(E106=0,V$3<D106),0,E106*IF(G106=0,H106,MIN(H106,H106*(V$3-D106+1)/MAX(1,G106)))*(1+F106)^(V$3-D106)*$E93) | W15: =IF(OR(E106=0,W$3<D106),0,E106*IF(G106=0,H106,MIN(H106,H106*(W$3-D106+1)/MAX(1,G106)))*(1+F106)^(W$3-D106)*$E93) | X15: =IF(OR(E106=0,X$3<D106),0,E106*IF(G106=0,H106,MIN(H106,H106*(X$3-D106+1)/MAX(1,G106)))*(1+F106)^(X$3-D106)*$E93) | Y15: =IF(OR(E106=0,Y$3<D106),0,E106*IF(G106=0,H106,MIN(H106,H106*(Y$3-D106+1)/MAX(1,G106)))*(1+F106)^(Y$3-D106)*$E93) | Z15: =IF(OR(E106=0,Z$3<D106),0,E106*IF(G106=0,H106,MIN(H106,H106*(Z$3-D106+1)/MAX(1,G106)))*(1+F106)^(Z$3-D106)*$E93) | AA15: =IF(OR(E106=0,AA$3<D106),0,E106*IF(G106=0,H106,MIN(H106,H106*(AA$3-D106+1)/MAX(1,G106)))*(1+F106)^(AA$3-D106)*$E93) | AB15: =IF(OR(E106=0,AB$3<D106),0,E106*IF(G106=0,H106,MIN(H106,H106*(AB$3-D106+1)/MAX(1,G106)))*(1+F106)^(AB$3-D106)*$E93) | AC15: =IF(OR(E106=0,AC$3<D106),0,E106*IF(G106=0,H106,MIN(H106,H106*(AC$3-D106+1)/MAX(1,G106)))*(1+F106)^(AC$3-D106)*$E93) | AD15: =IF(OR(E106=0,AD$3<D106),0,E106*IF(G106=0,H106,MIN(H106,H106*(AD$3-D106+1)/MAX(1,G106)))*(1+F106)^(AD$3-D106)*$E93) | AE15: =IF(OR(E106=0,AE$3<D106),0,E106*IF(G106=0,H106,MIN(H106,H106*(AE$3-D106+1)/MAX(1,G106)))*(1+F106)^(AE$3-D106)*$E93) | AF15: =IF(OR(E106=0,AF$3<D106),0,E106*IF(G106=0,H106,MIN(H106,H106*(AF$3-D106+1)/MAX(1,G106)))*(1+F106)^(AF$3-D106)*$E93) | AG15: =IF(OR(E106=0,AG$3<D106),0,E106*IF(G106=0,H106,MIN(H106,H106*(AG$3-D106+1)/MAX(1,G106)))*(1+F106)^(AG$3-D106)*$E93) | AH15: =IF(OR(E106=0,AH$3<D106),0,E106*IF(G106=0,H106,MIN(H106,H106*(AH$3-D106+1)/MAX(1,G106)))*(1+F106)^(AH$3-D106)*$E93) | AI15: =IF(OR(E106=0,AI$3<D106),0,E106*IF(G106=0,H106,MIN(H106,H106*(AI$3-D106+1)/MAX(1,G106)))*(1+F106)^(AI$3-D106)*$E93) | AJ15: =IF(OR(E106=0,AJ$3<D106),0,E106*IF(G106=0,H106,MIN(H106,H106*(AJ$3-D106+1)/MAX(1,G106)))*(1+F106)^(AJ$3-D106)*$E93) | AK15: =IF(OR(E106=0,AK$3<D106),0,E106*IF(G106=0,H106,MIN(H106,H106*(AK$3-D106+1)/MAX(1,G106)))*(1+F106)^(AK$3-D106)*$E93) | AL15: =IF(OR(E106=0,AL$3<D106),0,E106*IF(G106=0,H106,MIN(H106,H106*(AL$3-D106+1)/MAX(1,G106)))*(1+F106)^(AL$3-D106)*$E93) | AM15: =IF(OR(E106=0,AM$3<D106),0,E106*IF(G106=0,H106,MIN(H106,H106*(AM$3-D106+1)/MAX(1,G106)))*(1+F106)^(AM$3-D106)*$E93) | AN15: =IF(OR(E106=0,AN$3<D106),0,E106*IF(G106=0,H106,MIN(H106,H106*(AN$3-D106+1)/MAX(1,G106)))*(1+F106)^(AN$3-D106)*$E93) | AO15: =IF(OR(E106=0,AO$3<D106),0,E106*IF(G106=0,H106,MIN(H106,H106*(AO$3-D106+1)/MAX(1,G106)))*(1+F106)^(AO$3-D106)*$E93) | AP15: =IF(OR(E106=0,AP$3<D106),0,E106*IF(G106=0,H106,MIN(H106,H106*(AP$3-D106+1)/MAX(1,G106)))*(1+F106)^(AP$3-D106)*$E93) | AQ15: =IF(OR(E106=0,AQ$3<D106),0,E106*IF(G106=0,H106,MIN(H106,H106*(AQ$3-D106+1)/MAX(1,G106)))*(1+F106)^(AQ$3-D106)*$E93) | AR15: =IF(OR(E106=0,AR$3<D106),0,E106*IF(G106=0,H106,MIN(H106,H106*(AR$3-D106+1)/MAX(1,G106)))*(1+F106)^(AR$3-D106)*$E93) | AS15: =IF(OR(E106=0,AS$3<D106),0,E106*IF(G106=0,H106,MIN(H106,H106*(AS$3-D106+1)/MAX(1,G106)))*(1+F106)^(AS$3-D106)*$E93) | AT15: =IF(OR(E106=0,AT$3<D106),0,E106*IF(G106=0,H106,MIN(H106,H106*(AT$3-D106+1)/MAX(1,G106)))*(1+F106)^(AT$3-D106)*$E93) | AU15: =IF(OR(E106=0,AU$3<D106),0,E106*IF(G106=0,H106,MIN(H106,H106*(AU$3-D106+1)/MAX(1,G106)))*(1+F106)^(AU$3-D106)*$E93) | AV15: =IF(OR(E106=0,AV$3<D106),0,E106*IF(G106=0,H106,MIN(H106,H106*(AV$3-D106+1)/MAX(1,G106)))*(1+F106)^(AV$3-D106)*$E93) | AW15: =IF(OR(E106=0,AW$3<D106),0,E106*IF(G106=0,H106,MIN(H106,H106*(AW$3-D106+1)/MAX(1,G106)))*(1+F106)^(AW$3-D106)*$E93) | AX15: =IF(OR(E106=0,AX$3<D106),0,E106*IF(G106=0,H106,MIN(H106,H106*(AX$3-D106+1)/MAX(1,G106)))*(1+F106)^(AX$3-D106)*$E93) | AY15: =IF(OR(E106=0,AY$3<D106),0,E106*IF(G106=0,H106,MIN(H106,H106*(AY$3-D106+1)/MAX(1,G106)))*(1+F106)^(AY$3-D106)*$E93) | AZ15: =IF(OR(E106=0,AZ$3<D106),0,E106*IF(G106=0,H106,MIN(H106,H106*(AZ$3-D106+1)/MAX(1,G106)))*(1+F106)^(AZ$3-D106)*$E93) | BA15: =IF(OR(E106=0,BA$3<D106),0,E106*IF(G106=0,H106,MIN(H106,H106*(BA$3-D106+1)/MAX(1,G106)))*(1+F106)^(BA$3-D106)*$E93) | BB15: =IF(OR(E106=0,BB$3<D106),0,E106*IF(G106=0,H106,MIN(H106,H106*(BB$3-D106+1)/MAX(1,G106)))*(1+F106)^(BB$3-D106)*$E93)
A16: =A107 | B16: =B107 | C16: =C107 | D16: =SUM(E16:BB16) | E16: =IF(OR(E107=0,E$3<D107),0,E107*IF(G107=0,H107,MIN(H107,H107*(E$3-D107+1)/MAX(1,G107)))*(1+F107)^(E$3-D107)*$E93) | F16: =IF(OR(E107=0,F$3<D107),0,E107*IF(G107=0,H107,MIN(H107,H107*(F$3-D107+1)/MAX(1,G107)))*(1+F107)^(F$3-D107)*$E93) | G16: =IF(OR(E107=0,G$3<D107),0,E107*IF(G107=0,H107,MIN(H107,H107*(G$3-D107+1)/MAX(1,G107)))*(1+F107)^(G$3-D107)*$E93) | H16: =IF(OR(E107=0,H$3<D107),0,E107*IF(G107=0,H107,MIN(H107,H107*(H$3-D107+1)/MAX(1,G107)))*(1+F107)^(H$3-D107)*$E93) | I16: =IF(OR(E107=0,I$3<D107),0,E107*IF(G107=0,H107,MIN(H107,H107*(I$3-D107+1)/MAX(1,G107)))*(1+F107)^(I$3-D107)*$E93) | J16: =IF(OR(E107=0,J$3<D107),0,E107*IF(G107=0,H107,MIN(H107,H107*(J$3-D107+1)/MAX(1,G107)))*(1+F107)^(J$3-D107)*$E93) | K16: =IF(OR(E107=0,K$3<D107),0,E107*IF(G107=0,H107,MIN(H107,H107*(K$3-D107+1)/MAX(1,G107)))*(1+F107)^(K$3-D107)*$E93) | L16: =IF(OR(E107=0,L$3<D107),0,E107*IF(G107=0,H107,MIN(H107,H107*(L$3-D107+1)/MAX(1,G107)))*(1+F107)^(L$3-D107)*$E93) | M16: =IF(OR(E107=0,M$3<D107),0,E107*IF(G107=0,H107,MIN(H107,H107*(M$3-D107+1)/MAX(1,G107)))*(1+F107)^(M$3-D107)*$E93) | N16: =IF(OR(E107=0,N$3<D107),0,E107*IF(G107=0,H107,MIN(H107,H107*(N$3-D107+1)/MAX(1,G107)))*(1+F107)^(N$3-D107)*$E93) | O16: =IF(OR(E107=0,O$3<D107),0,E107*IF(G107=0,H107,MIN(H107,H107*(O$3-D107+1)/MAX(1,G107)))*(1+F107)^(O$3-D107)*$E93) | P16: =IF(OR(E107=0,P$3<D107),0,E107*IF(G107=0,H107,MIN(H107,H107*(P$3-D107+1)/MAX(1,G107)))*(1+F107)^(P$3-D107)*$E93) | Q16: =IF(OR(E107=0,Q$3<D107),0,E107*IF(G107=0,H107,MIN(H107,H107*(Q$3-D107+1)/MAX(1,G107)))*(1+F107)^(Q$3-D107)*$E93) | R16: =IF(OR(E107=0,R$3<D107),0,E107*IF(G107=0,H107,MIN(H107,H107*(R$3-D107+1)/MAX(1,G107)))*(1+F107)^(R$3-D107)*$E93) | S16: =IF(OR(E107=0,S$3<D107),0,E107*IF(G107=0,H107,MIN(H107,H107*(S$3-D107+1)/MAX(1,G107)))*(1+F107)^(S$3-D107)*$E93) | T16: =IF(OR(E107=0,T$3<D107),0,E107*IF(G107=0,H107,MIN(H107,H107*(T$3-D107+1)/MAX(1,G107)))*(1+F107)^(T$3-D107)*$E93) | U16: =IF(OR(E107=0,U$3<D107),0,E107*IF(G107=0,H107,MIN(H107,H107*(U$3-D107+1)/MAX(1,G107)))*(1+F107)^(U$3-D107)*$E93) | V16: =IF(OR(E107=0,V$3<D107),0,E107*IF(G107=0,H107,MIN(H107,H107*(V$3-D107+1)/MAX(1,G107)))*(1+F107)^(V$3-D107)*$E93) | W16: =IF(OR(E107=0,W$3<D107),0,E107*IF(G107=0,H107,MIN(H107,H107*(W$3-D107+1)/MAX(1,G107)))*(1+F107)^(W$3-D107)*$E93) | X16: =IF(OR(E107=0,X$3<D107),0,E107*IF(G107=0,H107,MIN(H107,H107*(X$3-D107+1)/MAX(1,G107)))*(1+F107)^(X$3-D107)*$E93) | Y16: =IF(OR(E107=0,Y$3<D107),0,E107*IF(G107=0,H107,MIN(H107,H107*(Y$3-D107+1)/MAX(1,G107)))*(1+F107)^(Y$3-D107)*$E93) | Z16: =IF(OR(E107=0,Z$3<D107),0,E107*IF(G107=0,H107,MIN(H107,H107*(Z$3-D107+1)/MAX(1,G107)))*(1+F107)^(Z$3-D107)*$E93) | AA16: =IF(OR(E107=0,AA$3<D107),0,E107*IF(G107=0,H107,MIN(H107,H107*(AA$3-D107+1)/MAX(1,G107)))*(1+F107)^(AA$3-D107)*$E93) | AB16: =IF(OR(E107=0,AB$3<D107),0,E107*IF(G107=0,H107,MIN(H107,H107*(AB$3-D107+1)/MAX(1,G107)))*(1+F107)^(AB$3-D107)*$E93) | AC16: =IF(OR(E107=0,AC$3<D107),0,E107*IF(G107=0,H107,MIN(H107,H107*(AC$3-D107+1)/MAX(1,G107)))*(1+F107)^(AC$3-D107)*$E93) | AD16: =IF(OR(E107=0,AD$3<D107),0,E107*IF(G107=0,H107,MIN(H107,H107*(AD$3-D107+1)/MAX(1,G107)))*(1+F107)^(AD$3-D107)*$E93) | AE16: =IF(OR(E107=0,AE$3<D107),0,E107*IF(G107=0,H107,MIN(H107,H107*(AE$3-D107+1)/MAX(1,G107)))*(1+F107)^(AE$3-D107)*$E93) | AF16: =IF(OR(E107=0,AF$3<D107),0,E107*IF(G107=0,H107,MIN(H107,H107*(AF$3-D107+1)/MAX(1,G107)))*(1+F107)^(AF$3-D107)*$E93) | AG16: =IF(OR(E107=0,AG$3<D107),0,E107*IF(G107=0,H107,MIN(H107,H107*(AG$3-D107+1)/MAX(1,G107)))*(1+F107)^(AG$3-D107)*$E93) | AH16: =IF(OR(E107=0,AH$3<D107),0,E107*IF(G107=0,H107,MIN(H107,H107*(AH$3-D107+1)/MAX(1,G107)))*(1+F107)^(AH$3-D107)*$E93) | AI16: =IF(OR(E107=0,AI$3<D107),0,E107*IF(G107=0,H107,MIN(H107,H107*(AI$3-D107+1)/MAX(1,G107)))*(1+F107)^(AI$3-D107)*$E93) | AJ16: =IF(OR(E107=0,AJ$3<D107),0,E107*IF(G107=0,H107,MIN(H107,H107*(AJ$3-D107+1)/MAX(1,G107)))*(1+F107)^(AJ$3-D107)*$E93) | AK16: =IF(OR(E107=0,AK$3<D107),0,E107*IF(G107=0,H107,MIN(H107,H107*(AK$3-D107+1)/MAX(1,G107)))*(1+F107)^(AK$3-D107)*$E93) | AL16: =IF(OR(E107=0,AL$3<D107),0,E107*IF(G107=0,H107,MIN(H107,H107*(AL$3-D107+1)/MAX(1,G107)))*(1+F107)^(AL$3-D107)*$E93) | AM16: =IF(OR(E107=0,AM$3<D107),0,E107*IF(G107=0,H107,MIN(H107,H107*(AM$3-D107+1)/MAX(1,G107)))*(1+F107)^(AM$3-D107)*$E93) | AN16: =IF(OR(E107=0,AN$3<D107),0,E107*IF(G107=0,H107,MIN(H107,H107*(AN$3-D107+1)/MAX(1,G107)))*(1+F107)^(AN$3-D107)*$E93) | AO16: =IF(OR(E107=0,AO$3<D107),0,E107*IF(G107=0,H107,MIN(H107,H107*(AO$3-D107+1)/MAX(1,G107)))*(1+F107)^(AO$3-D107)*$E93) | AP16: =IF(OR(E107=0,AP$3<D107),0,E107*IF(G107=0,H107,MIN(H107,H107*(AP$3-D107+1)/MAX(1,G107)))*(1+F107)^(AP$3-D107)*$E93) | AQ16: =IF(OR(E107=0,AQ$3<D107),0,E107*IF(G107=0,H107,MIN(H107,H107*(AQ$3-D107+1)/MAX(1,G107)))*(1+F107)^(AQ$3-D107)*$E93) | AR16: =IF(OR(E107=0,AR$3<D107),0,E107*IF(G107=0,H107,MIN(H107,H107*(AR$3-D107+1)/MAX(1,G107)))*(1+F107)^(AR$3-D107)*$E93) | AS16: =IF(OR(E107=0,AS$3<D107),0,E107*IF(G107=0,H107,MIN(H107,H107*(AS$3-D107+1)/MAX(1,G107)))*(1+F107)^(AS$3-D107)*$E93) | AT16: =IF(OR(E107=0,AT$3<D107),0,E107*IF(G107=0,H107,MIN(H107,H107*(AT$3-D107+1)/MAX(1,G107)))*(1+F107)^(AT$3-D107)*$E93) | AU16: =IF(OR(E107=0,AU$3<D107),0,E107*IF(G107=0,H107,MIN(H107,H107*(AU$3-D107+1)/MAX(1,G107)))*(1+F107)^(AU$3-D107)*$E93) | AV16: =IF(OR(E107=0,AV$3<D107),0,E107*IF(G107=0,H107,MIN(H107,H107*(AV$3-D107+1)/MAX(1,G107)))*(1+F107)^(AV$3-D107)*$E93) | AW16: =IF(OR(E107=0,AW$3<D107),0,E107*IF(G107=0,H107,MIN(H107,H107*(AW$3-D107+1)/MAX(1,G107)))*(1+F107)^(AW$3-D107)*$E93) | AX16: =IF(OR(E107=0,AX$3<D107),0,E107*IF(G107=0,H107,MIN(H107,H107*(AX$3-D107+1)/MAX(1,G107)))*(1+F107)^(AX$3-D107)*$E93) | AY16: =IF(OR(E107=0,AY$3<D107),0,E107*IF(G107=0,H107,MIN(H107,H107*(AY$3-D107+1)/MAX(1,G107)))*(1+F107)^(AY$3-D107)*$E93) | AZ16: =IF(OR(E107=0,AZ$3<D107),0,E107*IF(G107=0,H107,MIN(H107,H107*(AZ$3-D107+1)/MAX(1,G107)))*(1+F107)^(AZ$3-D107)*$E93) | BA16: =IF(OR(E107=0,BA$3<D107),0,E107*IF(G107=0,H107,MIN(H107,H107*(BA$3-D107+1)/MAX(1,G107)))*(1+F107)^(BA$3-D107)*$E93) | BB16: =IF(OR(E107=0,BB$3<D107),0,E107*IF(G107=0,H107,MIN(H107,H107*(BB$3-D107+1)/MAX(1,G107)))*(1+F107)^(BB$3-D107)*$E93)
A17: =A108 | B17: =B108 | C17: =C108 | D17: =SUM(E17:BB17) | E17: =IF(OR(E108=0,E$3<D108),0,E108*IF(G108=0,H108,MIN(H108,H108*(E$3-D108+1)/MAX(1,G108)))*(1+F108)^(E$3-D108)*$E93) | F17: =IF(OR(E108=0,F$3<D108),0,E108*IF(G108=0,H108,MIN(H108,H108*(F$3-D108+1)/MAX(1,G108)))*(1+F108)^(F$3-D108)*$E93) | G17: =IF(OR(E108=0,G$3<D108),0,E108*IF(G108=0,H108,MIN(H108,H108*(G$3-D108+1)/MAX(1,G108)))*(1+F108)^(G$3-D108)*$E93) | H17: =IF(OR(E108=0,H$3<D108),0,E108*IF(G108=0,H108,MIN(H108,H108*(H$3-D108+1)/MAX(1,G108)))*(1+F108)^(H$3-D108)*$E93) | I17: =IF(OR(E108=0,I$3<D108),0,E108*IF(G108=0,H108,MIN(H108,H108*(I$3-D108+1)/MAX(1,G108)))*(1+F108)^(I$3-D108)*$E93) | J17: =IF(OR(E108=0,J$3<D108),0,E108*IF(G108=0,H108,MIN(H108,H108*(J$3-D108+1)/MAX(1,G108)))*(1+F108)^(J$3-D108)*$E93) | K17: =IF(OR(E108=0,K$3<D108),0,E108*IF(G108=0,H108,MIN(H108,H108*(K$3-D108+1)/MAX(1,G108)))*(1+F108)^(K$3-D108)*$E93) | L17: =IF(OR(E108=0,L$3<D108),0,E108*IF(G108=0,H108,MIN(H108,H108*(L$3-D108+1)/MAX(1,G108)))*(1+F108)^(L$3-D108)*$E93) | M17: =IF(OR(E108=0,M$3<D108),0,E108*IF(G108=0,H108,MIN(H108,H108*(M$3-D108+1)/MAX(1,G108)))*(1+F108)^(M$3-D108)*$E93) | N17: =IF(OR(E108=0,N$3<D108),0,E108*IF(G108=0,H108,MIN(H108,H108*(N$3-D108+1)/MAX(1,G108)))*(1+F108)^(N$3-D108)*$E93) | O17: =IF(OR(E108=0,O$3<D108),0,E108*IF(G108=0,H108,MIN(H108,H108*(O$3-D108+1)/MAX(1,G108)))*(1+F108)^(O$3-D108)*$E93) | P17: =IF(OR(E108=0,P$3<D108),0,E108*IF(G108=0,H108,MIN(H108,H108*(P$3-D108+1)/MAX(1,G108)))*(1+F108)^(P$3-D108)*$E93) | Q17: =IF(OR(E108=0,Q$3<D108),0,E108*IF(G108=0,H108,MIN(H108,H108*(Q$3-D108+1)/MAX(1,G108)))*(1+F108)^(Q$3-D108)*$E93) | R17: =IF(OR(E108=0,R$3<D108),0,E108*IF(G108=0,H108,MIN(H108,H108*(R$3-D108+1)/MAX(1,G108)))*(1+F108)^(R$3-D108)*$E93) | S17: =IF(OR(E108=0,S$3<D108),0,E108*IF(G108=0,H108,MIN(H108,H108*(S$3-D108+1)/MAX(1,G108)))*(1+F108)^(S$3-D108)*$E93) | T17: =IF(OR(E108=0,T$3<D108),0,E108*IF(G108=0,H108,MIN(H108,H108*(T$3-D108+1)/MAX(1,G108)))*(1+F108)^(T$3-D108)*$E93) | U17: =IF(OR(E108=0,U$3<D108),0,E108*IF(G108=0,H108,MIN(H108,H108*(U$3-D108+1)/MAX(1,G108)))*(1+F108)^(U$3-D108)*$E93) | V17: =IF(OR(E108=0,V$3<D108),0,E108*IF(G108=0,H108,MIN(H108,H108*(V$3-D108+1)/MAX(1,G108)))*(1+F108)^(V$3-D108)*$E93) | W17: =IF(OR(E108=0,W$3<D108),0,E108*IF(G108=0,H108,MIN(H108,H108*(W$3-D108+1)/MAX(1,G108)))*(1+F108)^(W$3-D108)*$E93) | X17: =IF(OR(E108=0,X$3<D108),0,E108*IF(G108=0,H108,MIN(H108,H108*(X$3-D108+1)/MAX(1,G108)))*(1+F108)^(X$3-D108)*$E93) | Y17: =IF(OR(E108=0,Y$3<D108),0,E108*IF(G108=0,H108,MIN(H108,H108*(Y$3-D108+1)/MAX(1,G108)))*(1+F108)^(Y$3-D108)*$E93) | Z17: =IF(OR(E108=0,Z$3<D108),0,E108*IF(G108=0,H108,MIN(H108,H108*(Z$3-D108+1)/MAX(1,G108)))*(1+F108)^(Z$3-D108)*$E93) | AA17: =IF(OR(E108=0,AA$3<D108),0,E108*IF(G108=0,H108,MIN(H108,H108*(AA$3-D108+1)/MAX(1,G108)))*(1+F108)^(AA$3-D108)*$E93) | AB17: =IF(OR(E108=0,AB$3<D108),0,E108*IF(G108=0,H108,MIN(H108,H108*(AB$3-D108+1)/MAX(1,G108)))*(1+F108)^(AB$3-D108)*$E93) | AC17: =IF(OR(E108=0,AC$3<D108),0,E108*IF(G108=0,H108,MIN(H108,H108*(AC$3-D108+1)/MAX(1,G108)))*(1+F108)^(AC$3-D108)*$E93) | AD17: =IF(OR(E108=0,AD$3<D108),0,E108*IF(G108=0,H108,MIN(H108,H108*(AD$3-D108+1)/MAX(1,G108)))*(1+F108)^(AD$3-D108)*$E93) | AE17: =IF(OR(E108=0,AE$3<D108),0,E108*IF(G108=0,H108,MIN(H108,H108*(AE$3-D108+1)/MAX(1,G108)))*(1+F108)^(AE$3-D108)*$E93) | AF17: =IF(OR(E108=0,AF$3<D108),0,E108*IF(G108=0,H108,MIN(H108,H108*(AF$3-D108+1)/MAX(1,G108)))*(1+F108)^(AF$3-D108)*$E93) | AG17: =IF(OR(E108=0,AG$3<D108),0,E108*IF(G108=0,H108,MIN(H108,H108*(AG$3-D108+1)/MAX(1,G108)))*(1+F108)^(AG$3-D108)*$E93) | AH17: =IF(OR(E108=0,AH$3<D108),0,E108*IF(G108=0,H108,MIN(H108,H108*(AH$3-D108+1)/MAX(1,G108)))*(1+F108)^(AH$3-D108)*$E93) | AI17: =IF(OR(E108=0,AI$3<D108),0,E108*IF(G108=0,H108,MIN(H108,H108*(AI$3-D108+1)/MAX(1,G108)))*(1+F108)^(AI$3-D108)*$E93) | AJ17: =IF(OR(E108=0,AJ$3<D108),0,E108*IF(G108=0,H108,MIN(H108,H108*(AJ$3-D108+1)/MAX(1,G108)))*(1+F108)^(AJ$3-D108)*$E93) | AK17: =IF(OR(E108=0,AK$3<D108),0,E108*IF(G108=0,H108,MIN(H108,H108*(AK$3-D108+1)/MAX(1,G108)))*(1+F108)^(AK$3-D108)*$E93) | AL17: =IF(OR(E108=0,AL$3<D108),0,E108*IF(G108=0,H108,MIN(H108,H108*(AL$3-D108+1)/MAX(1,G108)))*(1+F108)^(AL$3-D108)*$E93) | AM17: =IF(OR(E108=0,AM$3<D108),0,E108*IF(G108=0,H108,MIN(H108,H108*(AM$3-D108+1)/MAX(1,G108)))*(1+F108)^(AM$3-D108)*$E93) | AN17: =IF(OR(E108=0,AN$3<D108),0,E108*IF(G108=0,H108,MIN(H108,H108*(AN$3-D108+1)/MAX(1,G108)))*(1+F108)^(AN$3-D108)*$E93) | AO17: =IF(OR(E108=0,AO$3<D108),0,E108*IF(G108=0,H108,MIN(H108,H108*(AO$3-D108+1)/MAX(1,G108)))*(1+F108)^(AO$3-D108)*$E93) | AP17: =IF(OR(E108=0,AP$3<D108),0,E108*IF(G108=0,H108,MIN(H108,H108*(AP$3-D108+1)/MAX(1,G108)))*(1+F108)^(AP$3-D108)*$E93) | AQ17: =IF(OR(E108=0,AQ$3<D108),0,E108*IF(G108=0,H108,MIN(H108,H108*(AQ$3-D108+1)/MAX(1,G108)))*(1+F108)^(AQ$3-D108)*$E93) | AR17: =IF(OR(E108=0,AR$3<D108),0,E108*IF(G108=0,H108,MIN(H108,H108*(AR$3-D108+1)/MAX(1,G108)))*(1+F108)^(AR$3-D108)*$E93) | AS17: =IF(OR(E108=0,AS$3<D108),0,E108*IF(G108=0,H108,MIN(H108,H108*(AS$3-D108+1)/MAX(1,G108)))*(1+F108)^(AS$3-D108)*$E93) | AT17: =IF(OR(E108=0,AT$3<D108),0,E108*IF(G108=0,H108,MIN(H108,H108*(AT$3-D108+1)/MAX(1,G108)))*(1+F108)^(AT$3-D108)*$E93) | AU17: =IF(OR(E108=0,AU$3<D108),0,E108*IF(G108=0,H108,MIN(H108,H108*(AU$3-D108+1)/MAX(1,G108)))*(1+F108)^(AU$3-D108)*$E93) | AV17: =IF(OR(E108=0,AV$3<D108),0,E108*IF(G108=0,H108,MIN(H108,H108*(AV$3-D108+1)/MAX(1,G108)))*(1+F108)^(AV$3-D108)*$E93) | AW17: =IF(OR(E108=0,AW$3<D108),0,E108*IF(G108=0,H108,MIN(H108,H108*(AW$3-D108+1)/MAX(1,G108)))*(1+F108)^(AW$3-D108)*$E93) | AX17: =IF(OR(E108=0,AX$3<D108),0,E108*IF(G108=0,H108,MIN(H108,H108*(AX$3-D108+1)/MAX(1,G108)))*(1+F108)^(AX$3-D108)*$E93) | AY17: =IF(OR(E108=0,AY$3<D108),0,E108*IF(G108=0,H108,MIN(H108,H108*(AY$3-D108+1)/MAX(1,G108)))*(1+F108)^(AY$3-D108)*$E93) | AZ17: =IF(OR(E108=0,AZ$3<D108),0,E108*IF(G108=0,H108,MIN(H108,H108*(AZ$3-D108+1)/MAX(1,G108)))*(1+F108)^(AZ$3-D108)*$E93) | BA17: =IF(OR(E108=0,BA$3<D108),0,E108*IF(G108=0,H108,MIN(H108,H108*(BA$3-D108+1)/MAX(1,G108)))*(1+F108)^(BA$3-D108)*$E93) | BB17: =IF(OR(E108=0,BB$3<D108),0,E108*IF(G108=0,H108,MIN(H108,H108*(BB$3-D108+1)/MAX(1,G108)))*(1+F108)^(BB$3-D108)*$E93)
A18: =A109 | B18: =B109 | C18: =C109 | D18: =SUM(E18:BB18) | E18: =IF(OR(E109=0,E$3<D109),0,E109*IF(G109=0,H109,MIN(H109,H109*(E$3-D109+1)/MAX(1,G109)))*(1+F109)^(E$3-D109)*$E93) | F18: =IF(OR(E109=0,F$3<D109),0,E109*IF(G109=0,H109,MIN(H109,H109*(F$3-D109+1)/MAX(1,G109)))*(1+F109)^(F$3-D109)*$E93) | G18: =IF(OR(E109=0,G$3<D109),0,E109*IF(G109=0,H109,MIN(H109,H109*(G$3-D109+1)/MAX(1,G109)))*(1+F109)^(G$3-D109)*$E93) | H18: =IF(OR(E109=0,H$3<D109),0,E109*IF(G109=0,H109,MIN(H109,H109*(H$3-D109+1)/MAX(1,G109)))*(1+F109)^(H$3-D109)*$E93) | I18: =IF(OR(E109=0,I$3<D109),0,E109*IF(G109=0,H109,MIN(H109,H109*(I$3-D109+1)/MAX(1,G109)))*(1+F109)^(I$3-D109)*$E93) | J18: =IF(OR(E109=0,J$3<D109),0,E109*IF(G109=0,H109,MIN(H109,H109*(J$3-D109+1)/MAX(1,G109)))*(1+F109)^(J$3-D109)*$E93) | K18: =IF(OR(E109=0,K$3<D109),0,E109*IF(G109=0,H109,MIN(H109,H109*(K$3-D109+1)/MAX(1,G109)))*(1+F109)^(K$3-D109)*$E93) | L18: =IF(OR(E109=0,L$3<D109),0,E109*IF(G109=0,H109,MIN(H109,H109*(L$3-D109+1)/MAX(1,G109)))*(1+F109)^(L$3-D109)*$E93) | M18: =IF(OR(E109=0,M$3<D109),0,E109*IF(G109=0,H109,MIN(H109,H109*(M$3-D109+1)/MAX(1,G109)))*(1+F109)^(M$3-D109)*$E93) | N18: =IF(OR(E109=0,N$3<D109),0,E109*IF(G109=0,H109,MIN(H109,H109*(N$3-D109+1)/MAX(1,G109)))*(1+F109)^(N$3-D109)*$E93) | O18: =IF(OR(E109=0,O$3<D109),0,E109*IF(G109=0,H109,MIN(H109,H109*(O$3-D109+1)/MAX(1,G109)))*(1+F109)^(O$3-D109)*$E93) | P18: =IF(OR(E109=0,P$3<D109),0,E109*IF(G109=0,H109,MIN(H109,H109*(P$3-D109+1)/MAX(1,G109)))*(1+F109)^(P$3-D109)*$E93) | Q18: =IF(OR(E109=0,Q$3<D109),0,E109*IF(G109=0,H109,MIN(H109,H109*(Q$3-D109+1)/MAX(1,G109)))*(1+F109)^(Q$3-D109)*$E93) | R18: =IF(OR(E109=0,R$3<D109),0,E109*IF(G109=0,H109,MIN(H109,H109*(R$3-D109+1)/MAX(1,G109)))*(1+F109)^(R$3-D109)*$E93) | S18: =IF(OR(E109=0,S$3<D109),0,E109*IF(G109=0,H109,MIN(H109,H109*(S$3-D109+1)/MAX(1,G109)))*(1+F109)^(S$3-D109)*$E93) | T18: =IF(OR(E109=0,T$3<D109),0,E109*IF(G109=0,H109,MIN(H109,H109*(T$3-D109+1)/MAX(1,G109)))*(1+F109)^(T$3-D109)*$E93) | U18: =IF(OR(E109=0,U$3<D109),0,E109*IF(G109=0,H109,MIN(H109,H109*(U$3-D109+1)/MAX(1,G109)))*(1+F109)^(U$3-D109)*$E93) | V18: =IF(OR(E109=0,V$3<D109),0,E109*IF(G109=0,H109,MIN(H109,H109*(V$3-D109+1)/MAX(1,G109)))*(1+F109)^(V$3-D109)*$E93) | W18: =IF(OR(E109=0,W$3<D109),0,E109*IF(G109=0,H109,MIN(H109,H109*(W$3-D109+1)/MAX(1,G109)))*(1+F109)^(W$3-D109)*$E93) | X18: =IF(OR(E109=0,X$3<D109),0,E109*IF(G109=0,H109,MIN(H109,H109*(X$3-D109+1)/MAX(1,G109)))*(1+F109)^(X$3-D109)*$E93) | Y18: =IF(OR(E109=0,Y$3<D109),0,E109*IF(G109=0,H109,MIN(H109,H109*(Y$3-D109+1)/MAX(1,G109)))*(1+F109)^(Y$3-D109)*$E93) | Z18: =IF(OR(E109=0,Z$3<D109),0,E109*IF(G109=0,H109,MIN(H109,H109*(Z$3-D109+1)/MAX(1,G109)))*(1+F109)^(Z$3-D109)*$E93) | AA18: =IF(OR(E109=0,AA$3<D109),0,E109*IF(G109=0,H109,MIN(H109,H109*(AA$3-D109+1)/MAX(1,G109)))*(1+F109)^(AA$3-D109)*$E93) | AB18: =IF(OR(E109=0,AB$3<D109),0,E109*IF(G109=0,H109,MIN(H109,H109*(AB$3-D109+1)/MAX(1,G109)))*(1+F109)^(AB$3-D109)*$E93) | AC18: =IF(OR(E109=0,AC$3<D109),0,E109*IF(G109=0,H109,MIN(H109,H109*(AC$3-D109+1)/MAX(1,G109)))*(1+F109)^(AC$3-D109)*$E93) | AD18: =IF(OR(E109=0,AD$3<D109),0,E109*IF(G109=0,H109,MIN(H109,H109*(AD$3-D109+1)/MAX(1,G109)))*(1+F109)^(AD$3-D109)*$E93) | AE18: =IF(OR(E109=0,AE$3<D109),0,E109*IF(G109=0,H109,MIN(H109,H109*(AE$3-D109+1)/MAX(1,G109)))*(1+F109)^(AE$3-D109)*$E93) | AF18: =IF(OR(E109=0,AF$3<D109),0,E109*IF(G109=0,H109,MIN(H109,H109*(AF$3-D109+1)/MAX(1,G109)))*(1+F109)^(AF$3-D109)*$E93) | AG18: =IF(OR(E109=0,AG$3<D109),0,E109*IF(G109=0,H109,MIN(H109,H109*(AG$3-D109+1)/MAX(1,G109)))*(1+F109)^(AG$3-D109)*$E93) | AH18: =IF(OR(E109=0,AH$3<D109),0,E109*IF(G109=0,H109,MIN(H109,H109*(AH$3-D109+1)/MAX(1,G109)))*(1+F109)^(AH$3-D109)*$E93) | AI18: =IF(OR(E109=0,AI$3<D109),0,E109*IF(G109=0,H109,MIN(H109,H109*(AI$3-D109+1)/MAX(1,G109)))*(1+F109)^(AI$3-D109)*$E93) | AJ18: =IF(OR(E109=0,AJ$3<D109),0,E109*IF(G109=0,H109,MIN(H109,H109*(AJ$3-D109+1)/MAX(1,G109)))*(1+F109)^(AJ$3-D109)*$E93) | AK18: =IF(OR(E109=0,AK$3<D109),0,E109*IF(G109=0,H109,MIN(H109,H109*(AK$3-D109+1)/MAX(1,G109)))*(1+F109)^(AK$3-D109)*$E93) | AL18: =IF(OR(E109=0,AL$3<D109),0,E109*IF(G109=0,H109,MIN(H109,H109*(AL$3-D109+1)/MAX(1,G109)))*(1+F109)^(AL$3-D109)*$E93) | AM18: =IF(OR(E109=0,AM$3<D109),0,E109*IF(G109=0,H109,MIN(H109,H109*(AM$3-D109+1)/MAX(1,G109)))*(1+F109)^(AM$3-D109)*$E93) | AN18: =IF(OR(E109=0,AN$3<D109),0,E109*IF(G109=0,H109,MIN(H109,H109*(AN$3-D109+1)/MAX(1,G109)))*(1+F109)^(AN$3-D109)*$E93) | AO18: =IF(OR(E109=0,AO$3<D109),0,E109*IF(G109=0,H109,MIN(H109,H109*(AO$3-D109+1)/MAX(1,G109)))*(1+F109)^(AO$3-D109)*$E93) | AP18: =IF(OR(E109=0,AP$3<D109),0,E109*IF(G109=0,H109,MIN(H109,H109*(AP$3-D109+1)/MAX(1,G109)))*(1+F109)^(AP$3-D109)*$E93) | AQ18: =IF(OR(E109=0,AQ$3<D109),0,E109*IF(G109=0,H109,MIN(H109,H109*(AQ$3-D109+1)/MAX(1,G109)))*(1+F109)^(AQ$3-D109)*$E93) | AR18: =IF(OR(E109=0,AR$3<D109),0,E109*IF(G109=0,H109,MIN(H109,H109*(AR$3-D109+1)/MAX(1,G109)))*(1+F109)^(AR$3-D109)*$E93) | AS18: =IF(OR(E109=0,AS$3<D109),0,E109*IF(G109=0,H109,MIN(H109,H109*(AS$3-D109+1)/MAX(1,G109)))*(1+F109)^(AS$3-D109)*$E93) | AT18: =IF(OR(E109=0,AT$3<D109),0,E109*IF(G109=0,H109,MIN(H109,H109*(AT$3-D109+1)/MAX(1,G109)))*(1+F109)^(AT$3-D109)*$E93) | AU18: =IF(OR(E109=0,AU$3<D109),0,E109*IF(G109=0,H109,MIN(H109,H109*(AU$3-D109+1)/MAX(1,G109)))*(1+F109)^(AU$3-D109)*$E93) | AV18: =IF(OR(E109=0,AV$3<D109),0,E109*IF(G109=0,H109,MIN(H109,H109*(AV$3-D109+1)/MAX(1,G109)))*(1+F109)^(AV$3-D109)*$E93) | AW18: =IF(OR(E109=0,AW$3<D109),0,E109*IF(G109=0,H109,MIN(H109,H109*(AW$3-D109+1)/MAX(1,G109)))*(1+F109)^(AW$3-D109)*$E93) | AX18: =IF(OR(E109=0,AX$3<D109),0,E109*IF(G109=0,H109,MIN(H109,H109*(AX$3-D109+1)/MAX(1,G109)))*(1+F109)^(AX$3-D109)*$E93) | AY18: =IF(OR(E109=0,AY$3<D109),0,E109*IF(G109=0,H109,MIN(H109,H109*(AY$3-D109+1)/MAX(1,G109)))*(1+F109)^(AY$3-D109)*$E93) | AZ18: =IF(OR(E109=0,AZ$3<D109),0,E109*IF(G109=0,H109,MIN(H109,H109*(AZ$3-D109+1)/MAX(1,G109)))*(1+F109)^(AZ$3-D109)*$E93) | BA18: =IF(OR(E109=0,BA$3<D109),0,E109*IF(G109=0,H109,MIN(H109,H109*(BA$3-D109+1)/MAX(1,G109)))*(1+F109)^(BA$3-D109)*$E93) | BB18: =IF(OR(E109=0,BB$3<D109),0,E109*IF(G109=0,H109,MIN(H109,H109*(BB$3-D109+1)/MAX(1,G109)))*(1+F109)^(BB$3-D109)*$E93)
A19: =A110 | B19: =B110 | C19: =C110 | D19: =SUM(E19:BB19) | E19: =IF(OR(E110=0,E$3<D110),0,E110*IF(G110=0,H110,MIN(H110,H110*(E$3-D110+1)/MAX(1,G110)))*(1+F110)^(E$3-D110)*$E93) | F19: =IF(OR(E110=0,F$3<D110),0,E110*IF(G110=0,H110,MIN(H110,H110*(F$3-D110+1)/MAX(1,G110)))*(1+F110)^(F$3-D110)*$E93) | G19: =IF(OR(E110=0,G$3<D110),0,E110*IF(G110=0,H110,MIN(H110,H110*(G$3-D110+1)/MAX(1,G110)))*(1+F110)^(G$3-D110)*$E93) | H19: =IF(OR(E110=0,H$3<D110),0,E110*IF(G110=0,H110,MIN(H110,H110*(H$3-D110+1)/MAX(1,G110)))*(1+F110)^(H$3-D110)*$E93) | I19: =IF(OR(E110=0,I$3<D110),0,E110*IF(G110=0,H110,MIN(H110,H110*(I$3-D110+1)/MAX(1,G110)))*(1+F110)^(I$3-D110)*$E93) | J19: =IF(OR(E110=0,J$3<D110),0,E110*IF(G110=0,H110,MIN(H110,H110*(J$3-D110+1)/MAX(1,G110)))*(1+F110)^(J$3-D110)*$E93) | K19: =IF(OR(E110=0,K$3<D110),0,E110*IF(G110=0,H110,MIN(H110,H110*(K$3-D110+1)/MAX(1,G110)))*(1+F110)^(K$3-D110)*$E93) | L19: =IF(OR(E110=0,L$3<D110),0,E110*IF(G110=0,H110,MIN(H110,H110*(L$3-D110+1)/MAX(1,G110)))*(1+F110)^(L$3-D110)*$E93) | M19: =IF(OR(E110=0,M$3<D110),0,E110*IF(G110=0,H110,MIN(H110,H110*(M$3-D110+1)/MAX(1,G110)))*(1+F110)^(M$3-D110)*$E93) | N19: =IF(OR(E110=0,N$3<D110),0,E110*IF(G110=0,H110,MIN(H110,H110*(N$3-D110+1)/MAX(1,G110)))*(1+F110)^(N$3-D110)*$E93) | O19: =IF(OR(E110=0,O$3<D110),0,E110*IF(G110=0,H110,MIN(H110,H110*(O$3-D110+1)/MAX(1,G110)))*(1+F110)^(O$3-D110)*$E93) | P19: =IF(OR(E110=0,P$3<D110),0,E110*IF(G110=0,H110,MIN(H110,H110*(P$3-D110+1)/MAX(1,G110)))*(1+F110)^(P$3-D110)*$E93) | Q19: =IF(OR(E110=0,Q$3<D110),0,E110*IF(G110=0,H110,MIN(H110,H110*(Q$3-D110+1)/MAX(1,G110)))*(1+F110)^(Q$3-D110)*$E93) | R19: =IF(OR(E110=0,R$3<D110),0,E110*IF(G110=0,H110,MIN(H110,H110*(R$3-D110+1)/MAX(1,G110)))*(1+F110)^(R$3-D110)*$E93) | S19: =IF(OR(E110=0,S$3<D110),0,E110*IF(G110=0,H110,MIN(H110,H110*(S$3-D110+1)/MAX(1,G110)))*(1+F110)^(S$3-D110)*$E93) | T19: =IF(OR(E110=0,T$3<D110),0,E110*IF(G110=0,H110,MIN(H110,H110*(T$3-D110+1)/MAX(1,G110)))*(1+F110)^(T$3-D110)*$E93) | U19: =IF(OR(E110=0,U$3<D110),0,E110*IF(G110=0,H110,MIN(H110,H110*(U$3-D110+1)/MAX(1,G110)))*(1+F110)^(U$3-D110)*$E93) | V19: =IF(OR(E110=0,V$3<D110),0,E110*IF(G110=0,H110,MIN(H110,H110*(V$3-D110+1)/MAX(1,G110)))*(1+F110)^(V$3-D110)*$E93) | W19: =IF(OR(E110=0,W$3<D110),0,E110*IF(G110=0,H110,MIN(H110,H110*(W$3-D110+1)/MAX(1,G110)))*(1+F110)^(W$3-D110)*$E93) | X19: =IF(OR(E110=0,X$3<D110),0,E110*IF(G110=0,H110,MIN(H110,H110*(X$3-D110+1)/MAX(1,G110)))*(1+F110)^(X$3-D110)*$E93) | Y19: =IF(OR(E110=0,Y$3<D110),0,E110*IF(G110=0,H110,MIN(H110,H110*(Y$3-D110+1)/MAX(1,G110)))*(1+F110)^(Y$3-D110)*$E93) | Z19: =IF(OR(E110=0,Z$3<D110),0,E110*IF(G110=0,H110,MIN(H110,H110*(Z$3-D110+1)/MAX(1,G110)))*(1+F110)^(Z$3-D110)*$E93) | AA19: =IF(OR(E110=0,AA$3<D110),0,E110*IF(G110=0,H110,MIN(H110,H110*(AA$3-D110+1)/MAX(1,G110)))*(1+F110)^(AA$3-D110)*$E93) | AB19: =IF(OR(E110=0,AB$3<D110),0,E110*IF(G110=0,H110,MIN(H110,H110*(AB$3-D110+1)/MAX(1,G110)))*(1+F110)^(AB$3-D110)*$E93) | AC19: =IF(OR(E110=0,AC$3<D110),0,E110*IF(G110=0,H110,MIN(H110,H110*(AC$3-D110+1)/MAX(1,G110)))*(1+F110)^(AC$3-D110)*$E93) | AD19: =IF(OR(E110=0,AD$3<D110),0,E110*IF(G110=0,H110,MIN(H110,H110*(AD$3-D110+1)/MAX(1,G110)))*(1+F110)^(AD$3-D110)*$E93) | AE19: =IF(OR(E110=0,AE$3<D110),0,E110*IF(G110=0,H110,MIN(H110,H110*(AE$3-D110+1)/MAX(1,G110)))*(1+F110)^(AE$3-D110)*$E93) | AF19: =IF(OR(E110=0,AF$3<D110),0,E110*IF(G110=0,H110,MIN(H110,H110*(AF$3-D110+1)/MAX(1,G110)))*(1+F110)^(AF$3-D110)*$E93) | AG19: =IF(OR(E110=0,AG$3<D110),0,E110*IF(G110=0,H110,MIN(H110,H110*(AG$3-D110+1)/MAX(1,G110)))*(1+F110)^(AG$3-D110)*$E93) | AH19: =IF(OR(E110=0,AH$3<D110),0,E110*IF(G110=0,H110,MIN(H110,H110*(AH$3-D110+1)/MAX(1,G110)))*(1+F110)^(AH$3-D110)*$E93) | AI19: =IF(OR(E110=0,AI$3<D110),0,E110*IF(G110=0,H110,MIN(H110,H110*(AI$3-D110+1)/MAX(1,G110)))*(1+F110)^(AI$3-D110)*$E93) | AJ19: =IF(OR(E110=0,AJ$3<D110),0,E110*IF(G110=0,H110,MIN(H110,H110*(AJ$3-D110+1)/MAX(1,G110)))*(1+F110)^(AJ$3-D110)*$E93) | AK19: =IF(OR(E110=0,AK$3<D110),0,E110*IF(G110=0,H110,MIN(H110,H110*(AK$3-D110+1)/MAX(1,G110)))*(1+F110)^(AK$3-D110)*$E93) | AL19: =IF(OR(E110=0,AL$3<D110),0,E110*IF(G110=0,H110,MIN(H110,H110*(AL$3-D110+1)/MAX(1,G110)))*(1+F110)^(AL$3-D110)*$E93) | AM19: =IF(OR(E110=0,AM$3<D110),0,E110*IF(G110=0,H110,MIN(H110,H110*(AM$3-D110+1)/MAX(1,G110)))*(1+F110)^(AM$3-D110)*$E93) | AN19: =IF(OR(E110=0,AN$3<D110),0,E110*IF(G110=0,H110,MIN(H110,H110*(AN$3-D110+1)/MAX(1,G110)))*(1+F110)^(AN$3-D110)*$E93) | AO19: =IF(OR(E110=0,AO$3<D110),0,E110*IF(G110=0,H110,MIN(H110,H110*(AO$3-D110+1)/MAX(1,G110)))*(1+F110)^(AO$3-D110)*$E93) | AP19: =IF(OR(E110=0,AP$3<D110),0,E110*IF(G110=0,H110,MIN(H110,H110*(AP$3-D110+1)/MAX(1,G110)))*(1+F110)^(AP$3-D110)*$E93) | AQ19: =IF(OR(E110=0,AQ$3<D110),0,E110*IF(G110=0,H110,MIN(H110,H110*(AQ$3-D110+1)/MAX(1,G110)))*(1+F110)^(AQ$3-D110)*$E93) | AR19: =IF(OR(E110=0,AR$3<D110),0,E110*IF(G110=0,H110,MIN(H110,H110*(AR$3-D110+1)/MAX(1,G110)))*(1+F110)^(AR$3-D110)*$E93) | AS19: =IF(OR(E110=0,AS$3<D110),0,E110*IF(G110=0,H110,MIN(H110,H110*(AS$3-D110+1)/MAX(1,G110)))*(1+F110)^(AS$3-D110)*$E93) | AT19: =IF(OR(E110=0,AT$3<D110),0,E110*IF(G110=0,H110,MIN(H110,H110*(AT$3-D110+1)/MAX(1,G110)))*(1+F110)^(AT$3-D110)*$E93) | AU19: =IF(OR(E110=0,AU$3<D110),0,E110*IF(G110=0,H110,MIN(H110,H110*(AU$3-D110+1)/MAX(1,G110)))*(1+F110)^(AU$3-D110)*$E93) | AV19: =IF(OR(E110=0,AV$3<D110),0,E110*IF(G110=0,H110,MIN(H110,H110*(AV$3-D110+1)/MAX(1,G110)))*(1+F110)^(AV$3-D110)*$E93) | AW19: =IF(OR(E110=0,AW$3<D110),0,E110*IF(G110=0,H110,MIN(H110,H110*(AW$3-D110+1)/MAX(1,G110)))*(1+F110)^(AW$3-D110)*$E93) | AX19: =IF(OR(E110=0,AX$3<D110),0,E110*IF(G110=0,H110,MIN(H110,H110*(AX$3-D110+1)/MAX(1,G110)))*(1+F110)^(AX$3-D110)*$E93) | AY19: =IF(OR(E110=0,AY$3<D110),0,E110*IF(G110=0,H110,MIN(H110,H110*(AY$3-D110+1)/MAX(1,G110)))*(1+F110)^(AY$3-D110)*$E93) | AZ19: =IF(OR(E110=0,AZ$3<D110),0,E110*IF(G110=0,H110,MIN(H110,H110*(AZ$3-D110+1)/MAX(1,G110)))*(1+F110)^(AZ$3-D110)*$E93) | BA19: =IF(OR(E110=0,BA$3<D110),0,E110*IF(G110=0,H110,MIN(H110,H110*(BA$3-D110+1)/MAX(1,G110)))*(1+F110)^(BA$3-D110)*$E93) | BB19: =IF(OR(E110=0,BB$3<D110),0,E110*IF(G110=0,H110,MIN(H110,H110*(BB$3-D110+1)/MAX(1,G110)))*(1+F110)^(BB$3-D110)*$E93)
